Workbook

Sheet งบกำไรขาดทุน ปี 2025
B1: THONGLOR PET HOSPITAL COMPANY LIMITED
B2: บริษัท โรงพยาบาลสัตว์ทองหล่อ จำกัด
C4: Act ปี 2025 | Q4: %ต่อยอดขาย Act ปี 2025
C5: January | D5: February | E5: March | F5: April | G5: May | H5: June | I5: July | J5: August | K5: September | L5: October | M5: November | N5: December | O5: YTD | Q5: January | R5: February | S5: March | T5: April | U5: May | V5: June | W5: July | X5: August | Y5: September | Z5: October | AA5: November | AB5: December | AC5: YTD
B6: รายได้
B7: รายได้จากการขายและอื่นๆ
A8: 41100001 | B8: รายได้จากการขาย - OPD/IPD | O8: =SUM(C8:N8) -> 0 | Q8: =C8/C$18 -> #DIV/0! | R8: =D8/D$18 -> #DIV/0! | S8: =E8/E$18 -> #DIV/0! | T8: =F8/F$18 -> #DIV/0! | U8: =G8/G$18 -> #DIV/0! | V8: =H8/H$18 -> #DIV/0! | W8: =I8/I$18 -> #DIV/0! | X8: =J8/J$18 -> #DIV/0! | ... AC8: =O8/O$18 -> #DIV/0!
A9: 41200001 | B9: รายได้จากการขาย - Grooming | O9: =SUM(C9:N9) -> 0 | Q9: =C9/C$18 -> #DIV/0! | R9: =D9/D$18 -> #DIV/0! | S9: =E9/E$18 -> #DIV/0! | T9: =F9/F$18 -> #DIV/0! | U9: =G9/G$18 -> #DIV/0! | V9: =H9/H$18 -> #DIV/0! | W9: =I9/I$18 -> #DIV/0! | X9: =J9/J$18 -> #DIV/0! | ... AC9: =O9/O$18 -> #DIV/0!
A10: 41100002 | B10: รายได้จากการขาย - Petshop | O10: =SUM(C10:N10) -> 0 | Q10: =C10/C$18 -> #DIV/0! | R10: =D10/D$18 -> #DIV/0! | S10: =E10/E$18 -> #DIV/0! | T10: =F10/F$18 -> #DIV/0! | U10: =G10/G$18 -> #DIV/0! | V10: =H10/H$18 -> #DIV/0! | W10: =I10/I$18 -> #DIV/0! | X10: =J10/J$18 -> #DIV/0! | ... AC10: =O10/O$18 -> #DIV/0!
A11: 41200004 | B11: รายได้จากการขาย - Swimming | O11: =SUM(C11:N11) -> 0 | Q11: =C11/C$18 -> #DIV/0! | R11: =D11/D$18 -> #DIV/0! | S11: =E11/E$18 -> #DIV/0! | T11: =F11/F$18 -> #DIV/0! | U11: =G11/G$18 -> #DIV/0! | V11: =H11/H$18 -> #DIV/0! | W11: =I11/I$18 -> #DIV/0! | X11: =J11/J$18 -> #DIV/0! | ... AC11: =O11/O$18 -> #DIV/0!
A12: 41200002 | B12: รายได้จากการขาย - Pettaxi | O12: =SUM(C12:N12) -> 0 | Q12: =C12/C$18 -> #DIV/0! | R12: =D12/D$18 -> #DIV/0! | S12: =E12/E$18 -> #DIV/0! | T12: =F12/F$18 -> #DIV/0! | U12: =G12/G$18 -> #DIV/0! | V12: =H12/H$18 -> #DIV/0! | W12: =I12/I$18 -> #DIV/0! | X12: =J12/J$18 -> #DIV/0! | ... AC12: =O12/O$18 -> #DIV/0!
A13: 41200003 | B13: รายได้จากการขาย - อื่นๆ | O13: =SUM(C13:N13) -> 0 | Q13: =C13/C$18 -> #DIV/0! | R13: =D13/D$18 -> #DIV/0! | S13: =E13/E$18 -> #DIV/0! | T13: =F13/F$18 -> #DIV/0! | U13: =G13/G$18 -> #DIV/0! | V13: =H13/H$18 -> #DIV/0! | W13: =I13/I$18 -> #DIV/0! | X13: =J13/J$18 -> #DIV/0! | ... AC13: =O13/O$18 -> #DIV/0!
A14: 41300001 | B14: หัก รับคืน | O14: =SUM(C14:N14) -> 0 | Q14: =C14/C$18 -> #DIV/0! | R14: =D14/D$18 -> #DIV/0! | S14: =E14/E$18 -> #DIV/0! | T14: =F14/F$18 -> #DIV/0! | U14: =G14/G$18 -> #DIV/0! | V14: =H14/H$18 -> #DIV/0! | W14: =I14/I$18 -> #DIV/0! | X14: =J14/J$18 -> #DIV/0! | ... AC14: =O14/O$18 -> #DIV/0!
A15: 41300002 | B15: หัก ส่วนลดจ่าย | O15: =SUM(C15:N15) -> 0 | Q15: =C15/C$18 -> #DIV/0! | R15: =D15/D$18 -> #DIV/0! | S15: =E15/E$18 -> #DIV/0! | T15: =F15/F$18 -> #DIV/0! | U15: =G15/G$18 -> #DIV/0! | V15: =H15/H$18 -> #DIV/0! | W15: =I15/I$18 -> #DIV/0! | X15: =J15/J$18 -> #DIV/0! | ... AC15: =O15/O$18 -> #DIV/0!
A16: 42000001 | B16: รายได้อื่นๆ | O16: =SUM(C16:N16) -> 0 | Q16: =C16/C$18 -> #DIV/0! | R16: =D16/D$18 -> #DIV/0! | S16: =E16/E$18 -> #DIV/0! | T16: =F16/F$18 -> #DIV/0! | U16: =G16/G$18 -> #DIV/0! | V16: =H16/H$18 -> #DIV/0! | W16: =I16/I$18 -> #DIV/0! | X16: =J16/J$18 -> #DIV/0! | ... AC16: =O16/O$18 -> #DIV/0!
A17: 42000019 | B17: รายได้ Package/PR/ขนส่ง
B18: รวมรายได้จาการขายและอื่นๆ | O18: =SUM(C18:N18) -> 0 | Q18: =C18/C$18 -> #DIV/0! | R18: =D18/D$18 -> #DIV/0! | S18: =E18/E$18 -> #DIV/0! | T18: =F18/F$18 -> #DIV/0! | U18: =G18/G$18 -> #DIV/0! | V18: =H18/H$18 -> #DIV/0! | W18: =I18/I$18 -> #DIV/0! | X18: =J18/J$18 -> #DIV/0! | ... AC18: =O18/O$18 -> #DIV/0!
B19: ต้นทุนขายและค่าใช้จ่ายที่เกี่ยวข้อง | O19: =SUM(C19:N19) -> 0
B20: ต้นทุนขาย | O20: =SUM(C20:N20) -> 0
A21: 51000002 | B21: ต้นทุนขายสินค้า PH | O21: =SUM(C21:N21) -> 0 | Q21: =C21/C$18 -> #DIV/0! | R21: =D21/D$18 -> #DIV/0! | S21: =E21/E$18 -> #DIV/0! | T21: =F21/F$18 -> #DIV/0! | U21: =G21/G$18 -> #DIV/0! | V21: =H21/H$18 -> #DIV/0! | W21: =I21/I$18 -> #DIV/0! | X21: =J21/J$18 -> #DIV/0! | ... AC21: =O21/O$18 -> #DIV/0!
A22: 51000003 | B22: ต้นทุนขายสินค้า PC | O22: =SUM(C22:N22) -> 0 | Q22: =C22/C$18 -> #DIV/0! | R22: =D22/D$18 -> #DIV/0! | S22: =E22/E$18 -> #DIV/0! | T22: =F22/F$18 -> #DIV/0! | U22: =G22/G$18 -> #DIV/0! | V22: =H22/H$18 -> #DIV/0! | W22: =I22/I$18 -> #DIV/0! | X22: =J22/J$18 -> #DIV/0! | ... AC22: =O22/O$18 -> #DIV/0!
A23: 51000004 | B23: หัก ส่วนลดรับ | O23: =SUM(C23:N23) -> 0 | Q23: =C23/C$18 -> #DIV/0! | R23: =D23/D$18 -> #DIV/0! | S23: =E23/E$18 -> #DIV/0! | T23: =F23/F$18 -> #DIV/0! | U23: =G23/G$18 -> #DIV/0! | V23: =H23/H$18 -> #DIV/0! | W23: =I23/I$18 -> #DIV/0! | X23: =J23/J$18 -> #DIV/0! | ... AC23: =O23/O$18 -> #DIV/0!
A24: 51000001 | B24: รวมต้นทุนขาย | O24: =SUM(C24:N24) -> 0 | Q24: =C24/C$18 -> #DIV/0! | R24: =D24/D$18 -> #DIV/0! | S24: =E24/E$18 -> #DIV/0! | T24: =F24/F$18 -> #DIV/0! | U24: =G24/G$18 -> #DIV/0! | V24: =H24/H$18 -> #DIV/0! | W24: =I24/I$18 -> #DIV/0! | X24: =J24/J$18 -> #DIV/0! | ... AC24: =O24/O$18 -> #DIV/0!
B25: ค่าใช้จ่ายในการขาย | O25: =SUM(C25:N25) -> 0
A26: 52000017 | B26: ค่าใช้จ่ายในการขาย และค่าธรรมเนียม | O26: =SUM(C26:N26) -> 0 | Q26: =C26/C$18 -> #DIV/0! | R26: =D26/D$18 -> #DIV/0! | S26: =E26/E$18 -> #DIV/0! | T26: =F26/F$18 -> #DIV/0! | U26: =G26/G$18 -> #DIV/0! | V26: =H26/H$18 -> #DIV/0! | W26: =I26/I$18 -> #DIV/0! | X26: =J26/J$18 -> #DIV/0! | ... AC26: =O26/O$18 -> #DIV/0!
A27: 52000001 | B27: ค่าส่งเสริมการขาย | O27: =SUM(C27:N27) -> 0 | Q27: =C27/C$18 -> #DIV/0! | R27: =D27/D$18 -> #DIV/0! | S27: =E27/E$18 -> #DIV/0! | T27: =F27/F$18 -> #DIV/0! | U27: =G27/G$18 -> #DIV/0! | V27: =H27/H$18 -> #DIV/0! | W27: =I27/I$18 -> #DIV/0! | X27: =J27/J$18 -> #DIV/0! | ... AC27: =O27/O$18 -> #DIV/0!
A28: 52000003 | B28: ค่าชันสูตรโรค | O28: =SUM(C28:N28) -> 0 | Q28: =C28/C$18 -> #DIV/0! | R28: =D28/D$18 -> #DIV/0! | S28: =E28/E$18 -> #DIV/0! | T28: =F28/F$18 -> #DIV/0! | U28: =G28/G$18 -> #DIV/0! | V28: =H28/H$18 -> #DIV/0! | W28: =I28/I$18 -> #DIV/0! | X28: =J28/J$18 -> #DIV/0! | ... AC28: =O28/O$18 -> #DIV/0!
A29: 52000004 | B29: ค่าส่งเผา | O29: =SUM(C29:N29) -> 0 | Q29: =C29/C$18 -> #DIV/0! | R29: =D29/D$18 -> #DIV/0! | S29: =E29/E$18 -> #DIV/0! | T29: =F29/F$18 -> #DIV/0! | U29: =G29/G$18 -> #DIV/0! | V29: =H29/H$18 -> #DIV/0! | W29: =I29/I$18 -> #DIV/0! | X29: =J29/J$18 -> #DIV/0! | ... AC29: =O29/O$18 -> #DIV/0!
A30: 52000005 | B30: ค่าตรวจเลือด | O30: =SUM(C30:N30) -> 0 | Q30: =C30/C$18 -> #DIV/0! | R30: =D30/D$18 -> #DIV/0! | S30: =E30/E$18 -> #DIV/0! | T30: =F30/F$18 -> #DIV/0! | U30: =G30/G$18 -> #DIV/0! | V30: =H30/H$18 -> #DIV/0! | W30: =I30/I$18 -> #DIV/0! | X30: =J30/J$18 -> #DIV/0! | ... AC30: =O30/O$18 -> #DIV/0!
A31: 52000006 | B31: ค่าตรวจเลือดภายใน | O31: =SUM(C31:N31) -> 0 | Q31: =C31/C$18 -> #DIV/0! | R31: =D31/D$18 -> #DIV/0! | S31: =E31/E$18 -> #DIV/0! | T31: =F31/F$18 -> #DIV/0! | U31: =G31/G$18 -> #DIV/0! | V31: =H31/H$18 -> #DIV/0! | W31: =I31/I$18 -> #DIV/0! | X31: =J31/J$18 -> #DIV/0! | ... AC31: =O31/O$18 -> #DIV/0!
A32: 52000007 | B32: ค่าเช่าเครื่องมือภายใน | O32: =SUM(C32:N32) -> 0 | Q32: =C32/C$18 -> #DIV/0! | R32: =D32/D$18 -> #DIV/0! | S32: =E32/E$18 -> #DIV/0! | T32: =F32/F$18 -> #DIV/0! | U32: =G32/G$18 -> #DIV/0! | V32: =H32/H$18 -> #DIV/0! | W32: =I32/I$18 -> #DIV/0! | X32: =J32/J$18 -> #DIV/0! | ... AC32: =O32/O$18 -> #DIV/0!
A33: 52000008 | B33: ค่าบริการวิชาชีพแพทย์ | O33: =SUM(C33:N33) -> 0 | Q33: =C33/C$18 -> #DIV/0! | R33: =D33/D$18 -> #DIV/0! | S33: =E33/E$18 -> #DIV/0! | T33: =F33/F$18 -> #DIV/0! | U33: =G33/G$18 -> #DIV/0! | V33: =H33/H$18 -> #DIV/0! | W33: =I33/I$18 -> #DIV/0! | X33: =J33/J$18 -> #DIV/0! | ... AC33: =O33/O$18 -> #DIV/0!
A34: 52000010 | B34: ค่าเช่าเครื่องมือแพทย์ | O34: =SUM(C34:N34) -> 0 | Q34: =C34/C$18 -> #DIV/0! | R34: =D34/D$18 -> #DIV/0! | S34: =E34/E$18 -> #DIV/0! | T34: =F34/F$18 -> #DIV/0! | U34: =G34/G$18 -> #DIV/0! | V34: =H34/H$18 -> #DIV/0! | W34: =I34/I$18 -> #DIV/0! | X34: =J34/J$18 -> #DIV/0! | ... AC34: =O34/O$18 -> #DIV/0!
A35: 52000011 | B35: ค่าวัสดุเครื่องมือแพทย์ | O35: =SUM(C35:N35) -> 0 | Q35: =C35/C$18 -> #DIV/0! | R35: =D35/D$18 -> #DIV/0! | S35: =E35/E$18 -> #DIV/0! | T35: =F35/F$18 -> #DIV/0! | U35: =G35/G$18 -> #DIV/0! | V35: =H35/H$18 -> #DIV/0! | W35: =I35/I$18 -> #DIV/0! | X35: =J35/J$18 -> #DIV/0! | ... AC35: =O35/O$18 -> #DIV/0!
A36: 52000014 | B36: ค่าเช่าอุปกรณ์-เครื่องมือระหว่างสาขา | O36: =SUM(C36:N36) -> 0 | Q36: =C36/C$18 -> #DIV/0! | R36: =D36/D$18 -> #DIV/0! | S36: =E36/E$18 -> #DIV/0! | T36: =F36/F$18 -> #DIV/0! | U36: =G36/G$18 -> #DIV/0! | V36: =H36/H$18 -> #DIV/0! | W36: =I36/I$18 -> #DIV/0! | X36: =J36/J$18 -> #DIV/0! | ... AC36: =O36/O$18 -> #DIV/0!
A37: 61300010 | B37: ค่าเสื่อมราคา - เครื่องมือแพทย์ | O37: =SUM(C37:N37) -> 0 | Q37: =C37/C$18 -> #DIV/0! | R37: =D37/D$18 -> #DIV/0! | S37: =E37/E$18 -> #DIV/0! | T37: =F37/F$18 -> #DIV/0! | U37: =G37/G$18 -> #DIV/0! | V37: =H37/H$18 -> #DIV/0! | W37: =I37/I$18 -> #DIV/0! | X37: =J37/J$18 -> #DIV/0! | ... AC37: =O37/O$18 -> #DIV/0!
B38: รวมค่าใช้จ่ายในการขาย | O38: =SUM(C38:N38) -> 0 | Q38: =C38/C$18 -> #DIV/0! | R38: =D38/D$18 -> #DIV/0! | S38: =E38/E$18 -> #DIV/0! | T38: =F38/F$18 -> #DIV/0! | U38: =G38/G$18 -> #DIV/0! | V38: =H38/H$18 -> #DIV/0! | W38: =I38/I$18 -> #DIV/0! | X38: =J38/J$18 -> #DIV/0! | ... AC38: =O38/O$18 -> #DIV/0!
B39: ค่ายานพาหนะ | O39: =SUM(C39:N39) -> 0
A40: 52000015 | B40: ค่าขนส่งในประเทศ | O40: =SUM(C40:N40) -> 0 | Q40: =C40/C$18 -> #DIV/0! | R40: =D40/D$18 -> #DIV/0! | S40: =E40/E$18 -> #DIV/0! | T40: =F40/F$18 -> #DIV/0! | U40: =G40/G$18 -> #DIV/0! | V40: =H40/H$18 -> #DIV/0! | W40: =I40/I$18 -> #DIV/0! | X40: =J40/J$18 -> #DIV/0! | ... AC40: =O40/O$18 -> #DIV/0!
B41: รวมค่ายานพาหนะ | O41: =SUM(C41:N41) -> 0 | Q41: =C41/C$18 -> #DIV/0! | R41: =D41/D$18 -> #DIV/0! | S41: =E41/E$18 -> #DIV/0! | T41: =F41/F$18 -> #DIV/0! | U41: =G41/G$18 -> #DIV/0! | V41: =H41/H$18 -> #DIV/0! | W41: =I41/I$18 -> #DIV/0! | X41: =J41/J$18 -> #DIV/0! | ... AC41: =O41/O$18 -> #DIV/0!
B42: รวมต้นทุนขายและค่าใช้จ่ายในการขาย | O42: =SUM(C42:N42) -> 0 | Q42: =C42/C$18 -> #DIV/0! | R42: =D42/D$18 -> #DIV/0! | S42: =E42/E$18 -> #DIV/0! | T42: =F42/F$18 -> #DIV/0! | U42: =G42/G$18 -> #DIV/0! | V42: =H42/H$18 -> #DIV/0! | W42: =I42/I$18 -> #DIV/0! | X42: =J42/J$18 -> #DIV/0! | ... AC42: =O42/O$18 -> #DIV/0!
B43: ค่าใช้จ่ายในการบริหาร | O43: =SUM(C43:N43) -> 0
B44: เงินเดือนและสวัสดิการพนักงาน | O44: =SUM(C44:N44) -> 0
A45: 60100001 | B45: เงินเดือน | O45: =SUM(C45:N45) -> 0 | Q45: =C45/C$18 -> #DIV/0! | R45: =D45/D$18 -> #DIV/0! | S45: =E45/E$18 -> #DIV/0! | T45: =F45/F$18 -> #DIV/0! | U45: =G45/G$18 -> #DIV/0! | V45: =H45/H$18 -> #DIV/0! | W45: =I45/I$18 -> #DIV/0! | X45: =J45/J$18 -> #DIV/0! | ... AC45: =O45/O$18 -> #DIV/0!
A46: 52000009 | B46: ค่าหัวหน้าฝ่ายวิชาการแพทย์ | O46: =SUM(C46:N46) -> 0 | Q46: =C46/C$18 -> #DIV/0! | R46: =D46/D$18 -> #DIV/0! | S46: =E46/E$18 -> #DIV/0! | T46: =F46/F$18 -> #DIV/0! | U46: =G46/G$18 -> #DIV/0! | V46: =H46/H$18 -> #DIV/0! | W46: =I46/I$18 -> #DIV/0! | X46: =J46/J$18 -> #DIV/0! | ... AC46: =O46/O$18 -> #DIV/0!
A47: 52000012 | B47: เงินเดือนพยาบาล | O47: =SUM(C47:N47) -> 0 | Q47: =C47/C$18 -> #DIV/0! | R47: =D47/D$18 -> #DIV/0! | S47: =E47/E$18 -> #DIV/0! | T47: =F47/F$18 -> #DIV/0! | U47: =G47/G$18 -> #DIV/0! | V47: =H47/H$18 -> #DIV/0! | W47: =I47/I$18 -> #DIV/0! | X47: =J47/J$18 -> #DIV/0! | ... AC47: =O47/O$18 -> #DIV/0!
A48: 52000013 | B48: ค่าพยาบาลพิเศษ | O48: =SUM(C48:N48) -> 0 | Q48: =C48/C$18 -> #DIV/0! | R48: =D48/D$18 -> #DIV/0! | S48: =E48/E$18 -> #DIV/0! | T48: =F48/F$18 -> #DIV/0! | U48: =G48/G$18 -> #DIV/0! | V48: =H48/H$18 -> #DIV/0! | W48: =I48/I$18 -> #DIV/0! | X48: =J48/J$18 -> #DIV/0! | ... AC48: =O48/O$18 -> #DIV/0!
A49: 52000016 | B49: ค่าเช่ายานพาหนะ | O49: =SUM(C49:N49) -> 0 | Q49: =C49/C$18 -> #DIV/0! | R49: =D49/D$18 -> #DIV/0! | S49: =E49/E$18 -> #DIV/0! | T49: =F49/F$18 -> #DIV/0! | U49: =G49/G$18 -> #DIV/0! | V49: =H49/H$18 -> #DIV/0! | W49: =I49/I$18 -> #DIV/0! | X49: =J49/J$18 -> #DIV/0! | ... AC49: =O49/O$18 -> #DIV/0!
A50: 60100002 | B50: ค่าวัดระดับ | O50: =SUM(C50:N50) -> 0 | Q50: =C50/C$18 -> #DIV/0! | R50: =D50/D$18 -> #DIV/0! | S50: =E50/E$18 -> #DIV/0! | T50: =F50/F$18 -> #DIV/0! | U50: =G50/G$18 -> #DIV/0! | V50: =H50/H$18 -> #DIV/0! | W50: =I50/I$18 -> #DIV/0! | X50: =J50/J$18 -> #DIV/0! | ... AC50: =O50/O$18 -> #DIV/0!
A51: 60100003 | B51: ค่าล่วงเวลา | O51: =SUM(C51:N51) -> 0 | Q51: =C51/C$18 -> #DIV/0! | R51: =D51/D$18 -> #DIV/0! | S51: =E51/E$18 -> #DIV/0! | T51: =F51/F$18 -> #DIV/0! | U51: =G51/G$18 -> #DIV/0! | V51: =H51/H$18 -> #DIV/0! | W51: =I51/I$18 -> #DIV/0! | X51: =J51/J$18 -> #DIV/0! | ... AC51: =O51/O$18 -> #DIV/0!
A52: 60100004 | B52: โบนัส | O52: =SUM(C52:N52) -> 0 | Q52: =C52/C$18 -> #DIV/0! | R52: =D52/D$18 -> #DIV/0! | S52: =E52/E$18 -> #DIV/0! | T52: =F52/F$18 -> #DIV/0! | U52: =G52/G$18 -> #DIV/0! | V52: =H52/H$18 -> #DIV/0! | W52: =I52/I$18 -> #DIV/0! | X52: =J52/J$18 -> #DIV/0! | ... AC52: =O52/O$18 -> #DIV/0!
A53: 60100005 | B53: เงินกองทุนสำรองเลี้ยงชีพ | O53: =SUM(C53:N53) -> 0 | Q53: =C53/C$18 -> #DIV/0! | R53: =D53/D$18 -> #DIV/0! | S53: =E53/E$18 -> #DIV/0! | T53: =F53/F$18 -> #DIV/0! | U53: =G53/G$18 -> #DIV/0! | V53: =H53/H$18 -> #DIV/0! | W53: =I53/I$18 -> #DIV/0! | X53: =J53/J$18 -> #DIV/0! | ... AC53: =O53/O$18 -> #DIV/0!
A54: 60100007 | B54: ค่าสวัสดิการพนักงาน | O54: =SUM(C54:N54) -> 0 | Q54: =C54/C$18 -> #DIV/0! | R54: =D54/D$18 -> #DIV/0! | S54: =E54/E$18 -> #DIV/0! | T54: =F54/F$18 -> #DIV/0! | U54: =G54/G$18 -> #DIV/0! | V54: =H54/H$18 -> #DIV/0! | W54: =I54/I$18 -> #DIV/0! | X54: =J54/J$18 -> #DIV/0! | ... AC54: =O54/O$18 -> #DIV/0!
A55: 60100008 | B55: เงินกองทุนประกันสังคม | O55: =SUM(C55:N55) -> 0 | Q55: =C55/C$18 -> #DIV/0! | R55: =D55/D$18 -> #DIV/0! | S55: =E55/E$18 -> #DIV/0! | T55: =F55/F$18 -> #DIV/0! | U55: =G55/G$18 -> #DIV/0! | V55: =H55/H$18 -> #DIV/0! | W55: =I55/I$18 -> #DIV/0! | X55: =J55/J$18 -> #DIV/0! | ... AC55: =O55/O$18 -> #DIV/0!
A56: 60100009 | B56: ค่าเบี้ยประกันชีวิตพนักงาน | O56: =SUM(C56:N56) -> 0 | Q56: =C56/C$18 -> #DIV/0! | R56: =D56/D$18 -> #DIV/0! | S56: =E56/E$18 -> #DIV/0! | T56: =F56/F$18 -> #DIV/0! | U56: =G56/G$18 -> #DIV/0! | V56: =H56/H$18 -> #DIV/0! | W56: =I56/I$18 -> #DIV/0! | X56: =J56/J$18 -> #DIV/0! | ... AC56: =O56/O$18 -> #DIV/0!
... A62: 60100015 | B62: ต้นทุนบริการผลประโยชน์พนักงาน | O62: =SUM(C62:N62) -> 0 | Q62: =C62/C$18 -> #DIV/0! | R62: =D62/D$18 -> #DIV/0! | S62: =E62/E$18 -> #DIV/0! | T62: =F62/F$18 -> #DIV/0! | U62: =G62/G$18 -> #DIV/0! | V62: =H62/H$18 -> #DIV/0! | W62: =I62/I$18 -> #DIV/0! | X62: =J62/J$18 -> #DIV/0! | ... AC62: =O62/O$18 -> #DIV/0!
B63: รวมเงินเดือนและสวัสดิการพนักงาน | O63: =SUM(C63:N63) -> 0 | Q63: =C63/C$18 -> #DIV/0! | R63: =D63/D$18 -> #DIV/0! | S63: =E63/E$18 -> #DIV/0! | T63: =F63/F$18 -> #DIV/0! | U63: =G63/G$18 -> #DIV/0! | V63: =H63/H$18 -> #DIV/0! | W63: =I63/I$18 -> #DIV/0! | X63: =J63/J$18 -> #DIV/0! | ... AC63: =O63/O$18 -> #DIV/0!
B64: ค่าอบรมสัมมนา | O64: =SUM(C64:N64) -> 0
A65: 60100017 | B65: ค่าอบรม&สัมมนาพนักงาน | O65: =SUM(C65:N65) -> 0 | Q65: =C65/C$18 -> #DIV/0! | R65: =D65/D$18 -> #DIV/0! | S65: =E65/E$18 -> #DIV/0! | T65: =F65/F$18 -> #DIV/0! | U65: =G65/G$18 -> #DIV/0! | V65: =H65/H$18 -> #DIV/0! | W65: =I65/I$18 -> #DIV/0! | X65: =J65/J$18 -> #DIV/0! | ... AC65: =O65/O$18 -> #DIV/0!
A66: 60100018 | B66: ค่าอบรม&สัมมนาหมอ | O66: =SUM(C66:N66) -> 0 | Q66: =C66/C$18 -> #DIV/0! | R66: =D66/D$18 -> #DIV/0! | S66: =E66/E$18 -> #DIV/0! | T66: =F66/F$18 -> #DIV/0! | U66: =G66/G$18 -> #DIV/0! | V66: =H66/H$18 -> #DIV/0! | W66: =I66/I$18 -> #DIV/0! | X66: =J66/J$18 -> #DIV/0! | ... AC66: =O66/O$18 -> #DIV/0!
A67: 60100019 | B67: ค่าอบรมISO | O67: =SUM(C67:N67) -> 0 | Q67: =C67/C$18 -> #DIV/0! | R67: =D67/D$18 -> #DIV/0! | S67: =E67/E$18 -> #DIV/0! | T67: =F67/F$18 -> #DIV/0! | U67: =G67/G$18 -> #DIV/0! | V67: =H67/H$18 -> #DIV/0! | W67: =I67/I$18 -> #DIV/0! | X67: =J67/J$18 -> #DIV/0! | ... AC67: =O67/O$18 -> #DIV/0!
B68: รวมค่าอบรมสัมมนา | O68: =SUM(C68:N68) -> 0 | Q68: =C68/C$18 -> #DIV/0! | R68: =D68/D$18 -> #DIV/0! | S68: =E68/E$18 -> #DIV/0! | T68: =F68/F$18 -> #DIV/0! | U68: =G68/G$18 -> #DIV/0! | V68: =H68/H$18 -> #DIV/0! | W68: =I68/I$18 -> #DIV/0! | X68: =J68/J$18 -> #DIV/0! | ... AC68: =O68/O$18 -> #DIV/0!
B69: Professional Fees | O69: =SUM(C69:N69) -> 0
A70: 60200004 | B70: ค่าสอบบัญชี | O70: =SUM(C70:N70) -> 0 | Q70: =C70/C$18 -> #DIV/0! | R70: =D70/D$18 -> #DIV/0! | S70: =E70/E$18 -> #DIV/0! | T70: =F70/F$18 -> #DIV/0! | U70: =G70/G$18 -> #DIV/0! | V70: =H70/H$18 -> #DIV/0! | W70: =I70/I$18 -> #DIV/0! | X70: =J70/J$18 -> #DIV/0! | ... AC70: =O70/O$18 -> #DIV/0!
A71: 60100020 | B71: ค่าที่ปรึกษา | O71: =SUM(C71:N71) -> 0 | Q71: =C71/C$18 -> #DIV/0! | R71: =D71/D$18 -> #DIV/0! | S71: =E71/E$18 -> #DIV/0! | T71: =F71/F$18 -> #DIV/0! | U71: =G71/G$18 -> #DIV/0! | V71: =H71/H$18 -> #DIV/0! | W71: =I71/I$18 -> #DIV/0! | X71: =J71/J$18 -> #DIV/0! | ... AC71: =O71/O$18 -> #DIV/0!
A72: 60100021 | B72: ค่าที่ปรึกษากฎหมาย | O72: =SUM(C72:N72) -> 0 | Q72: =C72/C$18 -> #DIV/0! | R72: =D72/D$18 -> #DIV/0! | S72: =E72/E$18 -> #DIV/0! | T72: =F72/F$18 -> #DIV/0! | U72: =G72/G$18 -> #DIV/0! | V72: =H72/H$18 -> #DIV/0! | W72: =I72/I$18 -> #DIV/0! | X72: =J72/J$18 -> #DIV/0! | ... AC72: =O72/O$18 -> #DIV/0!
A73: 60100022 | B73: เงินเดือนล่าม | O73: =SUM(C73:N73) -> 0 | Q73: =C73/C$18 -> #DIV/0! | R73: =D73/D$18 -> #DIV/0! | S73: =E73/E$18 -> #DIV/0! | T73: =F73/F$18 -> #DIV/0! | U73: =G73/G$18 -> #DIV/0! | V73: =H73/H$18 -> #DIV/0! | W73: =I73/I$18 -> #DIV/0! | X73: =J73/J$18 -> #DIV/0! | ... AC73: =O73/O$18 -> #DIV/0!
B74: รวม Professional Fees | O74: =SUM(C74:N74) -> 0 | Q74: =C74/C$18 -> #DIV/0! | R74: =D74/D$18 -> #DIV/0! | S74: =E74/E$18 -> #DIV/0! | T74: =F74/F$18 -> #DIV/0! | U74: =G74/G$18 -> #DIV/0! | V74: =H74/H$18 -> #DIV/0! | W74: =I74/I$18 -> #DIV/0! | X74: =J74/J$18 -> #DIV/0! | ... AC74: =O74/O$18 -> #DIV/0!
B75: ค่าธรรมเนียม | O75: =SUM(C75:N75) -> 0
A76: 60200001 | B76: ค่าบริการสอบเทียบ | O76: =SUM(C76:N76) -> 0 | Q76: =C76/C$18 -> #DIV/0! | R76: =D76/D$18 -> #DIV/0! | S76: =E76/E$18 -> #DIV/0! | T76: =F76/F$18 -> #DIV/0! | U76: =G76/G$18 -> #DIV/0! | V76: =H76/H$18 -> #DIV/0! | W76: =I76/I$18 -> #DIV/0! | X76: =J76/J$18 -> #DIV/0! | ... AC76: =O76/O$18 -> #DIV/0!
A77: 60200003 | B77: ค่าธรรมเนียมอื่นๆ | O77: =SUM(C77:N77) -> 0 | Q77: =C77/C$18 -> #DIV/0! | R77: =D77/D$18 -> #DIV/0! | S77: =E77/E$18 -> #DIV/0! | T77: =F77/F$18 -> #DIV/0! | U77: =G77/G$18 -> #DIV/0! | V77: =H77/H$18 -> #DIV/0! | W77: =I77/I$18 -> #DIV/0! | X77: =J77/J$18 -> #DIV/0! | ... AC77: =O77/O$18 -> #DIV/0!
A78: 60200002 | B78: ค่าธรรมเนียมธนาคาร | O78: =SUM(C78:N78) -> 0 | Q78: =C78/C$18 -> #DIV/0! | R78: =D78/D$18 -> #DIV/0! | S78: =E78/E$18 -> #DIV/0! | T78: =F78/F$18 -> #DIV/0! | U78: =G78/G$18 -> #DIV/0! | V78: =H78/H$18 -> #DIV/0! | W78: =I78/I$18 -> #DIV/0! | X78: =J78/J$18 -> #DIV/0! | ... AC78: =O78/O$18 -> #DIV/0!
B79: รวมค่าธรรมเนียม | O79: =SUM(C79:N79) -> 0 | Q79: =C79/C$18 -> #DIV/0! | R79: =D79/D$18 -> #DIV/0! | S79: =E79/E$18 -> #DIV/0! | T79: =F79/F$18 -> #DIV/0! | U79: =G79/G$18 -> #DIV/0! | V79: =H79/H$18 -> #DIV/0! | W79: =I79/I$18 -> #DIV/0! | X79: =J79/J$18 -> #DIV/0! | ... AC79: =O79/O$18 -> #DIV/0!
B80: วัสดุสิ้นเปลือง | O80: =SUM(C80:N80) -> 0
A81: 60300001 | B81: ค่าเครื่องเขียนแบบพิมพ์ | O81: =SUM(C81:N81) -> 0 | Q81: =C81/C$18 -> #DIV/0! | R81: =D81/D$18 -> #DIV/0! | S81: =E81/E$18 -> #DIV/0! | T81: =F81/F$18 -> #DIV/0! | U81: =G81/G$18 -> #DIV/0! | V81: =H81/H$18 -> #DIV/0! | W81: =I81/I$18 -> #DIV/0! | X81: =J81/J$18 -> #DIV/0! | ... AC81: =O81/O$18 -> #DIV/0!
A82: 60300002 | B82: ค่าอุปกรณ์สำนักงาน-ของใช้สิ้นเปลือง | O82: =SUM(C82:N82) -> 0 | Q82: =C82/C$18 -> #DIV/0! | R82: =D82/D$18 -> #DIV/0! | S82: =E82/E$18 -> #DIV/0! | T82: =F82/F$18 -> #DIV/0! | U82: =G82/G$18 -> #DIV/0! | V82: =H82/H$18 -> #DIV/0! | W82: =I82/I$18 -> #DIV/0! | X82: =J82/J$18 -> #DIV/0! | ... AC82: =O82/O$18 -> #DIV/0!
A83: 60300005 | B83: ค่าเช่าเครื่องถ่ายเอกสาร | O83: =SUM(C83:N83) -> 0 | Q83: =C83/C$18 -> #DIV/0! | R83: =D83/D$18 -> #DIV/0! | S83: =E83/E$18 -> #DIV/0! | T83: =F83/F$18 -> #DIV/0! | U83: =G83/G$18 -> #DIV/0! | V83: =H83/H$18 -> #DIV/0! | W83: =I83/I$18 -> #DIV/0! | X83: =J83/J$18 -> #DIV/0! | ... AC83: =O83/O$18 -> #DIV/0!
B84: รวมวัสดุสิ้นเปลือง | O84: =SUM(C84:N84) -> 0 | Q84: =C84/C$18 -> #DIV/0! | R84: =D84/D$18 -> #DIV/0! | S84: =E84/E$18 -> #DIV/0! | T84: =F84/F$18 -> #DIV/0! | U84: =G84/G$18 -> #DIV/0! | V84: =H84/H$18 -> #DIV/0! | W84: =I84/I$18 -> #DIV/0! | X84: =J84/J$18 -> #DIV/0! | ... AC84: =O84/O$18 -> #DIV/0!
B85: ค่่าโฆษณาและส่งเสริมการขาย | O85: =SUM(C85:N85) -> 0
A86: 60400001 | B86: ค่าโฆษณา | O86: =SUM(C86:N86) -> 0 | Q86: =C86/C$18 -> #DIV/0! | R86: =D86/D$18 -> #DIV/0! | S86: =E86/E$18 -> #DIV/0! | T86: =F86/F$18 -> #DIV/0! | U86: =G86/G$18 -> #DIV/0! | V86: =H86/H$18 -> #DIV/0! | W86: =I86/I$18 -> #DIV/0! | X86: =J86/J$18 -> #DIV/0! | ... AC86: =O86/O$18 -> #DIV/0!
A87: 60400003 | B87: ค่าโฆษณาหาคน | O87: =SUM(C87:N87) -> 0 | Q87: =C87/C$18 -> #DIV/0! | R87: =D87/D$18 -> #DIV/0! | S87: =E87/E$18 -> #DIV/0! | T87: =F87/F$18 -> #DIV/0! | U87: =G87/G$18 -> #DIV/0! | V87: =H87/H$18 -> #DIV/0! | W87: =I87/I$18 -> #DIV/0! | X87: =J87/J$18 -> #DIV/0! | ... AC87: =O87/O$18 -> #DIV/0!
A88: 60400002 | B88: ค่า CRM | O88: =SUM(C88:N88) -> 0 | Q88: =C88/C$18 -> #DIV/0! | R88: =D88/D$18 -> #DIV/0! | S88: =E88/E$18 -> #DIV/0! | T88: =F88/F$18 -> #DIV/0! | U88: =G88/G$18 -> #DIV/0! | V88: =H88/H$18 -> #DIV/0! | W88: =I88/I$18 -> #DIV/0! | X88: =J88/J$18 -> #DIV/0! | ... AC88: =O88/O$18 -> #DIV/0!
B89: รวมค่าโฆษณาและส่งเสริมการขาย | O89: =SUM(C89:N89) -> 0 | Q89: =C89/C$18 -> #DIV/0! | R89: =D89/D$18 -> #DIV/0! | S89: =E89/E$18 -> #DIV/0! | T89: =F89/F$18 -> #DIV/0! | U89: =G89/G$18 -> #DIV/0! | V89: =H89/H$18 -> #DIV/0! | W89: =I89/I$18 -> #DIV/0! | X89: =J89/J$18 -> #DIV/0! | ... AC89: =O89/O$18 -> #DIV/0!
B90: ค่าซ่อมแซมและบำรุงรักษา | O90: =SUM(C90:N90) -> 0
A91: 60600001 | B91: ค่าซ่อมแซมคอมพิวเตอร์ | O91: =SUM(C91:N91) -> 0 | Q91: =C91/C$18 -> #DIV/0! | R91: =D91/D$18 -> #DIV/0! | S91: =E91/E$18 -> #DIV/0! | T91: =F91/F$18 -> #DIV/0! | U91: =G91/G$18 -> #DIV/0! | V91: =H91/H$18 -> #DIV/0! | W91: =I91/I$18 -> #DIV/0! | X91: =J91/J$18 -> #DIV/0! | ... AC91: =O91/O$18 -> #DIV/0!
A92: 60600002 | B92: ค่าซ่อมแซมเครื่องใช้สำนักงาน | O92: =SUM(C92:N92) -> 0 | Q92: =C92/C$18 -> #DIV/0! | R92: =D92/D$18 -> #DIV/0! | S92: =E92/E$18 -> #DIV/0! | T92: =F92/F$18 -> #DIV/0! | U92: =G92/G$18 -> #DIV/0! | V92: =H92/H$18 -> #DIV/0! | W92: =I92/I$18 -> #DIV/0! | X92: =J92/J$18 -> #DIV/0! | ... AC92: =O92/O$18 -> #DIV/0!
A93: 60600003 | B93: ค่าซ่อมแซมเครื่องตกแต่งและติดตั้ง | O93: =SUM(C93:N93) -> 0 | Q93: =C93/C$18 -> #DIV/0! | R93: =D93/D$18 -> #DIV/0! | S93: =E93/E$18 -> #DIV/0! | T93: =F93/F$18 -> #DIV/0! | U93: =G93/G$18 -> #DIV/0! | V93: =H93/H$18 -> #DIV/0! | W93: =I93/I$18 -> #DIV/0! | X93: =J93/J$18 -> #DIV/0! | ... AC93: =O93/O$18 -> #DIV/0!
A94: 60600004 | B94: ค่าซ่อมแซมยานพาหนะ | O94: =SUM(C94:N94) -> 0 | Q94: =C94/C$18 -> #DIV/0! | R94: =D94/D$18 -> #DIV/0! | S94: =E94/E$18 -> #DIV/0! | T94: =F94/F$18 -> #DIV/0! | U94: =G94/G$18 -> #DIV/0! | V94: =H94/H$18 -> #DIV/0! | W94: =I94/I$18 -> #DIV/0! | X94: =J94/J$18 -> #DIV/0! | ... AC94: =O94/O$18 -> #DIV/0!
A95: 60600005 | B95: ค่าซ่อมแซมเครื่องมือแพทย์ | O95: =SUM(C95:N95) -> 0 | Q95: =C95/C$18 -> #DIV/0! | R95: =D95/D$18 -> #DIV/0! | S95: =E95/E$18 -> #DIV/0! | T95: =F95/F$18 -> #DIV/0! | U95: =G95/G$18 -> #DIV/0! | V95: =H95/H$18 -> #DIV/0! | W95: =I95/I$18 -> #DIV/0! | X95: =J95/J$18 -> #DIV/0! | ... AC95: =O95/O$18 -> #DIV/0!
A96: 60600006 | B96: ค่าบำรุงรักษาโปรแกรม | O96: =SUM(C96:N96) -> 0 | Q96: =C96/C$18 -> #DIV/0! | R96: =D96/D$18 -> #DIV/0! | S96: =E96/E$18 -> #DIV/0! | T96: =F96/F$18 -> #DIV/0! | U96: =G96/G$18 -> #DIV/0! | V96: =H96/H$18 -> #DIV/0! | W96: =I96/I$18 -> #DIV/0! | X96: =J96/J$18 -> #DIV/0! | ... AC96: =O96/O$18 -> #DIV/0!
A97: 60600007 | B97: ค่าบำรุงรักษาเครื่องใช้สำนักงาน | O97: =SUM(C97:N97) -> 0 | Q97: =C97/C$18 -> #DIV/0! | R97: =D97/D$18 -> #DIV/0! | S97: =E97/E$18 -> #DIV/0! | T97: =F97/F$18 -> #DIV/0! | U97: =G97/G$18 -> #DIV/0! | V97: =H97/H$18 -> #DIV/0! | W97: =I97/I$18 -> #DIV/0! | X97: =J97/J$18 -> #DIV/0! | ... AC97: =O97/O$18 -> #DIV/0!
B98: รวมค่าซ่อมแซมและค่าบำรุงรักษา | O98: =SUM(C98:N98) -> 0 | Q98: =C98/C$18 -> #DIV/0! | R98: =D98/D$18 -> #DIV/0! | S98: =E98/E$18 -> #DIV/0! | T98: =F98/F$18 -> #DIV/0! | U98: =G98/G$18 -> #DIV/0! | V98: =H98/H$18 -> #DIV/0! | W98: =I98/I$18 -> #DIV/0! | X98: =J98/J$18 -> #DIV/0! | ... AC98: =O98/O$18 -> #DIV/0!
B99: ค่าสาธารณูปโภค | O99: =SUM(C99:N99) -> 0
A100: 60700001 | B100: ค่าโทรศัพท์ | O100: =SUM(C100:N100) -> 0 | Q100: =C100/C$18 -> #DIV/0! | R100: =D100/D$18 -> #DIV/0! | S100: =E100/E$18 -> #DIV/0! | T100: =F100/F$18 -> #DIV/0! | U100: =G100/G$18 -> #DIV/0! | V100: =H100/H$18 -> #DIV/0! | W100: =I100/I$18 -> #DIV/0! | X100: =J100/J$18 -> #DIV/0! | ... AC100: =O100/O$18 -> #DIV/0!
A101: 60700002 | B101: ค่าน้ำประปา | O101: =SUM(C101:N101) -> 0 | Q101: =C101/C$18 -> #DIV/0! | R101: =D101/D$18 -> #DIV/0! | S101: =E101/E$18 -> #DIV/0! | T101: =F101/F$18 -> #DIV/0! | U101: =G101/G$18 -> #DIV/0! | V101: =H101/H$18 -> #DIV/0! | W101: =I101/I$18 -> #DIV/0! | X101: =J101/J$18 -> #DIV/0! | ... AC101: =O101/O$18 -> #DIV/0!
A102: 60700003 | B102: ค่าไฟฟ้า | O102: =SUM(C102:N102) -> 0 | Q102: =C102/C$18 -> #DIV/0! | R102: =D102/D$18 -> #DIV/0! | S102: =E102/E$18 -> #DIV/0! | T102: =F102/F$18 -> #DIV/0! | U102: =G102/G$18 -> #DIV/0! | V102: =H102/H$18 -> #DIV/0! | W102: =I102/I$18 -> #DIV/0! | X102: =J102/J$18 -> #DIV/0! | ... AC102: =O102/O$18 -> #DIV/0!
A103: 60700005 | B103: ค่าบริจาค | O103: =SUM(C103:N103) -> 0 | Q103: =C103/C$18 -> #DIV/0! | R103: =D103/D$18 -> #DIV/0! | S103: =E103/E$18 -> #DIV/0! | T103: =F103/F$18 -> #DIV/0! | U103: =G103/G$18 -> #DIV/0! | V103: =H103/H$18 -> #DIV/0! | W103: =I103/I$18 -> #DIV/0! | X103: =J103/J$18 -> #DIV/0! | ... AC103: =O103/O$18 -> #DIV/0!
A104: 60700006 | B104: ค่าประกันภัย | O104: =SUM(C104:N104) -> 0 | Q104: =C104/C$18 -> #DIV/0! | R104: =D104/D$18 -> #DIV/0! | S104: =E104/E$18 -> #DIV/0! | T104: =F104/F$18 -> #DIV/0! | U104: =G104/G$18 -> #DIV/0! | V104: =H104/H$18 -> #DIV/0! | W104: =I104/I$18 -> #DIV/0! | X104: =J104/J$18 -> #DIV/0! | ... AC104: =O104/O$18 -> #DIV/0!
A105: 60700009 | B105: ค่าเช่าอื่นๆ | O105: =SUM(C105:N105) -> 0 | Q105: =C105/C$18 -> #DIV/0! | R105: =D105/D$18 -> #DIV/0! | S105: =E105/E$18 -> #DIV/0! | T105: =F105/F$18 -> #DIV/0! | U105: =G105/G$18 -> #DIV/0! | V105: =H105/H$18 -> #DIV/0! | W105: =I105/I$18 -> #DIV/0! | X105: =J105/J$18 -> #DIV/0! | ... AC105: =O105/O$18 -> #DIV/0!
A106: 60700010 | B106: ค่าบริการ Internet | O106: =SUM(C106:N106) -> 0 | Q106: =C106/C$18 -> #DIV/0! | R106: =D106/D$18 -> #DIV/0! | S106: =E106/E$18 -> #DIV/0! | T106: =F106/F$18 -> #DIV/0! | U106: =G106/G$18 -> #DIV/0! | V106: =H106/H$18 -> #DIV/0! | W106: =I106/I$18 -> #DIV/0! | X106: =J106/J$18 -> #DIV/0! | ... AC106: =O106/O$18 -> #DIV/0!
...

Sheet Budget ปี 2026
B1: THONGLOR PET HOSPITAL COMPANY LIMITED | G1: F | H1: Fixed
B2: บริษัท โรงพยาบาลสัตว์ทองหล่อ จำกัด | G2: V | H2: Variable | S2: 0.5 | T2: % การโต2 | U2: =S2*U3 -> #DIV/0! | V2: >for fixed expense
G3: z | H3: Zero-based: คำนวนใหม่ตามใช้จริง | T3: % การโต | U3: =(U18-E18)/E18 -> #DIV/0! | V3: >revenue%
C4: Act จริง | F4: สัดส่วน/ยอดขาย | G4: % การโต | I4: BG ปี 2025 ( ครึ่งปี แรก) | O4: BG ปี 2025 (ครึ่งปี หลัง) | U4: TOTAL | V4: ส้ดส่วน/ยอดขาย
C5: 9 | D5: ต่อเดือน | E5: 12 | H5: R,F,V,Z | I5: January | J5: February | K5: March | L5: April | M5: May | N5: June | O5: July | P5: August | Q5: September | R5: October | S5: November | T5: December | V5: January | W5: February | X5: March | Y5: April | Z5: May | AA5: June | AB5: July | AC5: August | AD5: September | AE5: October | AF5: November | AG5: December | AH5: TOTAL
A6: ='งบกำไรขาดทุน ปี 2025'!A6 -> 0 | B6: ='งบกำไรขาดทุน ปี 2025'!B6 -> รายได้ | AJ6: =IFERROR(U6/E6,0)-1 -> -1
A7: ='งบกำไรขาดทุน ปี 2025'!A7 -> 0 | B7: ='งบกำไรขาดทุน ปี 2025'!B7 -> รายได้จากการขายและอื่นๆ | AJ7: =IFERROR(U7/E7,0)-1 -> -1
A8: ='งบกำไรขาดทุน ปี 2025'!A8 -> 41100001 | B8: ='งบกำไรขาดทุน ปี 2025'!B8 -> รายได้จากการขาย - OPD/IPD | C8: ='งบกำไรขาดทุน ปี 2025'!O8 -> 0 | D8: =C8/$C$5 -> 0 | E8: =D8*$E$5 -> 0 | F8: =E8/$E$18 -> #DIV/0! | H8: R | I8: ='การลงระหว่างเดือน ปี 2026'!E7 -> 0 | J8: ='การลงระหว่างเดือน ปี 2026'!H7 -> 0 | K8: ='การลงระหว่างเดือน ปี 2026'!K7 -> 0 | L8: ='การลงระหว่างเดือน ปี 2026'!N7 -> 0 | M8: ='การลงระหว่างเดือน ปี 2026'!Q7 -> 0 | N8: ='การลงระหว่างเดือน ปี 2026'!T7 -> 0 | O8: ='การลงระหว่างเดือน ปี 2026'!W7 -> 0 | P8: ='การลงระหว่างเดือน ปี 2026'!Z7 -> 0 | Q8: ='การลงระหว่างเดือน ปี 2026'!AC7 -> 0 | R8: ='การลงระหว่างเดือน ปี 2026'!AF7 -> 0 | S8: ='การลงระหว่างเดือน ปี 2026'!AI7 -> 0 | T8: ='การลงระหว่างเดือน ปี 2026'!AL7 -> 0 | U8: =SUM(I8:T8) -> 0 | V8: =I8/$I$18 -> #DIV/0! | W8: =J8/$J$18 -> #DIV/0! | X8: =K8/$K$18 -> #DIV/0! | Y8: =L8/$L$18 -> #DIV/0! | Z8: =M8/$M$18 -> #DIV/0! | AA8: =N8/$N$18 -> #DIV/0! | AB8: =O8/$O$18 -> #DIV/0! | AC8: =P8/$P$18 -> #DIV/0! | AD8: =Q8/$Q$18 -> #DIV/0! | AE8: =R8/$R$18 -> #DIV/0! | AF8: =S8/$S$18 -> #DIV/0! | AG8: =T8/$T$18 -> #DIV/0! | AH8: =U8/$U$18 -> #DIV/0! | AI8: R | AJ8: =IFERROR(U8/E8,0)-1 -> -1
A9: ='งบกำไรขาดทุน ปี 2025'!A9 -> 41200001 | B9: ='งบกำไรขาดทุน ปี 2025'!B9 -> รายได้จากการขาย - Grooming | C9: ='งบกำไรขาดทุน ปี 2025'!O9 -> 0 | D9: =C9/$C$5 -> 0 | E9: =D9*$E$5 -> 0 | F9: =E9/$E$18 -> #DIV/0! | H9: R | I9: ='การลงระหว่างเดือน ปี 2026'!E8 -> 0 | J9: ='การลงระหว่างเดือน ปี 2026'!H8 -> 0 | K9: ='การลงระหว่างเดือน ปี 2026'!K8 -> 0 | L9: ='การลงระหว่างเดือน ปี 2026'!N8 -> 0 | M9: ='การลงระหว่างเดือน ปี 2026'!Q8 -> 0 | N9: ='การลงระหว่างเดือน ปี 2026'!T8 -> 0 | O9: ='การลงระหว่างเดือน ปี 2026'!W8 -> 0 | P9: ='การลงระหว่างเดือน ปี 2026'!Z8 -> 0 | Q9: ='การลงระหว่างเดือน ปี 2026'!AC8 -> 0 | R9: ='การลงระหว่างเดือน ปี 2026'!AF8 -> 0 | S9: ='การลงระหว่างเดือน ปี 2026'!AI8 -> 0 | T9: ='การลงระหว่างเดือน ปี 2026'!AL8 -> 0 | U9: =SUM(I9:T9) -> 0 | V9: =I9/$I$18 -> #DIV/0! | W9: =J9/$J$18 -> #DIV/0! | X9: =K9/$K$18 -> #DIV/0! | Y9: =L9/$L$18 -> #DIV/0! | Z9: =M9/$M$18 -> #DIV/0! | AA9: =N9/$N$18 -> #DIV/0! | AB9: =O9/$O$18 -> #DIV/0! | AC9: =P9/$P$18 -> #DIV/0! | AD9: =Q9/$Q$18 -> #DIV/0! | AE9: =R9/$R$18 -> #DIV/0! | AF9: =S9/$S$18 -> #DIV/0! | AG9: =T9/$T$18 -> #DIV/0! | AH9: =U9/$U$18 -> #DIV/0! | AI9: R | AJ9: =IFERROR(U9/E9,0)-1 -> -1
A10: ='งบกำไรขาดทุน ปี 2025'!A10 -> 41100002 | B10: ='งบกำไรขาดทุน ปี 2025'!B10 -> รายได้จากการขาย - Petshop | C10: ='งบกำไรขาดทุน ปี 2025'!O10 -> 0 | D10: =C10/$C$5 -> 0 | E10: =D10*$E$5 -> 0 | F10: =E10/$E$18 -> #DIV/0! | H10: R | I10: ='การลงระหว่างเดือน ปี 2026'!E9 -> 0 | J10: ='การลงระหว่างเดือน ปี 2026'!H9 -> 0 | K10: ='การลงระหว่างเดือน ปี 2026'!K9 -> 0 | L10: ='การลงระหว่างเดือน ปี 2026'!N9 -> 0 | M10: ='การลงระหว่างเดือน ปี 2026'!Q9 -> 0 | N10: ='การลงระหว่างเดือน ปี 2026'!T9 -> 0 | O10: ='การลงระหว่างเดือน ปี 2026'!W9 -> 0 | P10: ='การลงระหว่างเดือน ปี 2026'!Z9 -> 0 | Q10: ='การลงระหว่างเดือน ปี 2026'!AC9 -> 0 | R10: ='การลงระหว่างเดือน ปี 2026'!AF9 -> 0 | S10: ='การลงระหว่างเดือน ปี 2026'!AI9 -> 0 | T10: ='การลงระหว่างเดือน ปี 2026'!AL9 -> 0 | U10: =SUM(I10:T10) -> 0 | V10: =I10/$I$18 -> #DIV/0! | W10: =J10/$J$18 -> #DIV/0! | X10: =K10/$K$18 -> #DIV/0! | Y10: =L10/$L$18 -> #DIV/0! | Z10: =M10/$M$18 -> #DIV/0! | AA10: =N10/$N$18 -> #DIV/0! | AB10: =O10/$O$18 -> #DIV/0! | AC10: =P10/$P$18 -> #DIV/0! | AD10: =Q10/$Q$18 -> #DIV/0! | AE10: =R10/$R$18 -> #DIV/0! | AF10: =S10/$S$18 -> #DIV/0! | AG10: =T10/$T$18 -> #DIV/0! | AH10: =U10/$U$18 -> #DIV/0! | AI10: R | AJ10: =IFERROR(U10/E10,0)-1 -> -1
A11: ='งบกำไรขาดทุน ปี 2025'!A11 -> 41200004 | B11: ='งบกำไรขาดทุน ปี 2025'!B11 -> รายได้จากการขาย - Swimming | C11: ='งบกำไรขาดทุน ปี 2025'!O11 -> 0 | D11: =C11/$C$5 -> 0 | E11: =D11*$E$5 -> 0 | F11: =E11/$E$18 -> #DIV/0! | H11: R | I11: ='การลงระหว่างเดือน ปี 2026'!E10 -> 0 | J11: ='การลงระหว่างเดือน ปี 2026'!H10 -> 0 | K11: ='การลงระหว่างเดือน ปี 2026'!K10 -> 0 | L11: ='การลงระหว่างเดือน ปี 2026'!N10 -> 0 | M11: ='การลงระหว่างเดือน ปี 2026'!Q10 -> 0 | N11: ='การลงระหว่างเดือน ปี 2026'!T10 -> 0 | O11: ='การลงระหว่างเดือน ปี 2026'!W10 -> 0 | P11: ='การลงระหว่างเดือน ปี 2026'!Z10 -> 0 | Q11: ='การลงระหว่างเดือน ปี 2026'!AC10 -> 0 | R11: ='การลงระหว่างเดือน ปี 2026'!AF10 -> 0 | S11: ='การลงระหว่างเดือน ปี 2026'!AI10 -> 0 | T11: ='การลงระหว่างเดือน ปี 2026'!AL10 -> 0 | U11: =SUM(I11:T11) -> 0 | V11: =I11/$I$18 -> #DIV/0! | W11: =J11/$J$18 -> #DIV/0! | X11: =K11/$K$18 -> #DIV/0! | Y11: =L11/$L$18 -> #DIV/0! | Z11: =M11/$M$18 -> #DIV/0! | AA11: =N11/$N$18 -> #DIV/0! | AB11: =O11/$O$18 -> #DIV/0! | AC11: =P11/$P$18 -> #DIV/0! | AD11: =Q11/$Q$18 -> #DIV/0! | AE11: =R11/$R$18 -> #DIV/0! | AF11: =S11/$S$18 -> #DIV/0! | AG11: =T11/$T$18 -> #DIV/0! | AH11: =U11/$U$18 -> #DIV/0! | AI11: R | AJ11: =IFERROR(U11/E11,0)-1 -> -1
A12: ='งบกำไรขาดทุน ปี 2025'!A12 -> 41200002 | B12: ='งบกำไรขาดทุน ปี 2025'!B12 -> รายได้จากการขาย - Pettaxi | C12: ='งบกำไรขาดทุน ปี 2025'!O12 -> 0 | D12: =C12/$C$5 -> 0 | E12: =D12*$E$5 -> 0 | F12: =E12/$E$18 -> #DIV/0! | H12: R | I12: ='การลงระหว่างเดือน ปี 2026'!E11 -> 0 | J12: ='การลงระหว่างเดือน ปี 2026'!H11 -> 0 | K12: ='การลงระหว่างเดือน ปี 2026'!K11 -> 0 | L12: ='การลงระหว่างเดือน ปี 2026'!N11 -> 0 | M12: ='การลงระหว่างเดือน ปี 2026'!Q11 -> 0 | N12: ='การลงระหว่างเดือน ปี 2026'!T11 -> 0 | O12: ='การลงระหว่างเดือน ปี 2026'!W11 -> 0 | P12: ='การลงระหว่างเดือน ปี 2026'!Z11 -> 0 | Q12: ='การลงระหว่างเดือน ปี 2026'!AC11 -> 0 | R12: ='การลงระหว่างเดือน ปี 2026'!AF11 -> 0 | S12: ='การลงระหว่างเดือน ปี 2026'!AI11 -> 0 | T12: ='การลงระหว่างเดือน ปี 2026'!AL11 -> 0 | U12: =SUM(I12:T12) -> 0 | V12: =I12/$I$18 -> #DIV/0! | W12: =J12/$J$18 -> #DIV/0! | X12: =K12/$K$18 -> #DIV/0! | Y12: =L12/$L$18 -> #DIV/0! | Z12: =M12/$M$18 -> #DIV/0! | AA12: =N12/$N$18 -> #DIV/0! | AB12: =O12/$O$18 -> #DIV/0! | AC12: =P12/$P$18 -> #DIV/0! | AD12: =Q12/$Q$18 -> #DIV/0! | AE12: =R12/$R$18 -> #DIV/0! | AF12: =S12/$S$18 -> #DIV/0! | AG12: =T12/$T$18 -> #DIV/0! | AH12: =U12/$U$18 -> #DIV/0! | AI12: R | AJ12: =IFERROR(U12/E12,0)-1 -> -1
A13: ='งบกำไรขาดทุน ปี 2025'!A13 -> 41200003 | B13: ='งบกำไรขาดทุน ปี 2025'!B13 -> รายได้จากการขาย - อื่นๆ | C13: ='งบกำไรขาดทุน ปี 2025'!O13 -> 0 | D13: =C13/$C$5 -> 0 | E13: =D13*$E$5 -> 0 | F13: =E13/$E$18 -> #DIV/0! | H13: R | I13: =$D$13 -> 0 | J13: =$D$13 -> 0 | K13: =$D$13 -> 0 | L13: =$D$13 -> 0 | M13: =$D$13 -> 0 | N13: =$D$13 -> 0 | O13: =$D$13 -> 0 | P13: =$D$13 -> 0 | ... T13: =$D$13 -> 0 | U13: =SUM(I13:T13) -> 0 | V13: =I13/$I$18 -> #DIV/0! | W13: =J13/$J$18 -> #DIV/0! | X13: =K13/$K$18 -> #DIV/0! | Y13: =L13/$L$18 -> #DIV/0! | Z13: =M13/$M$18 -> #DIV/0! | AA13: =N13/$N$18 -> #DIV/0! | AB13: =O13/$O$18 -> #DIV/0! | AC13: =P13/$P$18 -> #DIV/0! | AD13: =Q13/$Q$18 -> #DIV/0! | AE13: =R13/$R$18 -> #DIV/0! | AF13: =S13/$S$18 -> #DIV/0! | AG13: =T13/$T$18 -> #DIV/0! | AH13: =U13/$U$18 -> #DIV/0! | AI13: R | AJ13: =IFERROR(U13/E13,0)-1 -> -1
A14: ='งบกำไรขาดทุน ปี 2025'!A14 -> 41300001 | B14: ='งบกำไรขาดทุน ปี 2025'!B14 -> หัก รับคืน | C14: ='งบกำไรขาดทุน ปี 2025'!O14 -> 0 | D14: =C14/$C$5 -> 0 | E14: =D14*$E$5 -> 0 | F14: =E14/$E$18 -> #DIV/0! | H14: R | I14: =$D$14 -> 0 | J14: =$D$14 -> 0 | K14: =$D$14 -> 0 | L14: =$D$14 -> 0 | M14: =$D$14 -> 0 | N14: =$D$14 -> 0 | O14: =$D$14 -> 0 | P14: =$D$14 -> 0 | ... T14: =$D$14 -> 0 | U14: =SUM(I14:T14) -> 0 | V14: =I14/$I$18 -> #DIV/0! | W14: =J14/$J$18 -> #DIV/0! | X14: =K14/$K$18 -> #DIV/0! | Y14: =L14/$L$18 -> #DIV/0! | Z14: =M14/$M$18 -> #DIV/0! | AA14: =N14/$N$18 -> #DIV/0! | AB14: =O14/$O$18 -> #DIV/0! | AC14: =P14/$P$18 -> #DIV/0! | AD14: =Q14/$Q$18 -> #DIV/0! | AE14: =R14/$R$18 -> #DIV/0! | AF14: =S14/$S$18 -> #DIV/0! | AG14: =T14/$T$18 -> #DIV/0! | AH14: =U14/$U$18 -> #DIV/0! | AI14: R | AJ14: =IFERROR(U14/E14,0)-1 -> -1
A15: ='งบกำไรขาดทุน ปี 2025'!A15 -> 41300002 | B15: ='งบกำไรขาดทุน ปี 2025'!B15 -> หัก ส่วนลดจ่าย | C15: ='งบกำไรขาดทุน ปี 2025'!O15 -> 0 | D15: =C15/$C$5 -> 0 | E15: =D15*$E$5 -> 0 | F15: =E15/$E$18 -> #DIV/0! | H15: R | I15: =$D$15 -> 0 | J15: =$D$15 -> 0 | K15: =$D$15 -> 0 | L15: =$D$15 -> 0 | M15: =$D$15 -> 0 | N15: =$D$15 -> 0 | O15: =$D$15 -> 0 | P15: =$D$15 -> 0 | ... T15: =$D$15 -> 0 | U15: =SUM(I15:T15) -> 0 | V15: =I15/$I$18 -> #DIV/0! | W15: =J15/$J$18 -> #DIV/0! | X15: =K15/$K$18 -> #DIV/0! | Y15: =L15/$L$18 -> #DIV/0! | Z15: =M15/$M$18 -> #DIV/0! | AA15: =N15/$N$18 -> #DIV/0! | AB15: =O15/$O$18 -> #DIV/0! | AC15: =P15/$P$18 -> #DIV/0! | AD15: =Q15/$Q$18 -> #DIV/0! | AE15: =R15/$R$18 -> #DIV/0! | AF15: =S15/$S$18 -> #DIV/0! | AG15: =T15/$T$18 -> #DIV/0! | AH15: =U15/$U$18 -> #DIV/0! | AI15: R | AJ15: =IFERROR(U15/E15,0)-1 -> -1
A16: ='งบกำไรขาดทุน ปี 2025'!A16 -> 42000001 | B16: ='งบกำไรขาดทุน ปี 2025'!B16 -> รายได้อื่นๆ | C16: ='งบกำไรขาดทุน ปี 2025'!O16 -> 0 | D16: =C16/$C$5 -> 0 | E16: =D16*$E$5 -> 0 | F16: =E16/$E$18 -> #DIV/0! | H16: R | I16: =$D$16 -> 0 | J16: =$D$16 -> 0 | K16: =$D$16 -> 0 | L16: =$D$16 -> 0 | M16: =$D$16 -> 0 | N16: =$D$16 -> 0 | O16: =$D$16 -> 0 | P16: =$D$16 -> 0 | ... T16: =$D$16 -> 0 | U16: =SUM(I16:T16) -> 0 | V16: =I16/$I$18 -> #DIV/0! | W16: =J16/$J$18 -> #DIV/0! | X16: =K16/$K$18 -> #DIV/0! | Y16: =L16/$L$18 -> #DIV/0! | Z16: =M16/$M$18 -> #DIV/0! | AA16: =N16/$N$18 -> #DIV/0! | AB16: =O16/$O$18 -> #DIV/0! | AC16: =P16/$P$18 -> #DIV/0! | AD16: =Q16/$Q$18 -> #DIV/0! | AE16: =R16/$R$18 -> #DIV/0! | AF16: =S16/$S$18 -> #DIV/0! | AG16: =T16/$T$18 -> #DIV/0! | AH16: =U16/$U$18 -> #DIV/0! | AI16: R | AJ16: =IFERROR(U16/E16,0)-1 -> -1
A17: ='งบกำไรขาดทุน ปี 2025'!A17 -> 42000019 | B17: ='งบกำไรขาดทุน ปี 2025'!B17 -> รายได้ Package/PR/ขนส่ง | C17: ='งบกำไรขาดทุน ปี 2025'!O17 -> 0 | D17: =C17/$C$5 -> 0 | E17: =D17*$E$5 -> 0 | F17: =E17/$E$18 -> #DIV/0! | H17: R | I17: =$D$16 -> 0 | J17: =$D$16 -> 0 | K17: =$D$16 -> 0 | L17: =$D$16 -> 0 | M17: =$D$16 -> 0 | N17: =$D$16 -> 0 | O17: =$D$16 -> 0 | P17: =$D$16 -> 0 | ... T17: =$D$16 -> 0 | U17: =SUM(I17:T17) -> 0 | V17: =I17/$I$18 -> #DIV/0! | W17: =J17/$J$18 -> #DIV/0! | X17: =K17/$K$18 -> #DIV/0! | Y17: =L17/$L$18 -> #DIV/0! | Z17: =M17/$M$18 -> #DIV/0! | AA17: =N17/$N$18 -> #DIV/0! | AB17: =O17/$O$18 -> #DIV/0! | AC17: =P17/$P$18 -> #DIV/0! | AD17: =Q17/$Q$18 -> #DIV/0! | AE17: =R17/$R$18 -> #DIV/0! | AF17: =S17/$S$18 -> #DIV/0! | AG17: =T17/$T$18 -> #DIV/0! | AH17: =U17/$U$18 -> #DIV/0! | AI17: R | AJ17: =IFERROR(U17/E17,0)-1 -> -1
A18: ='งบกำไรขาดทุน ปี 2025'!A18 -> 0 | B18: ='งบกำไรขาดทุน ปี 2025'!B18 -> รวมรายได้จาการขายและอื่นๆ | C18: ='งบกำไรขาดทุน ปี 2025'!O18 -> 0 | D18: =C18/$C$5 -> 0 | E18: =D18*$E$5 -> 0 | F18: =E18/$E$18 -> #DIV/0! | I18: =SUM(I8:I16) -> 0 | J18: =SUM(J8:J16) -> 0 | K18: =SUM(K8:K16) -> 0 | L18: =SUM(L8:L16) -> 0 | M18: =SUM(M8:M16) -> 0 | N18: =SUM(N8:N16) -> 0 | O18: =SUM(O8:O16) -> 0 | P18: =SUM(P8:P16) -> 0 | ... U18: =SUM(U8:U16) -> 0 | V18: =I18/$I$18 -> #DIV/0! | W18: =J18/$J$18 -> #DIV/0! | X18: =K18/$K$18 -> #DIV/0! | Y18: =L18/$L$18 -> #DIV/0! | Z18: =M18/$M$18 -> #DIV/0! | AA18: =N18/$N$18 -> #DIV/0! | AB18: =O18/$O$18 -> #DIV/0! | AC18: =P18/$P$18 -> #DIV/0! | AD18: =Q18/$Q$18 -> #DIV/0! | AE18: =R18/$R$18 -> #DIV/0! | AF18: =S18/$S$18 -> #DIV/0! | AG18: =T18/$T$18 -> #DIV/0! | AH18: =U18/$U$18 -> #DIV/0! | AJ18: =IFERROR(U18/E18,0)-1 -> -1
A19: ='งบกำไรขาดทุน ปี 2025'!A19 -> 0 | B19: ='งบกำไรขาดทุน ปี 2025'!B19 -> ต้นทุนขายและค่าใช้จ่ายที่เกี่ยวข้อง | C19: ='งบกำไรขาดทุน ปี 2025'!O19 -> 0 | AJ19: =IFERROR(U19/E19,0)-1 -> -1
A20: ='งบกำไรขาดทุน ปี 2025'!A20 -> 0 | B20: ='งบกำไรขาดทุน ปี 2025'!B20 -> ต้นทุนขาย | C20: ='งบกำไรขาดทุน ปี 2025'!O20 -> 0 | AJ20: =IFERROR(U20/E20,0)-1 -> -1
A21: ='งบกำไรขาดทุน ปี 2025'!A21 -> 51000002 | B21: ='งบกำไรขาดทุน ปี 2025'!B21 -> ต้นทุนขายสินค้า PH | C21: ='งบกำไรขาดทุน ปี 2025'!O21 -> 0 | D21: =C21/$C$5 -> 0 | E21: =D21*$E$5 -> 0 | F21: =(E21+E23)/(E8+E9+E11+E12+E13) -> #DIV/0! | G21: -0.0075 | H21: C | I21: =((I8+I9+I11+I12+I13)*(F21+G21)) -> #DIV/0! | J21: =($J$18*(F21+G21)) -> #DIV/0! | K21: =($K$18*(F21+G21)) -> #DIV/0! | L21: =($L$18*(F21+G21)) -> #DIV/0! | M21: =($M$18*(F21+G21)) -> #DIV/0! | N21: =($N$18*(F21+G21)) -> #DIV/0! | O21: =($O$18*(F21+G21)) -> #DIV/0! | P21: =($P$18*(F21+G21)) -> #DIV/0! | Q21: =($Q$18*(F21+G21)) -> #DIV/0! | R21: =($R$18*(F21+G21)) -> #DIV/0! | S21: =($S$18*(F21+G21)) -> #DIV/0! | T21: =($T$18*(F21+G21)) -> #DIV/0! | U21: =SUM(I21:T21) -> #DIV/0! | V21: =I21/$I$18 -> #DIV/0! | W21: =J21/$J$18 -> #DIV/0! | X21: =K21/$K$18 -> #DIV/0! | Y21: =L21/$L$18 -> #DIV/0! | Z21: =M21/$M$18 -> #DIV/0! | AA21: =N21/$N$18 -> #DIV/0! | AB21: =O21/$O$18 -> #DIV/0! | AC21: =P21/$P$18 -> #DIV/0! | AD21: =Q21/$Q$18 -> #DIV/0! | AE21: =R21/$R$18 -> #DIV/0! | AF21: =S21/$S$18 -> #DIV/0! | AG21: =T21/$T$18 -> #DIV/0! | AH21: =U21/(U8+U9+U11+U12+U13) -> #DIV/0! | AJ21: =IFERROR(U21/E21,0)-1 -> -1
A22: ='งบกำไรขาดทุน ปี 2025'!A22 -> 51000003 | B22: ='งบกำไรขาดทุน ปี 2025'!B22 -> ต้นทุนขายสินค้า PC | C22: ='งบกำไรขาดทุน ปี 2025'!O22 -> 0 | D22: =C22/$C$5 -> 0 | E22: =D22*$E$5 -> 0 | F22: =E22/$E$10 -> #DIV/0! | G22: -0.015 | H22: C | I22: =(I10*($F$22+$G$22)) -> #DIV/0! | J22: =(J10*($F$22+$G$22)) -> #DIV/0! | K22: =(K10*($F$22+$G$22)) -> #DIV/0! | L22: =(L10*($F$22+$G$22)) -> #DIV/0! | M22: =(M10*($F$22+$G$22)) -> #DIV/0! | N22: =(N10*($F$22+$G$22)) -> #DIV/0! | O22: =(O10*($F$22+$G$22)) -> #DIV/0! | P22: =(P10*($F$22+$G$22)) -> #DIV/0! | ... T22: =(T10*($F$22+$G$22)) -> #DIV/0! | U22: =SUM(I22:T22) -> #DIV/0! | V22: =I22/$I$18 -> #DIV/0! | W22: =J22/$J$18 -> #DIV/0! | X22: =K22/$K$18 -> #DIV/0! | Y22: =L22/$L$18 -> #DIV/0! | Z22: =M22/$M$18 -> #DIV/0! | AA22: =N22/$N$18 -> #DIV/0! | AB22: =O22/$O$18 -> #DIV/0! | AC22: =P22/$P$18 -> #DIV/0! | AD22: =Q22/$Q$18 -> #DIV/0! | AE22: =R22/$R$18 -> #DIV/0! | AF22: =S22/$S$18 -> #DIV/0! | AG22: =T22/$T$18 -> #DIV/0! | AH22: =U22/$U$10 -> #DIV/0! | AJ22: =IFERROR(U22/E22,0)-1 -> -1
A23: ='งบกำไรขาดทุน ปี 2025'!A23 -> 51000004 | B23: ='งบกำไรขาดทุน ปี 2025'!B23 -> หัก ส่วนลดรับ | C23: ='งบกำไรขาดทุน ปี 2025'!O23 -> 0 | D23: =C23/$C$5 -> 0 | E23: =D23*$E$5 -> 0 | F23: =(E23)/(E8+E9+E11+E12+E13) -> #DIV/0! | G23: 0 | H23: C | I23: =($I$18*(F23+G23)) -> #DIV/0! | J23: =($J$18*(F23+G23)) -> #DIV/0! | K23: =($K$18*(F23+G23)) -> #DIV/0! | L23: =($L$18*(F23+G23)) -> #DIV/0! | M23: =($M$18*(F23+G23)) -> #DIV/0! | N23: =($N$18*(F23+G23)) -> #DIV/0! | O23: =($O$18*(F23+G23)) -> #DIV/0! | P23: =($P$18*(F23+G23)) -> #DIV/0! | Q23: =($Q$18*(F23+G23)) -> #DIV/0! | R23: =($R$18*(F23+G23)) -> #DIV/0! | S23: =($S$18*(F23+G23)) -> #DIV/0! | T23: =($T$18*(F23+G23)) -> #DIV/0! | U23: =SUM(I23:T23) -> #DIV/0! | V23: =I23/$I$18 -> #DIV/0! | W23: =J23/$J$18 -> #DIV/0! | X23: =K23/$K$18 -> #DIV/0! | Y23: =L23/$L$18 -> #DIV/0! | Z23: =M23/$M$18 -> #DIV/0! | AA23: =N23/$N$18 -> #DIV/0! | AB23: =O23/$O$18 -> #DIV/0! | AC23: =P23/$P$18 -> #DIV/0! | AD23: =Q23/$Q$18 -> #DIV/0! | AE23: =R23/$R$18 -> #DIV/0! | AF23: =S23/$S$18 -> #DIV/0! | AG23: =T23/$T$18 -> #DIV/0! | AH23: =U23/(U8+U9+U11+U13+U14) -> #DIV/0! | AJ23: =IFERROR(U23/E23,0)-1 -> -1
A24: ='งบกำไรขาดทุน ปี 2025'!A24 -> 51000001 | B24: ='งบกำไรขาดทุน ปี 2025'!B24 -> รวมต้นทุนขาย | C24: ='งบกำไรขาดทุน ปี 2025'!O24 -> 0 | D24: =C24/$C$5 -> 0 | E24: =D24*$E$5 -> 0 | F24: =E24/$E$18 -> #DIV/0! | H24: c | I24: =SUM(I20:I23) -> #DIV/0! | J24: =SUM(J20:J23) -> #DIV/0! | K24: =SUM(K20:K23) -> #DIV/0! | L24: =SUM(L20:L23) -> #DIV/0! | M24: =SUM(M20:M23) -> #DIV/0! | N24: =SUM(N20:N23) -> #DIV/0! | O24: =SUM(O20:O23) -> #DIV/0! | P24: =SUM(P20:P23) -> #DIV/0! | ... T24: =SUM(T20:T23) -> #DIV/0! | U24: =SUM(U19:U23) -> #DIV/0! | V24: =I24/$I$18 -> #DIV/0! | W24: =J24/$J$18 -> #DIV/0! | X24: =K24/$K$18 -> #DIV/0! | Y24: =L24/$L$18 -> #DIV/0! | Z24: =M24/$M$18 -> #DIV/0! | AA24: =N24/$N$18 -> #DIV/0! | AB24: =O24/$O$18 -> #DIV/0! | AC24: =P24/$P$18 -> #DIV/0! | AD24: =Q24/$Q$18 -> #DIV/0! | AE24: =R24/$R$18 -> #DIV/0! | AF24: =S24/$S$18 -> #DIV/0! | AG24: =T24/$T$18 -> #DIV/0! | AH24: =U24/$U$18 -> #DIV/0! | AI24: c | AJ24: =IFERROR(U24/E24,0)-1 -> -1
A25: ='งบกำไรขาดทุน ปี 2025'!A25 -> 0 | B25: ='งบกำไรขาดทุน ปี 2025'!B25 -> ค่าใช้จ่ายในการขาย | F25: =E25/$E$18 -> #DIV/0! | AJ25: =IFERROR(U25/E25,0)-1 -> -1
A26: ='งบกำไรขาดทุน ปี 2025'!A26 -> 52000017 | B26: ='งบกำไรขาดทุน ปี 2025'!B26 -> ค่าใช้จ่ายในการขาย และค่าธรรมเนียม | C26: ='งบกำไรขาดทุน ปี 2025'!O26 -> 0 | D26: =C26/$C$5 -> 0 | E26: =D26*$E$5 -> 0 | F26: =E26/$E$18 -> #DIV/0! | H26: V | I26: =((I$18*($F26+$G26))) -> #DIV/0! | J26: =((J$18*($F26+$G26))+'การลงระหว่างเดือน ปี 2026'!AP13) -> #DIV/0! | K26: =((K$18*($F26+$G26))+'การลงระหว่างเดือน ปี 2026'!AQ13) -> #DIV/0! | L26: =((L$18*($F26+$G26))+'การลงระหว่างเดือน ปี 2026'!AR13) -> #DIV/0! | M26: =((M$18*($F26+$G26))+'การลงระหว่างเดือน ปี 2026'!AS13) -> #DIV/0! | N26: =((N$18*($F26+$G26))+'การลงระหว่างเดือน ปี 2026'!AT13) -> #DIV/0! | O26: =((O$18*($F26+$G26))+'การลงระหว่างเดือน ปี 2026'!AU13) -> #DIV/0! | P26: =((P$18*($F26+$G26))+'การลงระหว่างเดือน ปี 2026'!AV13) -> #DIV/0! | Q26: =((Q$18*($F26+$G26))+'การลงระหว่างเดือน ปี 2026'!AW13) -> #DIV/0! | ... T26: =((T$18*($F26+$G26))+'การลงระหว่างเดือน ปี 2026'!AZ13) -> #DIV/0! | U26: =SUM(I26:T26) -> #DIV/0! | V26: =I26/$I$18 -> #DIV/0! | W26: =J26/$J$18 -> #DIV/0! | X26: =K26/$K$18 -> #DIV/0! | Y26: =L26/$L$18 -> #DIV/0! | Z26: =M26/$M$18 -> #DIV/0! | AA26: =N26/$N$18 -> #DIV/0! | AB26: =O26/$O$18 -> #DIV/0! | AC26: =P26/$P$18 -> #DIV/0! | AD26: =Q26/$Q$18 -> #DIV/0! | AE26: =R26/$R$18 -> #DIV/0! | AF26: =S26/$S$18 -> #DIV/0! | AG26: =T26/$T$18 -> #DIV/0! | AH26: =U26/$U$18 -> #DIV/0! | AI26: V | AJ26: =IFERROR(U26/E26,0)-1 -> -1
A27: ='งบกำไรขาดทุน ปี 2025'!A27 -> 52000001 | B27: ='งบกำไรขาดทุน ปี 2025'!B27 -> ค่าส่งเสริมการขาย | C27: ='งบกำไรขาดทุน ปี 2025'!O27 -> 0 | D27: =C27/$C$5 -> 0 | E27: =D27*$E$5 -> 0 | F27: =E27/$E$18 -> #DIV/0! | H27: Z | I27: ='การลงระหว่างเดือน ปี 2026'!AO13 -> 0 | J27: ='การลงระหว่างเดือน ปี 2026'!AP13 -> 0 | K27: ='การลงระหว่างเดือน ปี 2026'!AQ13 -> 0 | L27: ='การลงระหว่างเดือน ปี 2026'!AR13 -> 0 | M27: ='การลงระหว่างเดือน ปี 2026'!AS13 -> 0 | N27: ='การลงระหว่างเดือน ปี 2026'!AT13 -> 0 | O27: ='การลงระหว่างเดือน ปี 2026'!AU13 -> 0 | P27: ='การลงระหว่างเดือน ปี 2026'!AV13 -> 0 | ... T27: ='การลงระหว่างเดือน ปี 2026'!AZ13 -> 0 | U27: =SUM(I27:T27) -> 0 | V27: =I27/$I$18 -> #DIV/0! | W27: =J27/$J$18 -> #DIV/0! | X27: =K27/$K$18 -> #DIV/0! | Y27: =L27/$L$18 -> #DIV/0! | Z27: =M27/$M$18 -> #DIV/0! | AA27: =N27/$N$18 -> #DIV/0! | AB27: =O27/$O$18 -> #DIV/0! | AC27: =P27/$P$18 -> #DIV/0! | AD27: =Q27/$Q$18 -> #DIV/0! | AE27: =R27/$R$18 -> #DIV/0! | AF27: =S27/$S$18 -> #DIV/0! | AG27: =T27/$T$18 -> #DIV/0! | AH27: =U27/$U$18 -> #DIV/0! | AI27: V | AJ27: =IFERROR(U27/E27,0)-1 -> -1
A28: ='งบกำไรขาดทุน ปี 2025'!A28 -> 52000003 | B28: ='งบกำไรขาดทุน ปี 2025'!B28 -> ค่าชันสูตรโรค | C28: ='งบกำไรขาดทุน ปี 2025'!O28 -> 0 | D28: =C28/$C$5 -> 0 | E28: =D28*$E$5 -> 0 | F28: =E28/$E$18 -> #DIV/0! | H28: V | I28: =((I$18*($F28+$G28))) -> #DIV/0! | J28: =((J$18*($F28+$G28))) -> #DIV/0! | K28: =((K$18*($F28+$G28))) -> #DIV/0! | L28: =((L$18*($F28+$G28))) -> #DIV/0! | M28: =((M$18*($F28+$G28))) -> #DIV/0! | N28: =((N$18*($F28+$G28))) -> #DIV/0! | O28: =((O$18*($F28+$G28))) -> #DIV/0! | P28: =((P$18*($F28+$G28))) -> #DIV/0! | ... T28: =((T$18*($F28+$G28))) -> #DIV/0! | U28: =SUM(I28:T28) -> #DIV/0! | V28: =I28/$I$18 -> #DIV/0! | W28: =J28/$J$18 -> #DIV/0! | X28: =K28/$K$18 -> #DIV/0! | Y28: =L28/$L$18 -> #DIV/0! | Z28: =M28/$M$18 -> #DIV/0! | AA28: =N28/$N$18 -> #DIV/0! | AB28: =O28/$O$18 -> #DIV/0! | AC28: =P28/$P$18 -> #DIV/0! | AD28: =Q28/$Q$18 -> #DIV/0! | AE28: =R28/$R$18 -> #DIV/0! | AF28: =S28/$S$18 -> #DIV/0! | AG28: =T28/$T$18 -> #DIV/0! | AH28: =U28/$U$18 -> #DIV/0! | AI28: V | AJ28: =IFERROR(U28/E28,0)-1 -> -1
A29: ='งบกำไรขาดทุน ปี 2025'!A29 -> 52000004 | B29: ='งบกำไรขาดทุน ปี 2025'!B29 -> ค่าส่งเผา | C29: ='งบกำไรขาดทุน ปี 2025'!O29 -> 0 | D29: =C29/$C$5 -> 0 | E29: =D29*$E$5 -> 0 | F29: =E29/$E$18 -> #DIV/0! | H29: V | I29: =((I$18*($F29+$G29))) -> #DIV/0! | J29: =((J$18*($F29+$G29))) -> #DIV/0! | K29: =((K$18*($F29+$G29))) -> #DIV/0! | L29: =((L$18*($F29+$G29))) -> #DIV/0! | M29: =((M$18*($F29+$G29))) -> #DIV/0! | N29: =((N$18*($F29+$G29))) -> #DIV/0! | O29: =((O$18*($F29+$G29))) -> #DIV/0! | P29: =((P$18*($F29+$G29))) -> #DIV/0! | ... T29: =((T$18*($F29+$G29))) -> #DIV/0! | U29: =SUM(I29:T29) -> #DIV/0! | V29: =I29/$I$18 -> #DIV/0! | W29: =J29/$J$18 -> #DIV/0! | X29: =K29/$K$18 -> #DIV/0! | Y29: =L29/$L$18 -> #DIV/0! | Z29: =M29/$M$18 -> #DIV/0! | AA29: =N29/$N$18 -> #DIV/0! | AB29: =O29/$O$18 -> #DIV/0! | AC29: =P29/$P$18 -> #DIV/0! | AD29: =Q29/$Q$18 -> #DIV/0! | AE29: =R29/$R$18 -> #DIV/0! | AF29: =S29/$S$18 -> #DIV/0! | AG29: =T29/$T$18 -> #DIV/0! | AH29: =U29/$U$18 -> #DIV/0! | AI29: V | AJ29: =IFERROR(U29/E29,0)-1 -> -1
A30: ='งบกำไรขาดทุน ปี 2025'!A30 -> 52000005 | B30: ='งบกำไรขาดทุน ปี 2025'!B30 -> ค่าตรวจเลือด | C30: ='งบกำไรขาดทุน ปี 2025'!O30 -> 0 | D30: =C30/$C$5 -> 0 | E30: =D30*$E$5 -> 0 | F30: =E30/$E$18 -> #DIV/0! | H30: V | I30: =((I$18*($F30+$G30))) -> #DIV/0! | J30: =((J$18*($F30+$G30))) -> #DIV/0! | K30: =((K$18*($F30+$G30))) -> #DIV/0! | L30: =((L$18*($F30+$G30))) -> #DIV/0! | M30: =((M$18*($F30+$G30))) -> #DIV/0! | N30: =((N$18*($F30+$G30))) -> #DIV/0! | O30: =((O$18*($F30+$G30))) -> #DIV/0! | P30: =((P$18*($F30+$G30))) -> #DIV/0! | ... T30: =((T$18*($F30+$G30))) -> #DIV/0! | U30: =SUM(I30:T30) -> #DIV/0! | V30: =I30/$I$18 -> #DIV/0! | W30: =J30/$J$18 -> #DIV/0! | X30: =K30/$K$18 -> #DIV/0! | Y30: =L30/$L$18 -> #DIV/0! | Z30: =M30/$M$18 -> #DIV/0! | AA30: =N30/$N$18 -> #DIV/0! | AB30: =O30/$O$18 -> #DIV/0! | AC30: =P30/$P$18 -> #DIV/0! | AD30: =Q30/$Q$18 -> #DIV/0! | AE30: =R30/$R$18 -> #DIV/0! | AF30: =S30/$S$18 -> #DIV/0! | AG30: =T30/$T$18 -> #DIV/0! | AH30: =U30/$U$18 -> #DIV/0! | AI30: V | AJ30: =IFERROR(U30/E30,0)-1 -> -1
A31: ='งบกำไรขาดทุน ปี 2025'!A31 -> 52000006 | B31: ='งบกำไรขาดทุน ปี 2025'!B31 -> ค่าตรวจเลือดภายใน | C31: ='งบกำไรขาดทุน ปี 2025'!O31 -> 0 | D31: =C31/$C$5 -> 0 | E31: =D31*$E$5 -> 0 | F31: =E31/$E$18 -> #DIV/0! | H31: V | I31: =((I$18*($F31+$G31))) -> #DIV/0! | J31: =((J$18*($F31+$G31))) -> #DIV/0! | K31: =((K$18*($F31+$G31))) -> #DIV/0! | L31: =((L$18*($F31+$G31))) -> #DIV/0! | M31: =((M$18*($F31+$G31))) -> #DIV/0! | N31: =((N$18*($F31+$G31))) -> #DIV/0! | O31: =((O$18*($F31+$G31))) -> #DIV/0! | P31: =((P$18*($F31+$G31))) -> #DIV/0! | ... T31: =((T$18*($F31+$G31))) -> #DIV/0! | U31: =SUM(I31:T31) -> #DIV/0! | V31: =I31/$I$18 -> #DIV/0! | W31: =J31/$J$18 -> #DIV/0! | X31: =K31/$K$18 -> #DIV/0! | Y31: =L31/$L$18 -> #DIV/0! | Z31: =M31/$M$18 -> #DIV/0! | AA31: =N31/$N$18 -> #DIV/0! | AB31: =O31/$O$18 -> #DIV/0! | AC31: =P31/$P$18 -> #DIV/0! | AD31: =Q31/$Q$18 -> #DIV/0! | AE31: =R31/$R$18 -> #DIV/0! | AF31: =S31/$S$18 -> #DIV/0! | AG31: =T31/$T$18 -> #DIV/0! | AH31: =U31/$U$18 -> #DIV/0! | AI31: V | AJ31: =IFERROR(U31/E31,0)-1 -> -1
A32: ='งบกำไรขาดทุน ปี 2025'!A32 -> 52000007 | B32: ='งบกำไรขาดทุน ปี 2025'!B32 -> ค่าเช่าเครื่องมือภายใน | C32: ='งบกำไรขาดทุน ปี 2025'!O32 -> 0 | D32: =C32/$C$5 -> 0 | E32: =D32*$E$5 -> 0 | F32: =E32/$E$18 -> #DIV/0! | H32: V | I32: =((I$18*($F32+$G32))) -> #DIV/0! | J32: =((J$18*($F32+$G32))) -> #DIV/0! | K32: =((K$18*($F32+$G32))) -> #DIV/0! | L32: =((L$18*($F32+$G32))) -> #DIV/0! | M32: =((M$18*($F32+$G32))) -> #DIV/0! | N32: =((N$18*($F32+$G32))) -> #DIV/0! | O32: =((O$18*($F32+$G32))) -> #DIV/0! | P32: =((P$18*($F32+$G32))) -> #DIV/0! | ... T32: =((T$18*($F32+$G32))) -> #DIV/0! | U32: =SUM(I32:T32) -> #DIV/0! | V32: =I32/$I$18 -> #DIV/0! | W32: =J32/$J$18 -> #DIV/0! | X32: =K32/$K$18 -> #DIV/0! | Y32: =L32/$L$18 -> #DIV/0! | Z32: =M32/$M$18 -> #DIV/0! | AA32: =N32/$N$18 -> #DIV/0! | AB32: =O32/$O$18 -> #DIV/0! | AC32: =P32/$P$18 -> #DIV/0! | AD32: =Q32/$Q$18 -> #DIV/0! | AE32: =R32/$R$18 -> #DIV/0! | AF32: =S32/$S$18 -> #DIV/0! | AG32: =T32/$T$18 -> #DIV/0! | AH32: =U32/$U$18 -> #DIV/0! | AI32: V | AJ32: =IFERROR(U32/E32,0)-1 -> -1
A33: ='งบกำไรขาดทุน ปี 2025'!A33 -> 52000008 | B33: ='งบกำไรขาดทุน ปี 2025'!B33 -> ค่าบริการวิชาชีพแพทย์ | C33: ='งบกำไรขาดทุน ปี 2025'!O33 -> 0 | D33: =C33/$C$5 -> 0 | E33: =D33*$E$5 -> 0 | F33: =E33/$E$18 -> #DIV/0! | H33: V | I33: =((I$18*($F33+$G33))+'การลงระหว่างเดือน ปี 2026'!AO14) -> #DIV/0! | J33: =((J$18*($F33+$G33))+'การลงระหว่างเดือน ปี 2026'!AP14) -> #DIV/0! | K33: =((K$18*($F33+$G33))+'การลงระหว่างเดือน ปี 2026'!AQ14) -> #DIV/0! | L33: =((L$18*($F33+$G33))+'การลงระหว่างเดือน ปี 2026'!AR14) -> #DIV/0! | M33: =((M$18*($F33+$G33))+'การลงระหว่างเดือน ปี 2026'!AS14) -> #DIV/0! | N33: =((N$18*($F33+$G33))+'การลงระหว่างเดือน ปี 2026'!AT14) -> #DIV/0! | O33: =((O$18*($F33+$G33))+'การลงระหว่างเดือน ปี 2026'!AU14) -> #DIV/0! | P33: =((P$18*($F33+$G33))+'การลงระหว่างเดือน ปี 2026'!AV14) -> #DIV/0! | ... T33: =((T$18*($F33+$G33))+'การลงระหว่างเดือน ปี 2026'!AZ14) -> #DIV/0! | U33: =SUM(I33:T33) -> #DIV/0! | V33: =I33/$I$18 -> #DIV/0! | W33: =J33/$J$18 -> #DIV/0! | X33: =K33/$K$18 -> #DIV/0! | Y33: =L33/$L$18 -> #DIV/0! | Z33: =M33/$M$18 -> #DIV/0! | AA33: =N33/$N$18 -> #DIV/0! | AB33: =O33/$O$18 -> #DIV/0! | AC33: =P33/$P$18 -> #DIV/0! | AD33: =Q33/$Q$18 -> #DIV/0! | AE33: =R33/$R$18 -> #DIV/0! | AF33: =S33/$S$18 -> #DIV/0! | AG33: =T33/$T$18 -> #DIV/0! | AH33: =U33/$U$18 -> #DIV/0! | AI33: V | AJ33: =IFERROR(U33/E33,0)-1 -> -1
A34: ='งบกำไรขาดทุน ปี 2025'!A34 -> 52000010 | B34: ='งบกำไรขาดทุน ปี 2025'!B34 -> ค่าเช่าเครื่องมือแพทย์ | C34: ='งบกำไรขาดทุน ปี 2025'!O34 -> 0 | D34: =C34/$C$5 -> 0 | E34: =D34*$E$5 -> 0 | F34: =E34/$E$18 -> #DIV/0! | G34: =$U$2 -> #DIV/0! | H34: F | I34: =(($D34*$G34)+$D34)+'การลงระหว่างเดือน ปี 2026'!AO15 -> #DIV/0! | J34: =(($D34*$G34)+$D34)+'การลงระหว่างเดือน ปี 2026'!AP15 -> #DIV/0! | K34: =(($D34*$G34)+$D34)+'การลงระหว่างเดือน ปี 2026'!AQ15 -> #DIV/0! | L34: =(($D34*$G34)+$D34)+'การลงระหว่างเดือน ปี 2026'!AR15 -> #DIV/0! | M34: =(($D34*$G34)+$D34)+'การลงระหว่างเดือน ปี 2026'!AS15 -> #DIV/0! | N34: =(($D34*$G34)+$D34)+'การลงระหว่างเดือน ปี 2026'!AT15 -> #DIV/0! | O34: =(($D34*$G34)+$D34)+'การลงระหว่างเดือน ปี 2026'!AU15 -> #DIV/0! | P34: =(($D34*$G34)+$D34)+'การลงระหว่างเดือน ปี 2026'!AV15 -> #DIV/0! | ... T34: =(($D34*$G34)+$D34)+'การลงระหว่างเดือน ปี 2026'!AZ15 -> #DIV/0! | U34: =SUM(I34:T34) -> #DIV/0! | V34: =I34/$I$18 -> #DIV/0! | W34: =J34/$J$18 -> #DIV/0! | X34: =K34/$K$18 -> #DIV/0! | Y34: =L34/$L$18 -> #DIV/0! | Z34: =M34/$M$18 -> #DIV/0! | AA34: =N34/$N$18 -> #DIV/0! | AB34: =O34/$O$18 -> #DIV/0! | AC34: =P34/$P$18 -> #DIV/0! | AD34: =Q34/$Q$18 -> #DIV/0! | AE34: =R34/$R$18 -> #DIV/0! | AF34: =S34/$S$18 -> #DIV/0! | AG34: =T34/$T$18 -> #DIV/0! | AH34: =U34/$U$18 -> #DIV/0! | AI34: F | AJ34: =IFERROR(U34/E34,0)-1 -> -1
A35: ='งบกำไรขาดทุน ปี 2025'!A35 -> 52000011 | B35: ='งบกำไรขาดทุน ปี 2025'!B35 -> ค่าวัสดุเครื่องมือแพทย์ | C35: ='งบกำไรขาดทุน ปี 2025'!O35 -> 0 | D35: =C35/$C$5 -> 0 | E35: =D35*$E$5 -> 0 | F35: =E35/$E$18 -> #DIV/0! | H35: V | I35: =((I$18*($F35+$G35))+'การลงระหว่างเดือน ปี 2026'!AO16) -> #DIV/0! | J35: =((J$18*($F35+$G35))+'การลงระหว่างเดือน ปี 2026'!AP16) -> #DIV/0! | K35: =((K$18*($F35+$G35))+'การลงระหว่างเดือน ปี 2026'!AQ16) -> #DIV/0! | L35: =((L$18*($F35+$G35))+'การลงระหว่างเดือน ปี 2026'!AR16) -> #DIV/0! | M35: =((M$18*($F35+$G35))+'การลงระหว่างเดือน ปี 2026'!AS16) -> #DIV/0! | N35: =((N$18*($F35+$G35))+'การลงระหว่างเดือน ปี 2026'!AT16) -> #DIV/0! | O35: =((O$18*($F35+$G35))+'การลงระหว่างเดือน ปี 2026'!AU16) -> #DIV/0! | P35: =((P$18*($F35+$G35))+'การลงระหว่างเดือน ปี 2026'!AV16) -> #DIV/0! | ... T35: =((T$18*($F35+$G35))+'การลงระหว่างเดือน ปี 2026'!AZ16) -> #DIV/0! | U35: =SUM(I35:T35) -> #DIV/0! | V35: =I35/$I$18 -> #DIV/0! | W35: =J35/$J$18 -> #DIV/0! | X35: =K35/$K$18 -> #DIV/0! | Y35: =L35/$L$18 -> #DIV/0! | Z35: =M35/$M$18 -> #DIV/0! | AA35: =N35/$N$18 -> #DIV/0! | AB35: =O35/$O$18 -> #DIV/0! | AC35: =P35/$P$18 -> #DIV/0! | AD35: =Q35/$Q$18 -> #DIV/0! | AE35: =R35/$R$18 -> #DIV/0! | AF35: =S35/$S$18 -> #DIV/0! | AG35: =T35/$T$18 -> #DIV/0! | AH35: =U35/$U$18 -> #DIV/0! | AI35: V | AJ35: =IFERROR(U35/E35,0)-1 -> -1
A36: ='งบกำไรขาดทุน ปี 2025'!A36 -> 52000014 | B36: ='งบกำไรขาดทุน ปี 2025'!B36 -> ค่าเช่าอุปกรณ์-เครื่องมือระหว่างสาขา | C36: ='งบกำไรขาดทุน ปี 2025'!O36 -> 0 | D36: =C36/$C$5 -> 0 | E36: =D36*$E$5 -> 0 | F36: =E36/$E$18 -> #DIV/0! | H36: F | I36: =(($D36*$G36)+$D36)+'การลงระหว่างเดือน ปี 2026'!AO17 -> 0 | J36: =(($D36*$G36)+$D36)+'การลงระหว่างเดือน ปี 2026'!AP17 -> 0 | K36: =(($D36*$G36)+$D36)+'การลงระหว่างเดือน ปี 2026'!AQ17 -> 0 | L36: =(($D36*$G36)+$D36)+'การลงระหว่างเดือน ปี 2026'!AR17 -> 0 | M36: =(($D36*$G36)+$D36)+'การลงระหว่างเดือน ปี 2026'!AS17 -> 0 | N36: =(($D36*$G36)+$D36)+'การลงระหว่างเดือน ปี 2026'!AT17 -> 0 | O36: =(($D36*$G36)+$D36)+'การลงระหว่างเดือน ปี 2026'!AU17 -> 0 | P36: =(($D36*$G36)+$D36)+'การลงระหว่างเดือน ปี 2026'!AV17 -> 0 | ... T36: =(($D36*$G36)+$D36)+'การลงระหว่างเดือน ปี 2026'!AZ17 -> 0 | U36: =SUM(I36:T36) -> 0 | V36: =I36/$I$18 -> #DIV/0! | W36: =J36/$J$18 -> #DIV/0! | X36: =K36/$K$18 -> #DIV/0! | Y36: =L36/$L$18 -> #DIV/0! | Z36: =M36/$M$18 -> #DIV/0! | AA36: =N36/$N$18 -> #DIV/0! | AB36: =O36/$O$18 -> #DIV/0! | AC36: =P36/$P$18 -> #DIV/0! | AD36: =Q36/$Q$18 -> #DIV/0! | AE36: =R36/$R$18 -> #DIV/0! | AF36: =S36/$S$18 -> #DIV/0! | AG36: =T36/$T$18 -> #DIV/0! | AH36: =U36/$U$18 -> #DIV/0! | AI36: S | AJ36: =IFERROR(U36/E36,0)-1 -> -1
A37: ='งบกำไรขาดทุน ปี 2025'!A37 -> 61300010 | B37: ='งบกำไรขาดทุน ปี 2025'!B37 -> ค่าเสื่อมราคา - เครื่องมือแพทย์ | C37: ='งบกำไรขาดทุน ปี 2025'!O37 -> 0 | D37: =C37/$C$5 -> 0 | E37: =D37*$E$5 -> 0 | F37: =E37/$E$18 -> #DIV/0! | H37: x | I37: =(($D37*$G37)+$D37)+'การลงระหว่างเดือน ปี 2026'!AO18 -> 0 | J37: =(($D37*$G37)+$D37)+'การลงระหว่างเดือน ปี 2026'!AP18 -> 0 | K37: =(($D37*$G37)+$D37)+'การลงระหว่างเดือน ปี 2026'!AQ18 -> 0 | L37: =(($D37*$G37)+$D37)+'การลงระหว่างเดือน ปี 2026'!AR18 -> 0 | M37: =(($D37*$G37)+$D37)+'การลงระหว่างเดือน ปี 2026'!AS18 -> 0 | N37: =(($D37*$G37)+$D37)+'การลงระหว่างเดือน ปี 2026'!AT18 -> 0 | O37: =(($D37*$G37)+$D37)+'การลงระหว่างเดือน ปี 2026'!AU18 -> 0 | P37: =(($D37*$G37)+$D37)+'การลงระหว่างเดือน ปี 2026'!AV18 -> 0 | ... T37: =(($D37*$G37)+$D37)+'การลงระหว่างเดือน ปี 2026'!AZ18 -> 0 | U37: =SUM(I37:T37) -> 0 | V37: =I37/$I$18 -> #DIV/0! | W37: =J37/$J$18 -> #DIV/0! | X37: =K37/$K$18 -> #DIV/0! | Y37: =L37/$L$18 -> #DIV/0! | Z37: =M37/$M$18 -> #DIV/0! | AA37: =N37/$N$18 -> #DIV/0! | AB37: =O37/$O$18 -> #DIV/0! | AC37: =P37/$P$18 -> #DIV/0! | AD37: =Q37/$Q$18 -> #DIV/0! | AE37: =R37/$R$18 -> #DIV/0! | AF37: =S37/$S$18 -> #DIV/0! | AG37: =T37/$T$18 -> #DIV/0! | AH37: =U37/$U$18 -> #DIV/0! | AI37: F | AJ37: =IFERROR(U37/E37,0)-1 -> -1
A38: ='งบกำไรขาดทุน ปี 2025'!A38 -> 0 | B38: ='งบกำไรขาดทุน ปี 2025'!B38 -> รวมค่าใช้จ่ายในการขาย | C38: ='งบกำไรขาดทุน ปี 2025'!O38 -> 0 | D38: =C38/$C$5 -> 0 | E38: =D38*$E$5 -> 0 | F38: =E38/$E$18 -> #DIV/0! | I38: =SUM(I26:I37) -> #DIV/0! | J38: =SUM(J26:J37) -> #DIV/0! | K38: =SUM(K26:K37) -> #DIV/0! | L38: =SUM(L26:L37) -> #DIV/0! | M38: =SUM(M26:M37) -> #DIV/0! | N38: =SUM(N26:N37) -> #DIV/0! | O38: =SUM(O26:O37) -> #DIV/0! | P38: =SUM(P26:P37) -> #DIV/0! | ... T38: =SUM(T26:T37) -> #DIV/0! | U38: =SUM(U25:U37) -> #DIV/0! | V38: =I38/$I$18 -> #DIV/0! | W38: =J38/$J$18 -> #DIV/0! | X38: =K38/$K$18 -> #DIV/0! | Y38: =L38/$L$18 -> #DIV/0! | Z38: =M38/$M$18 -> #DIV/0! | AA38: =N38/$N$18 -> #DIV/0! | AB38: =O38/$O$18 -> #DIV/0! | AC38: =P38/$P$18 -> #DIV/0! | AD38: =Q38/$Q$18 -> #DIV/0! | AE38: =R38/$R$18 -> #DIV/0! | AF38: =S38/$S$18 -> #DIV/0! | AG38: =T38/$T$18 -> #DIV/0! | AH38: =U38/$U$18 -> #DIV/0! | AJ38: =IFERROR(U38/E38,0)-1 -> -1
A39: ='งบกำไรขาดทุน ปี 2025'!A39 -> 0 | B39: ='งบกำไรขาดทุน ปี 2025'!B39 -> ค่ายานพาหนะ | C39: ='งบกำไรขาดทุน ปี 2025'!O39 -> 0 | AJ39: =IFERROR(U39/E39,0)-1 -> -1
A40: ='งบกำไรขาดทุน ปี 2025'!A40 -> 52000015 | B40: ='งบกำไรขาดทุน ปี 2025'!B40 -> ค่าขนส่งในประเทศ | C40: ='งบกำไรขาดทุน ปี 2025'!O40 -> 0 | D40: =C40/$C$5 -> 0 | E40: =D40*$E$5 -> 0 | F40: =E40/$E$18 -> #DIV/0! | H40: V | I40: =((I$18*($F40+$G40))) -> #DIV/0! | J40: =((J$18*($F40+$G40))) -> #DIV/0! | K40: =((K$18*($F40+$G40))) -> #DIV/0! | L40: =((L$18*($F40+$G40))) -> #DIV/0! | M40: =((M$18*($F40+$G40))) -> #DIV/0! | N40: =((N$18*($F40+$G40))) -> #DIV/0! | O40: =((O$18*($F40+$G40))) -> #DIV/0! | P40: =((P$18*($F40+$G40))) -> #DIV/0! | ... T40: =((T$18*($F40+$G40))) -> #DIV/0! | U40: =SUM(I40:T40) -> #DIV/0! | V40: =I40/$I$18 -> #DIV/0! | W40: =J40/$J$18 -> #DIV/0! | X40: =K40/$K$18 -> #DIV/0! | Y40: =L40/$L$18 -> #DIV/0! | Z40: =M40/$M$18 -> #DIV/0! | AA40: =N40/$N$18 -> #DIV/0! | AB40: =O40/$O$18 -> #DIV/0! | AC40: =P40/$P$18 -> #DIV/0! | AD40: =Q40/$Q$18 -> #DIV/0! | AE40: =R40/$R$18 -> #DIV/0! | AF40: =S40/$S$18 -> #DIV/0! | AG40: =T40/$T$18 -> #DIV/0! | AH40: =U40/$U$18 -> #DIV/0! | AI40: V | AJ40: =IFERROR(U40/E40,0)-1 -> -1
A41: ='งบกำไรขาดทุน ปี 2025'!A41 -> 0 | B41: ='งบกำไรขาดทุน ปี 2025'!B41 -> รวมค่ายานพาหนะ | C41: ='งบกำไรขาดทุน ปี 2025'!O41 -> 0 | D41: =C41/$C$5 -> 0 | E41: =D41*$E$5 -> 0 | F41: =E41/$E$18 -> #DIV/0! | I41: =SUM(I40:I40) -> #DIV/0! | J41: =SUM(J40:J40) -> #DIV/0! | K41: =SUM(K40:K40) -> #DIV/0! | L41: =SUM(L40:L40) -> #DIV/0! | M41: =SUM(M40:M40) -> #DIV/0! | N41: =SUM(N40:N40) -> #DIV/0! | O41: =SUM(O40:O40) -> #DIV/0! | P41: =SUM(P40:P40) -> #DIV/0! | ... T41: =SUM(T40:T40) -> #DIV/0! | U41: =SUM(U39:U40) -> #DIV/0! | V41: =I41/$I$18 -> #DIV/0! | W41: =J41/$J$18 -> #DIV/0! | X41: =K41/$K$18 -> #DIV/0! | Y41: =L41/$L$18 -> #DIV/0! | Z41: =M41/$M$18 -> #DIV/0! | AA41: =N41/$N$18 -> #DIV/0! | AB41: =O41/$O$18 -> #DIV/0! | AC41: =P41/$P$18 -> #DIV/0! | AD41: =Q41/$Q$18 -> #DIV/0! | AE41: =R41/$R$18 -> #DIV/0! | AF41: =S41/$S$18 -> #DIV/0! | AG41: =T41/$T$18 -> #DIV/0! | AH41: =U41/$U$18 -> #DIV/0! | AJ41: =IFERROR(U41/E41,0)-1 -> -1
A42: ='งบกำไรขาดทุน ปี 2025'!A42 -> 0 | B42: ='งบกำไรขาดทุน ปี 2025'!B42 -> รวมต้นทุนขายและค่าใช้จ่ายในการขาย | C42: ='งบกำไรขาดทุน ปี 2025'!O42 -> 0 | D42: =C42/$C$5 -> 0 | E42: =D42*$E$5 -> 0 | F42: =E42/$E$18 -> #DIV/0! | I42: =I24+I38+I41 -> #DIV/0! | J42: =J24+J38+J41 -> #DIV/0! | K42: =K24+K38+K41 -> #DIV/0! | L42: =L24+L38+L41 -> #DIV/0! | M42: =M24+M38+M41 -> #DIV/0! | N42: =N24+N38+N41 -> #DIV/0! | O42: =O24+O38+O41 -> #DIV/0! | P42: =P24+P38+P41 -> #DIV/0! | ... T42: =T24+T38+T41 -> #DIV/0! | U42: =SUM(U24,U38,U41) -> #DIV/0! | V42: =I42/$I$18 -> #DIV/0! | W42: =J42/$J$18 -> #DIV/0! | X42: =K42/$K$18 -> #DIV/0! | Y42: =L42/$L$18 -> #DIV/0! | Z42: =M42/$M$18 -> #DIV/0! | AA42: =N42/$N$18 -> #DIV/0! | AB42: =O42/$O$18 -> #DIV/0! | AC42: =P42/$P$18 -> #DIV/0! | AD42: =Q42/$Q$18 -> #DIV/0! | AE42: =R42/$R$18 -> #DIV/0! | AF42: =S42/$S$18 -> #DIV/0! | AG42: =T42/$T$18 -> #DIV/0! | AH42: =U42/$U$18 -> #DIV/0! | AJ42: =IFERROR(U42/E42,0)-1 -> -1
A43: ='งบกำไรขาดทุน ปี 2025'!A43 -> 0 | B43: ='งบกำไรขาดทุน ปี 2025'!B43 -> ค่าใช้จ่ายในการบริหาร | C43: ='งบกำไรขาดทุน ปี 2025'!O43 -> 0 | AJ43: =IFERROR(U43/E43,0)-1 -> -1
A44: ='งบกำไรขาดทุน ปี 2025'!A44 -> 0 | B44: ='งบกำไรขาดทุน ปี 2025'!B44 -> เงินเดือนและสวัสดิการพนักงาน | C44: ='งบกำไรขาดทุน ปี 2025'!O44 -> 0 | AJ44: =IFERROR(U44/E44,0)-1 -> -1
A45: ='งบกำไรขาดทุน ปี 2025'!A45 -> 60100001 | B45: ='งบกำไรขาดทุน ปี 2025'!B45 -> เงินเดือน | C45: ='งบกำไรขาดทุน ปี 2025'!O45 -> 0 | D45: =C45/$C$5 -> 0 | E45: =D45*$E$5 -> 0 | F45: =E45/$E$18 -> #DIV/0! | G45: 0.04 | H45: F | I45: =(($D45*$G45)+$D45)+'การลงระหว่างเดือน ปี 2026'!AO20 -> 0 | J45: =(($D45*$G45)+$D45)+'การลงระหว่างเดือน ปี 2026'!AP20 -> 0 | K45: =(($D45*$G45)+$D45)+'การลงระหว่างเดือน ปี 2026'!AQ20 -> 0 | L45: =(($D45*$G45)+$D45)+'การลงระหว่างเดือน ปี 2026'!AR20 -> 0 | M45: =(($D45*$G45)+$D45)+'การลงระหว่างเดือน ปี 2026'!AS20 -> 0 | N45: =(($D45*$G45)+$D45)+'การลงระหว่างเดือน ปี 2026'!AT20 -> 0 | O45: =(($D45*$G45)+$D45)+'การลงระหว่างเดือน ปี 2026'!AU20 -> 0 | P45: =(($D45*$G45)+$D45)+'การลงระหว่างเดือน ปี 2026'!AV20 -> 0 | ... T45: =(($D45*$G45)+$D45)+'การลงระหว่างเดือน ปี 2026'!AZ20 -> 0 | U45: =SUM(I45:T45) -> 0 | V45: =I45/$I$18 -> #DIV/0! | W45: =J45/$J$18 -> #DIV/0! | X45: =K45/$K$18 -> #DIV/0! | Y45: =L45/$L$18 -> #DIV/0! | Z45: =M45/$M$18 -> #DIV/0! | AA45: =N45/$N$18 -> #DIV/0! | AB45: =O45/$O$18 -> #DIV/0! | AC45: =P45/$P$18 -> #DIV/0! | AD45: =Q45/$Q$18 -> #DIV/0! | AE45: =R45/$R$18 -> #DIV/0! | AF45: =S45/$S$18 -> #DIV/0! | AG45: =T45/$T$18 -> #DIV/0! | AH45: =U45/$U$18 -> #DIV/0! | AI45: S | AJ45: =IFERROR(U45/E45,0)-1 -> -1
A46: ='งบกำไรขาดทุน ปี 2025'!A46 -> 52000009 | B46: ='งบกำไรขาดทุน ปี 2025'!B46 -> ค่าหัวหน้าฝ่ายวิชาการแพทย์ | C46: ='งบกำไรขาดทุน ปี 2025'!O46 -> 0 | D46: =C46/$C$5 -> 0 | E46: =D46*$E$5 -> 0 | F46: =E46/$E$18 -> #DIV/0! | G46: =$G$45 -> 0.04 | H46: F | I46: =(($D46*$G46)+$D46)+'การลงระหว่างเดือน ปี 2026'!AO21 -> 0 | J46: =(($D46*$G46)+$D46)+'การลงระหว่างเดือน ปี 2026'!AP21 -> 0 | K46: =(($D46*$G46)+$D46)+'การลงระหว่างเดือน ปี 2026'!AQ21 -> 0 | L46: =(($D46*$G46)+$D46)+'การลงระหว่างเดือน ปี 2026'!AR21 -> 0 | M46: =(($D46*$G46)+$D46)+'การลงระหว่างเดือน ปี 2026'!AS21 -> 0 | N46: =(($D46*$G46)+$D46)+'การลงระหว่างเดือน ปี 2026'!AT21 -> 0 | O46: =(($D46*$G46)+$D46)+'การลงระหว่างเดือน ปี 2026'!AU21 -> 0 | P46: =(($D46*$G46)+$D46)+'การลงระหว่างเดือน ปี 2026'!AV21 -> 0 | ... T46: =(($D46*$G46)+$D46)+'การลงระหว่างเดือน ปี 2026'!AZ21 -> 0 | U46: =SUM(I46:T46) -> 0 | V46: =I46/$I$18 -> #DIV/0! | W46: =J46/$J$18 -> #DIV/0! | X46: =K46/$K$18 -> #DIV/0! | Y46: =L46/$L$18 -> #DIV/0! | Z46: =M46/$M$18 -> #DIV/0! | AA46: =N46/$N$18 -> #DIV/0! | AB46: =O46/$O$18 -> #DIV/0! | AC46: =P46/$P$18 -> #DIV/0! | AD46: =Q46/$Q$18 -> #DIV/0! | AE46: =R46/$R$18 -> #DIV/0! | AF46: =S46/$S$18 -> #DIV/0! | AG46: =T46/$T$18 -> #DIV/0! | AH46: =U46/$U$18 -> #DIV/0! | AI46: S | AJ46: =IFERROR(U46/E46,0)-1 -> -1
A47: ='งบกำไรขาดทุน ปี 2025'!A47 -> 52000012 | B47: ='งบกำไรขาดทุน ปี 2025'!B47 -> เงินเดือนพยาบาล | C47: ='งบกำไรขาดทุน ปี 2025'!O47 -> 0 | D47: =C47/$C$5 -> 0 | E47: =D47*$E$5 -> 0 | F47: =E47/$E$18 -> #DIV/0! | G47: =$G$45 -> 0.04 | H47: F | I47: =(($D47*$G47)+$D47)+'การลงระหว่างเดือน ปี 2026'!AO22 -> 0 | J47: =(($D47*$G47)+$D47)+'การลงระหว่างเดือน ปี 2026'!AP22 -> 0 | K47: =(($D47*$G47)+$D47)+'การลงระหว่างเดือน ปี 2026'!AQ22 -> 0 | L47: =(($D47*$G47)+$D47)+'การลงระหว่างเดือน ปี 2026'!AR22 -> 0 | M47: =(($D47*$G47)+$D47)+'การลงระหว่างเดือน ปี 2026'!AS22 -> 0 | N47: =(($D47*$G47)+$D47)+'การลงระหว่างเดือน ปี 2026'!AT22 -> 0 | O47: =(($D47*$G47)+$D47)+'การลงระหว่างเดือน ปี 2026'!AU22 -> 0 | P47: =(($D47*$G47)+$D47)+'การลงระหว่างเดือน ปี 2026'!AV22 -> 0 | ... T47: =(($D47*$G47)+$D47)+'การลงระหว่างเดือน ปี 2026'!AZ22 -> 0 | U47: =SUM(I47:T47) -> 0 | V47: =I47/$I$18 -> #DIV/0! | W47: =J47/$J$18 -> #DIV/0! | X47: =K47/$K$18 -> #DIV/0! | Y47: =L47/$L$18 -> #DIV/0! | Z47: =M47/$M$18 -> #DIV/0! | AA47: =N47/$N$18 -> #DIV/0! | AB47: =O47/$O$18 -> #DIV/0! | AC47: =P47/$P$18 -> #DIV/0! | AD47: =Q47/$Q$18 -> #DIV/0! | AE47: =R47/$R$18 -> #DIV/0! | AF47: =S47/$S$18 -> #DIV/0! | AG47: =T47/$T$18 -> #DIV/0! | AH47: =U47/$U$18 -> #DIV/0! | AI47: S | AJ47: =IFERROR(U47/E47,0)-1 -> -1
A48: ='งบกำไรขาดทุน ปี 2025'!A48 -> 52000013 | B48: ='งบกำไรขาดทุน ปี 2025'!B48 -> ค่าพยาบาลพิเศษ | C48: ='งบกำไรขาดทุน ปี 2025'!O48 -> 0 | D48: =C48/$C$5 -> 0 | E48: =D48*$E$5 -> 0 | F48: =E48/$E$18 -> #DIV/0! | G48: =$G$45 -> 0.04 | H48: F | I48: =(($D48*$G48)+$D48) -> 0 | J48: =(($D48*$G48)+$D48) -> 0 | K48: =(($D48*$G48)+$D48) -> 0 | L48: =(($D48*$G48)+$D48) -> 0 | M48: =(($D48*$G48)+$D48) -> 0 | N48: =(($D48*$G48)+$D48) -> 0 | O48: =(($D48*$G48)+$D48) -> 0 | P48: =(($D48*$G48)+$D48) -> 0 | ... T48: =(($D48*$G48)+$D48) -> 0 | U48: =SUM(I48:T48) -> 0 | V48: =I48/$I$18 -> #DIV/0! | W48: =J48/$J$18 -> #DIV/0! | X48: =K48/$K$18 -> #DIV/0! | Y48: =L48/$L$18 -> #DIV/0! | Z48: =M48/$M$18 -> #DIV/0! | AA48: =N48/$N$18 -> #DIV/0! | AB48: =O48/$O$18 -> #DIV/0! | AC48: =P48/$P$18 -> #DIV/0! | AD48: =Q48/$Q$18 -> #DIV/0! | AE48: =R48/$R$18 -> #DIV/0! | AF48: =S48/$S$18 -> #DIV/0! | AG48: =T48/$T$18 -> #DIV/0! | AH48: =U48/$U$18 -> #DIV/0! | AI48: S | AJ48: =IFERROR(U48/E48,0)-1 -> -1
A49: ='งบกำไรขาดทุน ปี 2025'!A49 -> 52000016 | B49: ='งบกำไรขาดทุน ปี 2025'!B49 -> ค่าเช่ายานพาหนะ | C49: ='งบกำไรขาดทุน ปี 2025'!O49 -> 0 | D49: =C49/$C$5 -> 0 | E49: =D49*$E$5 -> 0 | F49: =E49/$E$18 -> #DIV/0! | G49: =$G$45 -> 0.04 | H49: F | I49: =(($D49*$G49)+$D49)+'การลงระหว่างเดือน ปี 2026'!AO23 -> 0 | J49: =(($D49*$G49)+$D49)+'การลงระหว่างเดือน ปี 2026'!AP23 -> 0 | K49: =(($D49*$G49)+$D49)+'การลงระหว่างเดือน ปี 2026'!AQ23 -> 0 | L49: =(($D49*$G49)+$D49)+'การลงระหว่างเดือน ปี 2026'!AR23 -> 0 | M49: =(($D49*$G49)+$D49)+'การลงระหว่างเดือน ปี 2026'!AS23 -> 0 | N49: =(($D49*$G49)+$D49)+'การลงระหว่างเดือน ปี 2026'!AT23 -> 0 | O49: =(($D49*$G49)+$D49)+'การลงระหว่างเดือน ปี 2026'!AU23 -> 0 | P49: =(($D49*$G49)+$D49)+'การลงระหว่างเดือน ปี 2026'!AV23 -> 0 | ... T49: =(($D49*$G49)+$D49)+'การลงระหว่างเดือน ปี 2026'!AZ23 -> 0 | U49: =SUM(I49:T49) -> 0 | V49: =I49/$I$18 -> #DIV/0! | W49: =J49/$J$18 -> #DIV/0! | X49: =K49/$K$18 -> #DIV/0! | Y49: =L49/$L$18 -> #DIV/0! | Z49: =M49/$M$18 -> #DIV/0! | AA49: =N49/$N$18 -> #DIV/0! | AB49: =O49/$O$18 -> #DIV/0! | AC49: =P49/$P$18 -> #DIV/0! | AD49: =Q49/$Q$18 -> #DIV/0! | AE49: =R49/$R$18 -> #DIV/0! | AF49: =S49/$S$18 -> #DIV/0! | AG49: =T49/$T$18 -> #DIV/0! | AH49: =U49/$U$18 -> #DIV/0! | AI49: F | AJ49: =IFERROR(U49/E49,0)-1 -> -1
A50: ='งบกำไรขาดทุน ปี 2025'!A50 -> 60100002 | B50: ='งบกำไรขาดทุน ปี 2025'!B50 -> ค่าวัดระดับ | C50: ='งบกำไรขาดทุน ปี 2025'!O50 -> 0 | D50: =C50/$C$5 -> 0 | E50: =D50*$E$5 -> 0 | F50: =E50/$E$18 -> #DIV/0! | G50: =$G$45 -> 0.04 | H50: F | I50: =(($D50*$G50)+$D50)+'การลงระหว่างเดือน ปี 2026'!AO24 -> 0 | J50: =(($D50*$G50)+$D50)+'การลงระหว่างเดือน ปี 2026'!AP24 -> 0 | K50: =(($D50*$G50)+$D50)+'การลงระหว่างเดือน ปี 2026'!AQ24 -> 0 | L50: =(($D50*$G50)+$D50)+'การลงระหว่างเดือน ปี 2026'!AR24 -> 0 | M50: =(($D50*$G50)+$D50)+'การลงระหว่างเดือน ปี 2026'!AS24 -> 0 | N50: =(($D50*$G50)+$D50)+'การลงระหว่างเดือน ปี 2026'!AT24 -> 0 | O50: =(($D50*$G50)+$D50)+'การลงระหว่างเดือน ปี 2026'!AU24 -> 0 | P50: =(($D50*$G50)+$D50)+'การลงระหว่างเดือน ปี 2026'!AV24 -> 0 | ... T50: =(($D50*$G50)+$D50)+'การลงระหว่างเดือน ปี 2026'!AZ24 -> 0 | U50: =SUM(I50:T50) -> 0 | V50: =I50/$I$18 -> #DIV/0! | W50: =J50/$J$18 -> #DIV/0! | X50: =K50/$K$18 -> #DIV/0! | Y50: =L50/$L$18 -> #DIV/0! | Z50: =M50/$M$18 -> #DIV/0! | AA50: =N50/$N$18 -> #DIV/0! | AB50: =O50/$O$18 -> #DIV/0! | AC50: =P50/$P$18 -> #DIV/0! | AD50: =Q50/$Q$18 -> #DIV/0! | AE50: =R50/$R$18 -> #DIV/0! | AF50: =S50/$S$18 -> #DIV/0! | AG50: =T50/$T$18 -> #DIV/0! | AH50: =U50/$U$18 -> #DIV/0! | AI50: S | AJ50: =IFERROR(U50/E50,0)-1 -> -1
A51: ='งบกำไรขาดทุน ปี 2025'!A51 -> 60100003 | B51: ='งบกำไรขาดทุน ปี 2025'!B51 -> ค่าล่วงเวลา | C51: ='งบกำไรขาดทุน ปี 2025'!O51 -> 0 | D51: =C51/$C$5 -> 0 | E51: =D51*$E$5 -> 0 | F51: =E51/$E$18 -> #DIV/0! | H51: V | I51: =((I$18*($F51+$G51))) -> #DIV/0! | J51: =((J$18*($F51+$G51))) -> #DIV/0! | K51: =((K$18*($F51+$G51))) -> #DIV/0! | L51: =((L$18*($F51+$G51))) -> #DIV/0! | M51: =((M$18*($F51+$G51))) -> #DIV/0! | N51: =((N$18*($F51+$G51))) -> #DIV/0! | O51: =((O$18*($F51+$G51))) -> #DIV/0! | P51: =((P$18*($F51+$G51))) -> #DIV/0! | ... T51: =((T$18*($F51+$G51))) -> #DIV/0! | U51: =SUM(I51:T51) -> #DIV/0! | V51: =I51/$I$18 -> #DIV/0! | W51: =J51/$J$18 -> #DIV/0! | X51: =K51/$K$18 -> #DIV/0! | Y51: =L51/$L$18 -> #DIV/0! | Z51: =M51/$M$18 -> #DIV/0! | AA51: =N51/$N$18 -> #DIV/0! | AB51: =O51/$O$18 -> #DIV/0! | AC51: =P51/$P$18 -> #DIV/0! | AD51: =Q51/$Q$18 -> #DIV/0! | AE51: =R51/$R$18 -> #DIV/0! | AF51: =S51/$S$18 -> #DIV/0! | AG51: =T51/$T$18 -> #DIV/0! | AH51: =U51/$U$18 -> #DIV/0! | AI51: V | AJ51: =IFERROR(U51/E51,0)-1 -> -1
A52: ='งบกำไรขาดทุน ปี 2025'!A52 -> 60100004 | B52: ='งบกำไรขาดทุน ปี 2025'!B52 -> โบนัส | C52: ='งบกำไรขาดทุน ปี 2025'!O52 -> 0 | D52: =C52/$C$5 -> 0 | E52: =D52*$E$5 -> 0 | F52: =E52/$E$18 -> #DIV/0! | H52: V | I52: =((I$18*($F52+$G52))) -> #DIV/0! | J52: =((J$18*($F52+$G52))) -> #DIV/0! | K52: =((K$18*($F52+$G52))) -> #DIV/0! | L52: =((L$18*($F52+$G52))) -> #DIV/0! | M52: =((M$18*($F52+$G52))) -> #DIV/0! | N52: =((N$18*($F52+$G52))) -> #DIV/0! | O52: =((O$18*($F52+$G52))) -> #DIV/0! | P52: =((P$18*($F52+$G52))) -> #DIV/0! | ... T52: =((T$18*($F52+$G52))) -> #DIV/0! | U52: =SUM(I52:T52) -> #DIV/0! | V52: =I52/$I$18 -> #DIV/0! | W52: =J52/$J$18 -> #DIV/0! | X52: =K52/$K$18 -> #DIV/0! | Y52: =L52/$L$18 -> #DIV/0! | Z52: =M52/$M$18 -> #DIV/0! | AA52: =N52/$N$18 -> #DIV/0! | AB52: =O52/$O$18 -> #DIV/0! | AC52: =P52/$P$18 -> #DIV/0! | AD52: =Q52/$Q$18 -> #DIV/0! | AE52: =R52/$R$18 -> #DIV/0! | AF52: =S52/$S$18 -> #DIV/0! | AG52: =T52/$T$18 -> #DIV/0! | AH52: =U52/$U$18 -> #DIV/0! | AI52: V | AJ52: =IFERROR(U52/E52,0)-1 -> -1
A53: ='งบกำไรขาดทุน ปี 2025'!A53 -> 60100005 | B53: ='งบกำไรขาดทุน ปี 2025'!B53 -> เงินกองทุนสำรองเลี้ยงชีพ | C53: ='งบกำไรขาดทุน ปี 2025'!O53 -> 0 | D53: =C53/$C$5 -> 0 | E53: =D53*$E$5 -> 0 | F53: =E53/$E$18 -> #DIV/0! | G53: 0.02 | H53: F | I53: =(($D53*$G53)+$D53)+'การลงระหว่างเดือน ปี 2026'!AO25 -> 0 | J53: =(($D53*$G53)+$D53)+'การลงระหว่างเดือน ปี 2026'!AP25 -> 0 | K53: =(($D53*$G53)+$D53)+'การลงระหว่างเดือน ปี 2026'!AQ25 -> 0 | L53: =(($D53*$G53)+$D53)+'การลงระหว่างเดือน ปี 2026'!AR25 -> 0 | M53: =(($D53*$G53)+$D53)+'การลงระหว่างเดือน ปี 2026'!AS25 -> 0 | N53: =(($D53*$G53)+$D53)+'การลงระหว่างเดือน ปี 2026'!AT25 -> 0 | O53: =(($D53*$G53)+$D53)+'การลงระหว่างเดือน ปี 2026'!AU25 -> 0 | P53: =(($D53*$G53)+$D53)+'การลงระหว่างเดือน ปี 2026'!AV25 -> 0 | ... T53: =(($D53*$G53)+$D53)+'การลงระหว่างเดือน ปี 2026'!AZ25 -> 0 | U53: =SUM(I53:T53) -> 0 | V53: =I53/$I$18 -> #DIV/0! | W53: =J53/$J$18 -> #DIV/0! | X53: =K53/$K$18 -> #DIV/0! | Y53: =L53/$L$18 -> #DIV/0! | Z53: =M53/$M$18 -> #DIV/0! | AA53: =N53/$N$18 -> #DIV/0! | AB53: =O53/$O$18 -> #DIV/0! | AC53: =P53/$P$18 -> #DIV/0! | AD53: =Q53/$Q$18 -> #DIV/0! | AE53: =R53/$R$18 -> #DIV/0! | AF53: =S53/$S$18 -> #DIV/0! | AG53: =T53/$T$18 -> #DIV/0! | AH53: =U53/$U$18 -> #DIV/0! | AI53: S | AJ53: =IFERROR(U53/E53,0)-1 -> -1
A54: ='งบกำไรขาดทุน ปี 2025'!A54 -> 60100007 | B54: ='งบกำไรขาดทุน ปี 2025'!B54 -> ค่าสวัสดิการพนักงาน | C54: ='งบกำไรขาดทุน ปี 2025'!O54 -> 0 | D54: =C54/$C$5 -> 0 | E54: =D54*$E$5 -> 0 | F54: =E54/$E$18 -> #DIV/0! | H54: V | I54: =((I$18*($F54+$G54)))+'การลงระหว่างเดือน ปี 2026'!AO26 -> #DIV/0! | J54: =((J$18*($F54+$G54)))+'การลงระหว่างเดือน ปี 2026'!AP26 -> #DIV/0! | K54: =((K$18*($F54+$G54)))+'การลงระหว่างเดือน ปี 2026'!AQ26 -> #DIV/0! | L54: =((L$18*($F54+$G54)))+'การลงระหว่างเดือน ปี 2026'!AR26 -> #DIV/0! | M54: =((M$18*($F54+$G54)))+'การลงระหว่างเดือน ปี 2026'!AS26 -> #DIV/0! | N54: =((N$18*($F54+$G54)))+'การลงระหว่างเดือน ปี 2026'!AT26 -> #DIV/0! | O54: =((O$18*($F54+$G54)))+'การลงระหว่างเดือน ปี 2026'!AU26 -> #DIV/0! | P54: =((P$18*($F54+$G54)))+'การลงระหว่างเดือน ปี 2026'!AV26 -> #DIV/0! | ... T54: =((T$18*($F54+$G54)))+'การลงระหว่างเดือน ปี 2026'!AZ26 -> #DIV/0! | U54: =SUM(I54:T54) -> #DIV/0! | V54: =I54/$I$18 -> #DIV/0! | W54: =J54/$J$18 -> #DIV/0! | X54: =K54/$K$18 -> #DIV/0! | Y54: =L54/$L$18 -> #DIV/0! | Z54: =M54/$M$18 -> #DIV/0! | AA54: =N54/$N$18 -> #DIV/0! | AB54: =O54/$O$18 -> #DIV/0! | AC54: =P54/$P$18 -> #DIV/0! | AD54: =Q54/$Q$18 -> #DIV/0! | AE54: =R54/$R$18 -> #DIV/0! | AF54: =S54/$S$18 -> #DIV/0! | AG54: =T54/$T$18 -> #DIV/0! | AH54: =U54/$U$18 -> #DIV/0! | AI54: V | AJ54: =IFERROR(U54/E54,0)-1 -> -1
A55: ='งบกำไรขาดทุน ปี 2025'!A55 -> 60100008 | B55: ='งบกำไรขาดทุน ปี 2025'!B55 -> เงินกองทุนประกันสังคม | C55: ='งบกำไรขาดทุน ปี 2025'!O55 -> 0 | D55: =C55/$C$5 -> 0 | E55: =D55*$E$5 -> 0 | F55: =E55/$E$18 -> #DIV/0! | G55: =$G$45 -> 0.04 | H55: F | I55: =(($D55*$G55)+$D55)+'การลงระหว่างเดือน ปี 2026'!AO27 -> 0 | J55: =(($D55*$G55)+$D55)+'การลงระหว่างเดือน ปี 2026'!AP27 -> 0 | K55: =(($D55*$G55)+$D55)+'การลงระหว่างเดือน ปี 2026'!AQ27 -> 0 | L55: =(($D55*$G55)+$D55)+'การลงระหว่างเดือน ปี 2026'!AR27 -> 0 | M55: =(($D55*$G55)+$D55)+'การลงระหว่างเดือน ปี 2026'!AS27 -> 0 | N55: =(($D55*$G55)+$D55)+'การลงระหว่างเดือน ปี 2026'!AT27 -> 0 | O55: =(($D55*$G55)+$D55)+'การลงระหว่างเดือน ปี 2026'!AU27 -> 0 | P55: =(($D55*$G55)+$D55)+'การลงระหว่างเดือน ปี 2026'!AV27 -> 0 | ... T55: =(($D55*$G55)+$D55)+'การลงระหว่างเดือน ปี 2026'!AZ27 -> 0 | U55: =SUM(I55:T55) -> 0 | V55: =I55/$I$18 -> #DIV/0! | W55: =J55/$J$18 -> #DIV/0! | X55: =K55/$K$18 -> #DIV/0! | Y55: =L55/$L$18 -> #DIV/0! | Z55: =M55/$M$18 -> #DIV/0! | AA55: =N55/$N$18 -> #DIV/0! | AB55: =O55/$O$18 -> #DIV/0! | AC55: =P55/$P$18 -> #DIV/0! | AD55: =Q55/$Q$18 -> #DIV/0! | AE55: =R55/$R$18 -> #DIV/0! | AF55: =S55/$S$18 -> #DIV/0! | AG55: =T55/$T$18 -> #DIV/0! | AH55: =U55/$U$18 -> #DIV/0! | AI55: S | AJ55: =IFERROR(U55/E55,0)-1 -> -1
A56: ='งบกำไรขาดทุน ปี 2025'!A56 -> 60100009 | B56: ='งบกำไรขาดทุน ปี 2025'!B56 -> ค่าเบี้ยประกันชีวิตพนักงาน | C56: ='งบกำไรขาดทุน ปี 2025'!O56 -> 0 | D56: =C56/$C$5 -> 0 | E56: =D56*$E$5 -> 0 | F56: =E56/$E$18 -> #DIV/0! | G56: =$G$45 -> 0.04 | H56: F | I56: =(($D56*$G56)+$D56) -> 0 | J56: =(($D56*$G56)+$D56) -> 0 | K56: =(($D56*$G56)+$D56) -> 0 | L56: =(($D56*$G56)+$D56) -> 0 | M56: =(($D56*$G56)+$D56) -> 0 | N56: =(($D56*$G56)+$D56) -> 0 | O56: =(($D56*$G56)+$D56) -> 0 | P56: =(($D56*$G56)+$D56) -> 0 | ... T56: =(($D56*$G56)+$D56) -> 0 | U56: =SUM(I56:T56) -> 0 | V56: =I56/$I$18 -> #DIV/0! | W56: =J56/$J$18 -> #DIV/0! | X56: =K56/$K$18 -> #DIV/0! | Y56: =L56/$L$18 -> #DIV/0! | Z56: =M56/$M$18 -> #DIV/0! | AA56: =N56/$N$18 -> #DIV/0! | AB56: =O56/$O$18 -> #DIV/0! | AC56: =P56/$P$18 -> #DIV/0! | AD56: =Q56/$Q$18 -> #DIV/0! | AE56: =R56/$R$18 -> #DIV/0! | AF56: =S56/$S$18 -> #DIV/0! | AG56: =T56/$T$18 -> #DIV/0! | AH56: =U56/$U$18 -> #DIV/0! | AI56: S | AJ56: =IFERROR(U56/E56,0)-1 -> -1
A57: ='งบกำไรขาดทุน ปี 2025'!A57 -> 60100010 | B57: ='งบกำไรขาดทุน ปี 2025'!B57 -> ค่าเงินเดือน,โอที โอนย้ายระหว่างสาขา | C57: ='งบกำไรขาดทุน ปี 2025'!O57 -> 0 | D57: =C57/$C$5 -> 0 | E57: =D57*$E$5 -> 0 | F57: =E57/$E$18 -> #DIV/0! | G57: =$G$45 -> 0.04 | H57: F | I57: =(($D57*$G57)+$D57) -> 0 | J57: =(($D57*$G57)+$D57) -> 0 | K57: =(($D57*$G57)+$D57) -> 0 | L57: =(($D57*$G57)+$D57) -> 0 | M57: =(($D57*$G57)+$D57) -> 0 | N57: =(($D57*$G57)+$D57) -> 0 | O57: =(($D57*$G57)+$D57) -> 0 | P57: =(($D57*$G57)+$D57) -> 0 | ... T57: =(($D57*$G57)+$D57) -> 0 | U57: =SUM(I57:T57) -> 0 | V57: =I57/$I$18 -> #DIV/0! | W57: =J57/$J$18 -> #DIV/0! | X57: =K57/$K$18 -> #DIV/0! | Y57: =L57/$L$18 -> #DIV/0! | Z57: =M57/$M$18 -> #DIV/0! | AA57: =N57/$N$18 -> #DIV/0! | AB57: =O57/$O$18 -> #DIV/0! | AC57: =P57/$P$18 -> #DIV/0! | AD57: =Q57/$Q$18 -> #DIV/0! | AE57: =R57/$R$18 -> #DIV/0! | AF57: =S57/$S$18 -> #DIV/0! | AG57: =T57/$T$18 -> #DIV/0! | AH57: =U57/$U$18 -> #DIV/0! | AI57: F | AJ57: =IFERROR(U57/E57,0)-1 -> -1
A58: ='งบกำไรขาดทุน ปี 2025'!A58 -> 60100011 | B58: ='งบกำไรขาดทุน ปี 2025'!B58 -> ค่าแรงงาน | C58: ='งบกำไรขาดทุน ปี 2025'!O58 -> 0 | D58: =C58/$C$5 -> 0 | E58: =D58*$E$5 -> 0 | F58: =E58/$E$18 -> #DIV/0! | G58: =$G$45 -> 0.04 | H58: F | I58: =(($D58*$G58)+$D58) -> 0 | J58: =(($D58*$G58)+$D58) -> 0 | K58: =(($D58*$G58)+$D58) -> 0 | L58: =(($D58*$G58)+$D58) -> 0 | M58: =(($D58*$G58)+$D58) -> 0 | N58: =(($D58*$G58)+$D58) -> 0 | O58: =(($D58*$G58)+$D58) -> 0 | P58: =(($D58*$G58)+$D58) -> 0 | ... T58: =(($D58*$G58)+$D58) -> 0 | U58: =SUM(I58:T58) -> 0 | V58: =I58/$I$18 -> #DIV/0! | W58: =J58/$J$18 -> #DIV/0! | X58: =K58/$K$18 -> #DIV/0! | Y58: =L58/$L$18 -> #DIV/0! | Z58: =M58/$M$18 -> #DIV/0! | AA58: =N58/$N$18 -> #DIV/0! | AB58: =O58/$O$18 -> #DIV/0! | AC58: =P58/$P$18 -> #DIV/0! | AD58: =Q58/$Q$18 -> #DIV/0! | AE58: =R58/$R$18 -> #DIV/0! | AF58: =S58/$S$18 -> #DIV/0! | AG58: =T58/$T$18 -> #DIV/0! | AH58: =U58/$U$18 -> #DIV/0! | AI58: S | AJ58: =IFERROR(U58/E58,0)-1 -> -1
A59: ='งบกำไรขาดทุน ปี 2025'!A59 -> 60100012 | B59: ='งบกำไรขาดทุน ปี 2025'!B59 -> ค่า Incentive | C59: ='งบกำไรขาดทุน ปี 2025'!O59 -> 0 | D59: =C59/$C$5 -> 0 | E59: =D59*$E$5 -> 0 | F59: =E59/$E$18 -> #DIV/0! | H59: V | I59: =((I$18*($F59+$G59))) -> #DIV/0! | J59: =((J$18*($F59+$G59))) -> #DIV/0! | K59: =((K$18*($F59+$G59))) -> #DIV/0! | L59: =((L$18*($F59+$G59))) -> #DIV/0! | M59: =((M$18*($F59+$G59))) -> #DIV/0! | N59: =((N$18*($F59+$G59))) -> #DIV/0! | O59: =((O$18*($F59+$G59))) -> #DIV/0! | P59: =((P$18*($F59+$G59))) -> #DIV/0! | ... T59: =((T$18*($F59+$G59))) -> #DIV/0! | U59: =SUM(I59:T59) -> #DIV/0! | V59: =I59/$I$18 -> #DIV/0! | W59: =J59/$J$18 -> #DIV/0! | X59: =K59/$K$18 -> #DIV/0! | Y59: =L59/$L$18 -> #DIV/0! | Z59: =M59/$M$18 -> #DIV/0! | AA59: =N59/$N$18 -> #DIV/0! | AB59: =O59/$O$18 -> #DIV/0! | AC59: =P59/$P$18 -> #DIV/0! | AD59: =Q59/$Q$18 -> #DIV/0! | AE59: =R59/$R$18 -> #DIV/0! | AF59: =S59/$S$18 -> #DIV/0! | AG59: =T59/$T$18 -> #DIV/0! | AH59: =U59/$U$18 -> #DIV/0! | AI59: V | AJ59: =IFERROR(U59/E59,0)-1 -> -1
A60: ='งบกำไรขาดทุน ปี 2025'!A60 -> 60100013 | B60: ='งบกำไรขาดทุน ปี 2025'!B60 -> ค่า GF | C60: ='งบกำไรขาดทุน ปี 2025'!O60 -> 0 | D60: =C60/$C$5 -> 0 | E60: =D60*$E$5 -> 0 | F60: =E60/$E$18 -> #DIV/0! | H60: V | I60: =((I$18*($F60+$G60))) -> #DIV/0! | J60: =((J$18*($F60+$G60))) -> #DIV/0! | K60: =((K$18*($F60+$G60))) -> #DIV/0! | L60: =((L$18*($F60+$G60))) -> #DIV/0! | M60: =((M$18*($F60+$G60))) -> #DIV/0! | N60: =((N$18*($F60+$G60))) -> #DIV/0! | O60: =((O$18*($F60+$G60))) -> #DIV/0! | P60: =((P$18*($F60+$G60))) -> #DIV/0! | ... T60: =((T$18*($F60+$G60))) -> #DIV/0! | U60: =SUM(I60:T60) -> #DIV/0! | V60: =I60/$I$18 -> #DIV/0! | W60: =J60/$J$18 -> #DIV/0! | X60: =K60/$K$18 -> #DIV/0! | Y60: =L60/$L$18 -> #DIV/0! | Z60: =M60/$M$18 -> #DIV/0! | AA60: =N60/$N$18 -> #DIV/0! | AB60: =O60/$O$18 -> #DIV/0! | AC60: =P60/$P$18 -> #DIV/0! | AD60: =Q60/$Q$18 -> #DIV/0! | AE60: =R60/$R$18 -> #DIV/0! | AF60: =S60/$S$18 -> #DIV/0! | AG60: =T60/$T$18 -> #DIV/0! | AH60: =U60/$U$18 -> #DIV/0! | AI60: V | AJ60: =IFERROR(U60/E60,0)-1 -> -1
A61: ='งบกำไรขาดทุน ปี 2025'!A61 -> 60100014 | B61: ='งบกำไรขาดทุน ปี 2025'!B61 -> ค่าตอบแทนและค่าเบี้ยประชุมกรรมการ | C61: ='งบกำไรขาดทุน ปี 2025'!O61 -> 0 | D61: =C61/$C$5 -> 0 | E61: =D61*$E$5 -> 0 | F61: =E61/$E$18 -> #DIV/0! | G61: =$G$45 -> 0.04 | H61: F | I61: =(($D61*$G61)+$D61) -> 0 | J61: =(($D61*$G61)+$D61) -> 0 | K61: =(($D61*$G61)+$D61) -> 0 | L61: =(($D61*$G61)+$D61) -> 0 | M61: =(($D61*$G61)+$D61) -> 0 | N61: =(($D61*$G61)+$D61) -> 0 | O61: =(($D61*$G61)+$D61) -> 0 | P61: =(($D61*$G61)+$D61) -> 0 | ... T61: =(($D61*$G61)+$D61) -> 0 | U61: =SUM(I61:T61) -> 0 | V61: =I61/$I$18 -> #DIV/0! | W61: =J61/$J$18 -> #DIV/0! | X61: =K61/$K$18 -> #DIV/0! | Y61: =L61/$L$18 -> #DIV/0! | Z61: =M61/$M$18 -> #DIV/0! | AA61: =N61/$N$18 -> #DIV/0! | AB61: =O61/$O$18 -> #DIV/0! | AC61: =P61/$P$18 -> #DIV/0! | AD61: =Q61/$Q$18 -> #DIV/0! | AE61: =R61/$R$18 -> #DIV/0! | AF61: =S61/$S$18 -> #DIV/0! | AG61: =T61/$T$18 -> #DIV/0! | AH61: =U61/$U$18 -> #DIV/0! | AI61: F | AJ61: =IFERROR(U61/E61,0)-1 -> -1
A62: ='งบกำไรขาดทุน ปี 2025'!A62 -> 60100015 | B62: ='งบกำไรขาดทุน ปี 2025'!B62 -> ต้นทุนบริการผลประโยชน์พนักงาน | C62: ='งบกำไรขาดทุน ปี 2025'!O62 -> 0 | D62: =C62/$C$5 -> 0 | E62: =D62*$E$5 -> 0 | F62: =E62/$E$18 -> #DIV/0! | G62: =$G$45 -> 0.04 | H62: F | I62: =(($D62*$G62)+$D62) -> 0 | J62: =(($D62*$G62)+$D62) -> 0 | K62: =(($D62*$G62)+$D62) -> 0 | L62: =(($D62*$G62)+$D62) -> 0 | M62: =(($D62*$G62)+$D62) -> 0 | N62: =(($D62*$G62)+$D62) -> 0 | O62: =(($D62*$G62)+$D62) -> 0 | P62: =(($D62*$G62)+$D62) -> 0 | ... T62: =(($D62*$G62)+$D62) -> 0 | U62: =SUM(I62:T62) -> 0 | V62: =I62/$I$18 -> #DIV/0! | W62: =J62/$J$18 -> #DIV/0! | X62: =K62/$K$18 -> #DIV/0! | Y62: =L62/$L$18 -> #DIV/0! | Z62: =M62/$M$18 -> #DIV/0! | AA62: =N62/$N$18 -> #DIV/0! | AB62: =O62/$O$18 -> #DIV/0! | AC62: =P62/$P$18 -> #DIV/0! | AD62: =Q62/$Q$18 -> #DIV/0! | AE62: =R62/$R$18 -> #DIV/0! | AF62: =S62/$S$18 -> #DIV/0! | AG62: =T62/$T$18 -> #DIV/0! | AH62: =U62/$U$18 -> #DIV/0! | AI62: F | AJ62: =IFERROR(U62/E62,0)-1 -> -1
A63: ='งบกำไรขาดทุน ปี 2025'!A63 -> 0 | B63: ='งบกำไรขาดทุน ปี 2025'!B63 -> รวมเงินเดือนและสวัสดิการพนักงาน | C63: ='งบกำไรขาดทุน ปี 2025'!O63 -> 0 | D63: =C63/$C$5 -> 0 | E63: =D63*$E$5 -> 0 | F63: =E63/$E$18 -> #DIV/0! | I63: =SUM(I45:I62) -> #DIV/0! | J63: =SUM(J45:J62) -> #DIV/0! | K63: =SUM(K45:K62) -> #DIV/0! | L63: =SUM(L45:L62) -> #DIV/0! | M63: =SUM(M45:M62) -> #DIV/0! | N63: =SUM(N45:N62) -> #DIV/0! | O63: =SUM(O45:O62) -> #DIV/0! | P63: =SUM(P45:P62) -> #DIV/0! | ... U63: =SUM(U45:U62) -> #DIV/0! | V63: =I63/$I$18 -> #DIV/0! | W63: =J63/$J$18 -> #DIV/0! | X63: =K63/$K$18 -> #DIV/0! | Y63: =L63/$L$18 -> #DIV/0! | Z63: =M63/$M$18 -> #DIV/0! | AA63: =N63/$N$18 -> #DIV/0! | AB63: =O63/$O$18 -> #DIV/0! | AC63: =P63/$P$18 -> #DIV/0! | AD63: =Q63/$Q$18 -> #DIV/0! | AE63: =R63/$R$18 -> #DIV/0! | AF63: =S63/$S$18 -> #DIV/0! | AG63: =T63/$T$18 -> #DIV/0! | AH63: =U63/$U$18 -> #DIV/0! | AJ63: =IFERROR(U63/E63,0)-1 -> -1
A64: ='งบกำไรขาดทุน ปี 2025'!A64 -> 0 | B64: ='งบกำไรขาดทุน ปี 2025'!B64 -> ค่าอบรมสัมมนา | C64: ='งบกำไรขาดทุน ปี 2025'!O64 -> 0 | AJ64: =IFERROR(U64/E64,0)-1 -> -1
A65: ='งบกำไรขาดทุน ปี 2025'!A65 -> 60100017 | B65: ='งบกำไรขาดทุน ปี 2025'!B65 -> ค่าอบรม&สัมมนาพนักงาน | C65: ='งบกำไรขาดทุน ปี 2025'!O65 -> 0 | D65: =C65/$C$5 -> 0 | E65: =D65*$E$5 -> 0 | F65: =E65/$E$18 -> #DIV/0! | H65: Z | I65: =+'การลงระหว่างเดือน ปี 2026'!AO31 -> 0 | J65: =+'การลงระหว่างเดือน ปี 2026'!AP31 -> 0 | K65: =+'การลงระหว่างเดือน ปี 2026'!AQ31 -> 0 | L65: =+'การลงระหว่างเดือน ปี 2026'!AR31 -> 0 | M65: =+'การลงระหว่างเดือน ปี 2026'!AS31 -> 0 | N65: =+'การลงระหว่างเดือน ปี 2026'!AT31 -> 0 | O65: =+'การลงระหว่างเดือน ปี 2026'!AU31 -> 0 | P65: =+'การลงระหว่างเดือน ปี 2026'!AV31 -> 0 | ... T65: =+'การลงระหว่างเดือน ปี 2026'!AZ31 -> 0 | U65: =SUM(I65:T65) -> 0 | V65: =I65/$I$18 -> #DIV/0! | W65: =J65/$J$18 -> #DIV/0! | X65: =K65/$K$18 -> #DIV/0! | Y65: =L65/$L$18 -> #DIV/0! | Z65: =M65/$M$18 -> #DIV/0! | AA65: =N65/$N$18 -> #DIV/0! | AB65: =O65/$O$18 -> #DIV/0! | AC65: =P65/$P$18 -> #DIV/0! | AD65: =Q65/$Q$18 -> #DIV/0! | AE65: =R65/$R$18 -> #DIV/0! | AF65: =S65/$S$18 -> #DIV/0! | AG65: =T65/$T$18 -> #DIV/0! | AH65: =U65/$U$18 -> #DIV/0! | AI65: S | AJ65: =IFERROR(U65/E65,0)-1 -> -1
A66: ='งบกำไรขาดทุน ปี 2025'!A66 -> 60100018 | B66: ='งบกำไรขาดทุน ปี 2025'!B66 -> ค่าอบรม&สัมมนาหมอ | C66: ='งบกำไรขาดทุน ปี 2025'!O66 -> 0 | D66: =C66/$C$5 -> 0 | E66: =D66*$E$5 -> 0 | F66: =E66/$E$18 -> #DIV/0! | H66: Z | I66: =+'การลงระหว่างเดือน ปี 2026'!AO32 -> 0 | J66: =+'การลงระหว่างเดือน ปี 2026'!AP32 -> 0 | K66: =+'การลงระหว่างเดือน ปี 2026'!AQ32 -> 0 | L66: =+'การลงระหว่างเดือน ปี 2026'!AR32 -> 0 | M66: =+'การลงระหว่างเดือน ปี 2026'!AS32 -> 0 | N66: =+'การลงระหว่างเดือน ปี 2026'!AT32 -> 0 | O66: =+'การลงระหว่างเดือน ปี 2026'!AU32 -> 0 | P66: =+'การลงระหว่างเดือน ปี 2026'!AV32 -> 0 | ... T66: =+'การลงระหว่างเดือน ปี 2026'!AZ32 -> 0 | U66: =SUM(I66:T66) -> 0 | V66: =I66/$I$18 -> #DIV/0! | W66: =J66/$J$18 -> #DIV/0! | X66: =K66/$K$18 -> #DIV/0! | Y66: =L66/$L$18 -> #DIV/0! | Z66: =M66/$M$18 -> #DIV/0! | AA66: =N66/$N$18 -> #DIV/0! | AB66: =O66/$O$18 -> #DIV/0! | AC66: =P66/$P$18 -> #DIV/0! | AD66: =Q66/$Q$18 -> #DIV/0! | AE66: =R66/$R$18 -> #DIV/0! | AF66: =S66/$S$18 -> #DIV/0! | AG66: =T66/$T$18 -> #DIV/0! | AH66: =U66/$U$18 -> #DIV/0! | AI66: S | AJ66: =IFERROR(U66/E66,0)-1 -> -1
A67: ='งบกำไรขาดทุน ปี 2025'!A67 -> 60100019 | B67: ='งบกำไรขาดทุน ปี 2025'!B67 -> ค่าอบรมISO | C67: ='งบกำไรขาดทุน ปี 2025'!O67 -> 0 | D67: =C67/$C$5 -> 0 | E67: =D67*$E$5 -> 0 | F67: =E67/$E$18 -> #DIV/0! | H67: F | I67: =(($D67*$G67)+$D67)+'การลงระหว่างเดือน ปี 2026'!AO33 -> 0 | J67: =(($D67*$G67)+$D67)+'การลงระหว่างเดือน ปี 2026'!AP33 -> 0 | K67: =(($D67*$G67)+$D67)+'การลงระหว่างเดือน ปี 2026'!AQ33 -> 0 | L67: =(($D67*$G67)+$D67)+'การลงระหว่างเดือน ปี 2026'!AR33 -> 0 | M67: =(($D67*$G67)+$D67)+'การลงระหว่างเดือน ปี 2026'!AS33 -> 0 | N67: =(($D67*$G67)+$D67)+'การลงระหว่างเดือน ปี 2026'!AT33 -> 0 | O67: =(($D67*$G67)+$D67)+'การลงระหว่างเดือน ปี 2026'!AU33 -> 0 | P67: =(($D67*$G67)+$D67)+'การลงระหว่างเดือน ปี 2026'!AV33 -> 0 | ... T67: =(($D67*$G67)+$D67)+'การลงระหว่างเดือน ปี 2026'!AZ33 -> 0 | U67: =SUM(I67:T67) -> 0 | V67: =I67/$I$18 -> #DIV/0! | W67: =J67/$J$18 -> #DIV/0! | X67: =K67/$K$18 -> #DIV/0! | Y67: =L67/$L$18 -> #DIV/0! | Z67: =M67/$M$18 -> #DIV/0! | AA67: =N67/$N$18 -> #DIV/0! | AB67: =O67/$O$18 -> #DIV/0! | AC67: =P67/$P$18 -> #DIV/0! | AD67: =Q67/$Q$18 -> #DIV/0! | AE67: =R67/$R$18 -> #DIV/0! | AF67: =S67/$S$18 -> #DIV/0! | AG67: =T67/$T$18 -> #DIV/0! | AH67: =U67/$U$18 -> #DIV/0! | AI67: F | AJ67: =IFERROR(U67/E67,0)-1 -> -1
A68: ='งบกำไรขาดทุน ปี 2025'!A68 -> 0 | B68: ='งบกำไรขาดทุน ปี 2025'!B68 -> รวมค่าอบรมสัมมนา | C68: ='งบกำไรขาดทุน ปี 2025'!O68 -> 0 | D68: =C68/$C$5 -> 0 | E68: =D68*$E$5 -> 0 | F68: =E68/$E$18 -> #DIV/0! | I68: =SUM(I65:I67) -> 0 | J68: =SUM(J65:J67) -> 0 | K68: =SUM(K65:K67) -> 0 | L68: =SUM(L65:L67) -> 0 | M68: =SUM(M65:M67) -> 0 | N68: =SUM(N65:N67) -> 0 | O68: =SUM(O65:O67) -> 0 | P68: =SUM(P65:P67) -> 0 | ... U68: =SUM(U65:U67) -> 0 | V68: =I68/$I$18 -> #DIV/0! | W68: =J68/$J$18 -> #DIV/0! | X68: =K68/$K$18 -> #DIV/0! | Y68: =L68/$L$18 -> #DIV/0! | Z68: =M68/$M$18 -> #DIV/0! | AA68: =N68/$N$18 -> #DIV/0! | AB68: =O68/$O$18 -> #DIV/0! | AC68: =P68/$P$18 -> #DIV/0! | AD68: =Q68/$Q$18 -> #DIV/0! | AE68: =R68/$R$18 -> #DIV/0! | AF68: =S68/$S$18 -> #DIV/0! | AG68: =T68/$T$18 -> #DIV/0! | AH68: =U68/$U$18 -> #DIV/0! | AJ68: =IFERROR(U68/E68,0)-1 -> -1
A69: ='งบกำไรขาดทุน ปี 2025'!A69 -> 0 | B69: ='งบกำไรขาดทุน ปี 2025'!B69 -> Professional Fees | C69: ='งบกำไรขาดทุน ปี 2025'!O69 -> 0 | AJ69: =IFERROR(U69/E69,0)-1 -> -1
A70: ='งบกำไรขาดทุน ปี 2025'!A70 -> 60200004 | B70: ='งบกำไรขาดทุน ปี 2025'!B70 -> ค่าสอบบัญชี | C70: ='งบกำไรขาดทุน ปี 2025'!O70 -> 0 | D70: =C70/$C$5 -> 0 | E70: =D70*$E$5 -> 0 | F70: =E70/$E$18 -> #DIV/0! | G70: =$U$2 -> #DIV/0! | H70: F | I70: =(($D70*$G70)+$D70) -> #DIV/0! | J70: =(($D70*$G70)+$D70) -> #DIV/0! | K70: =(($D70*$G70)+$D70) -> #DIV/0! | L70: =(($D70*$G70)+$D70) -> #DIV/0! | M70: =(($D70*$G70)+$D70) -> #DIV/0! | N70: =(($D70*$G70)+$D70) -> #DIV/0! | O70: =(($D70*$G70)+$D70) -> #DIV/0! | P70: =(($D70*$G70)+$D70) -> #DIV/0! | ... T70: =(($D70*$G70)+$D70) -> #DIV/0! | U70: =SUM(I70:T70) -> #DIV/0! | V70: =I70/$I$18 -> #DIV/0! | W70: =J70/$J$18 -> #DIV/0! | X70: =K70/$K$18 -> #DIV/0! | Y70: =L70/$L$18 -> #DIV/0! | Z70: =M70/$M$18 -> #DIV/0! | AA70: =N70/$N$18 -> #DIV/0! | AB70: =O70/$O$18 -> #DIV/0! | AC70: =P70/$P$18 -> #DIV/0! | AD70: =Q70/$Q$18 -> #DIV/0! | AE70: =R70/$R$18 -> #DIV/0! | AF70: =S70/$S$18 -> #DIV/0! | AG70: =T70/$T$18 -> #DIV/0! | AH70: =U70/$U$18 -> #DIV/0! | AI70: F | AJ70: =IFERROR(U70/E70,0)-1 -> -1
A71: ='งบกำไรขาดทุน ปี 2025'!A71 -> 60100020 | B71: ='งบกำไรขาดทุน ปี 2025'!B71 -> ค่าที่ปรึกษา | C71: ='งบกำไรขาดทุน ปี 2025'!O71 -> 0 | D71: =C71/$C$5 -> 0 | E71: =D71*$E$5 -> 0 | F71: =E71/$E$18 -> #DIV/0! | G71: =$U$2 -> #DIV/0! | H71: F | I71: =(($D71*$G71)+$D71) -> #DIV/0! | J71: =(($D71*$G71)+$D71) -> #DIV/0! | K71: =(($D71*$G71)+$D71) -> #DIV/0! | L71: =(($D71*$G71)+$D71) -> #DIV/0! | M71: =(($D71*$G71)+$D71) -> #DIV/0! | N71: =(($D71*$G71)+$D71) -> #DIV/0! | O71: =(($D71*$G71)+$D71) -> #DIV/0! | P71: =(($D71*$G71)+$D71) -> #DIV/0! | ... T71: =(($D71*$G71)+$D71) -> #DIV/0! | U71: =SUM(I71:T71) -> #DIV/0! | V71: =I71/$I$18 -> #DIV/0! | W71: =J71/$J$18 -> #DIV/0! | X71: =K71/$K$18 -> #DIV/0! | Y71: =L71/$L$18 -> #DIV/0! | Z71: =M71/$M$18 -> #DIV/0! | AA71: =N71/$N$18 -> #DIV/0! | AB71: =O71/$O$18 -> #DIV/0! | AC71: =P71/$P$18 -> #DIV/0! | AD71: =Q71/$Q$18 -> #DIV/0! | AE71: =R71/$R$18 -> #DIV/0! | AF71: =S71/$S$18 -> #DIV/0! | AG71: =T71/$T$18 -> #DIV/0! | AH71: =U71/$U$18 -> #DIV/0! | AI71: F | AJ71: =IFERROR(U71/E71,0)-1 -> -1
A72: ='งบกำไรขาดทุน ปี 2025'!A72 -> 60100021 | B72: ='งบกำไรขาดทุน ปี 2025'!B72 -> ค่าที่ปรึกษากฎหมาย | C72: ='งบกำไรขาดทุน ปี 2025'!O72 -> 0 | D72: =C72/$C$5 -> 0 | E72: =D72*$E$5 -> 0 | F72: =E72/$E$18 -> #DIV/0! | G72: =$U$2 -> #DIV/0! | H72: F | I72: =(($D72*$G72)+$D72) -> #DIV/0! | J72: =(($D72*$G72)+$D72) -> #DIV/0! | K72: =(($D72*$G72)+$D72) -> #DIV/0! | L72: =(($D72*$G72)+$D72) -> #DIV/0! | M72: =(($D72*$G72)+$D72) -> #DIV/0! | N72: =(($D72*$G72)+$D72) -> #DIV/0! | O72: =(($D72*$G72)+$D72) -> #DIV/0! | P72: =(($D72*$G72)+$D72) -> #DIV/0! | ... T72: =(($D72*$G72)+$D72) -> #DIV/0! | U72: =SUM(I72:T72) -> #DIV/0! | V72: =I72/$I$18 -> #DIV/0! | W72: =J72/$J$18 -> #DIV/0! | X72: =K72/$K$18 -> #DIV/0! | Y72: =L72/$L$18 -> #DIV/0! | Z72: =M72/$M$18 -> #DIV/0! | AA72: =N72/$N$18 -> #DIV/0! | AB72: =O72/$O$18 -> #DIV/0! | AC72: =P72/$P$18 -> #DIV/0! | AD72: =Q72/$Q$18 -> #DIV/0! | AE72: =R72/$R$18 -> #DIV/0! | AF72: =S72/$S$18 -> #DIV/0! | AG72: =T72/$T$18 -> #DIV/0! | AH72: =U72/$U$18 -> #DIV/0! | AI72: F | AJ72: =IFERROR(U72/E72,0)-1 -> -1
A73: ='งบกำไรขาดทุน ปี 2025'!A73 -> 60100022 | B73: ='งบกำไรขาดทุน ปี 2025'!B73 -> เงินเดือนล่าม | C73: ='งบกำไรขาดทุน ปี 2025'!O73 -> 0 | D73: =C73/$C$5 -> 0 | E73: =D73*$E$5 -> 0 | F73: =E73/$E$18 -> #DIV/0! | G73: =$U$2 -> #DIV/0! | H73: F | I73: =(($D73*$G73)+$D73) -> #DIV/0! | J73: =(($D73*$G73)+$D73) -> #DIV/0! | K73: =(($D73*$G73)+$D73) -> #DIV/0! | L73: =(($D73*$G73)+$D73) -> #DIV/0! | M73: =(($D73*$G73)+$D73) -> #DIV/0! | N73: =(($D73*$G73)+$D73) -> #DIV/0! | O73: =(($D73*$G73)+$D73) -> #DIV/0! | P73: =(($D73*$G73)+$D73) -> #DIV/0! | ... T73: =(($D73*$G73)+$D73) -> #DIV/0! | U73: =SUM(I73:T73) -> #DIV/0! | V73: =I73/$I$18 -> #DIV/0! | W73: =J73/$J$18 -> #DIV/0! | X73: =K73/$K$18 -> #DIV/0! | Y73: =L73/$L$18 -> #DIV/0! | Z73: =M73/$M$18 -> #DIV/0! | AA73: =N73/$N$18 -> #DIV/0! | AB73: =O73/$O$18 -> #DIV/0! | AC73: =P73/$P$18 -> #DIV/0! | AD73: =Q73/$Q$18 -> #DIV/0! | AE73: =R73/$R$18 -> #DIV/0! | AF73: =S73/$S$18 -> #DIV/0! | AG73: =T73/$T$18 -> #DIV/0! | AH73: =U73/$U$18 -> #DIV/0! | AI73: F | AJ73: =IFERROR(U73/E73,0)-1 -> -1
A74: ='งบกำไรขาดทุน ปี 2025'!A74 -> 0 | B74: ='งบกำไรขาดทุน ปี 2025'!B74 -> รวม Professional Fees | C74: ='งบกำไรขาดทุน ปี 2025'!O74 -> 0 | D74: =C74/$C$5 -> 0 | E74: =D74*$E$5 -> 0 | F74: =E74/$E$18 -> #DIV/0! | I74: =SUM(I70:I73) -> #DIV/0! | J74: =SUM(J70:J73) -> #DIV/0! | K74: =SUM(K70:K73) -> #DIV/0! | L74: =SUM(L70:L73) -> #DIV/0! | M74: =SUM(M70:M73) -> #DIV/0! | N74: =SUM(N70:N73) -> #DIV/0! | O74: =SUM(O70:O73) -> #DIV/0! | P74: =SUM(P70:P73) -> #DIV/0! | ... T74: =SUM(T70:T73) -> #DIV/0! | U74: =SUM(U69:U73) -> #DIV/0! | V74: =I74/$I$18 -> #DIV/0! | W74: =J74/$J$18 -> #DIV/0! | X74: =K74/$K$18 -> #DIV/0! | Y74: =L74/$L$18 -> #DIV/0! | Z74: =M74/$M$18 -> #DIV/0! | AA74: =N74/$N$18 -> #DIV/0! | AB74: =O74/$O$18 -> #DIV/0! | AC74: =P74/$P$18 -> #DIV/0! | AD74: =Q74/$Q$18 -> #DIV/0! | AE74: =R74/$R$18 -> #DIV/0! | AF74: =S74/$S$18 -> #DIV/0! | AG74: =T74/$T$18 -> #DIV/0! | AH74: =U74/$U$18 -> #DIV/0! | AJ74: =IFERROR(U74/E74,0)-1 -> -1
A75: ='งบกำไรขาดทุน ปี 2025'!A75 -> 0 | B75: ='งบกำไรขาดทุน ปี 2025'!B75 -> ค่าธรรมเนียม | C75: ='งบกำไรขาดทุน ปี 2025'!O75 -> 0 | AJ75: =IFERROR(U75/E75,0)-1 -> -1
A76: ='งบกำไรขาดทุน ปี 2025'!A76 -> 60200001 | B76: ='งบกำไรขาดทุน ปี 2025'!B76 -> ค่าบริการสอบเทียบ | C76: ='งบกำไรขาดทุน ปี 2025'!O76 -> 0 | D76: =C76/$C$5 -> 0 | E76: =D76*$E$5 -> 0 | F76: =E76/$E$18 -> #DIV/0! | G76: =F76 -> #DIV/0! | H76: x | I76: =((I$18*(+$G76))) -> #DIV/0! | J76: =((J$18*(+$G76))) -> #DIV/0! | K76: =((K$18*(+$G76))) -> #DIV/0! | L76: =((L$18*(+$G76))) -> #DIV/0! | M76: =((M$18*(+$G76))) -> #DIV/0! | N76: =((N$18*(+$G76))) -> #DIV/0! | O76: =((O$18*(+$G76))) -> #DIV/0! | P76: =((P$18*(+$G76))) -> #DIV/0! | ... T76: =((T$18*(+$G76))) -> #DIV/0! | U76: =SUM(I76:T76) -> #DIV/0! | V76: =I76/$I$18 -> #DIV/0! | W76: =J76/$J$18 -> #DIV/0! | X76: =K76/$K$18 -> #DIV/0! | Y76: =L76/$L$18 -> #DIV/0! | Z76: =M76/$M$18 -> #DIV/0! | AA76: =N76/$N$18 -> #DIV/0! | AB76: =O76/$O$18 -> #DIV/0! | AC76: =P76/$P$18 -> #DIV/0! | AD76: =Q76/$Q$18 -> #DIV/0! | AE76: =R76/$R$18 -> #DIV/0! | AF76: =S76/$S$18 -> #DIV/0! | AG76: =T76/$T$18 -> #DIV/0! | AH76: =U76/$U$18 -> #DIV/0! | AJ76: =IFERROR(U76/E76,0)-1 -> -1
A77: ='งบกำไรขาดทุน ปี 2025'!A77 -> 60200003 | B77: ='งบกำไรขาดทุน ปี 2025'!B77 -> ค่าธรรมเนียมอื่นๆ | C77: ='งบกำไรขาดทุน ปี 2025'!O77 -> 0 | D77: =C77/$C$5 -> 0 | E77: =D77*$E$5 -> 0 | F77: =E77/$E$18 -> #DIV/0! | G77: =F77 -> #DIV/0! | H77: x | I77: =((I$18*(+$G77))) -> #DIV/0! | J77: =((J$18*(+$G77))) -> #DIV/0! | K77: =((K$18*(+$G77))) -> #DIV/0! | L77: =((L$18*(+$G77))) -> #DIV/0! | M77: =((M$18*(+$G77))) -> #DIV/0! | N77: =((N$18*(+$G77))) -> #DIV/0! | O77: =((O$18*(+$G77))) -> #DIV/0! | P77: =((P$18*(+$G77))) -> #DIV/0! | ... T77: =((T$18*(+$G77))) -> #DIV/0! | U77: =SUM(I77:T77) -> #DIV/0! | V77: =I77/$I$18 -> #DIV/0! | W77: =J77/$J$18 -> #DIV/0! | X77: =K77/$K$18 -> #DIV/0! | Y77: =L77/$L$18 -> #DIV/0! | Z77: =M77/$M$18 -> #DIV/0! | AA77: =N77/$N$18 -> #DIV/0! | AB77: =O77/$O$18 -> #DIV/0! | AC77: =P77/$P$18 -> #DIV/0! | AD77: =Q77/$Q$18 -> #DIV/0! | AE77: =R77/$R$18 -> #DIV/0! | AF77: =S77/$S$18 -> #DIV/0! | AG77: =T77/$T$18 -> #DIV/0! | AH77: =U77/$U$18 -> #DIV/0! | AI77: V | AJ77: =IFERROR(U77/E77,0)-1 -> -1
A78: ='งบกำไรขาดทุน ปี 2025'!A78 -> 60200002 | B78: ='งบกำไรขาดทุน ปี 2025'!B78 -> ค่าธรรมเนียมธนาคาร | C78: ='งบกำไรขาดทุน ปี 2025'!O78 -> 0 | D78: =C78/$C$5 -> 0 | E78: =D78*$E$5 -> 0 | F78: =E78/$E$18 -> #DIV/0! | G78: 0.01 | H78: x | I78: =((I$18*(+$G78))) -> 0 | J78: =((J$18*(+$G78))) -> 0 | K78: =((K$18*(+$G78))) -> 0 | L78: =((L$18*(+$G78))) -> 0 | M78: =((M$18*(+$G78))) -> 0 | N78: =((N$18*(+$G78))) -> 0 | O78: =((O$18*(+$G78))) -> 0 | P78: =((P$18*(+$G78))) -> 0 | ... T78: =((T$18*(+$G78))) -> 0 | U78: =SUM(I78:T78) -> 0 | V78: =I78/$I$18 -> #DIV/0! | W78: =J78/$J$18 -> #DIV/0! | X78: =K78/$K$18 -> #DIV/0! | Y78: =L78/$L$18 -> #DIV/0! | Z78: =M78/$M$18 -> #DIV/0! | AA78: =N78/$N$18 -> #DIV/0! | AB78: =O78/$O$18 -> #DIV/0! | AC78: =P78/$P$18 -> #DIV/0! | AD78: =Q78/$Q$18 -> #DIV/0! | AE78: =R78/$R$18 -> #DIV/0! | AF78: =S78/$S$18 -> #DIV/0! | AG78: =T78/$T$18 -> #DIV/0! | AH78: =U78/$U$18 -> #DIV/0! | AI78: V | AJ78: =IFERROR(U78/E78,0)-1 -> -1
A79: ='งบกำไรขาดทุน ปี 2025'!A79 -> 0 | B79: ='งบกำไรขาดทุน ปี 2025'!B79 -> รวมค่าธรรมเนียม | C79: ='งบกำไรขาดทุน ปี 2025'!O79 -> 0 | D79: =C79/$C$5 -> 0 | E79: =D79*$E$5 -> 0 | F79: =E79/$E$18 -> #DIV/0! | I79: =SUM(I76:I78) -> #DIV/0! | J79: =SUM(J76:J78) -> #DIV/0! | K79: =SUM(K76:K78) -> #DIV/0! | L79: =SUM(L76:L78) -> #DIV/0! | M79: =SUM(M76:M78) -> #DIV/0! | N79: =SUM(N76:N78) -> #DIV/0! | O79: =SUM(O76:O78) -> #DIV/0! | P79: =SUM(P76:P78) -> #DIV/0! | ... U79: =SUM(U76:U78) -> #DIV/0! | V79: =I79/$I$18 -> #DIV/0! | W79: =J79/$J$18 -> #DIV/0! | X79: =K79/$K$18 -> #DIV/0! | Y79: =L79/$L$18 -> #DIV/0! | Z79: =M79/$M$18 -> #DIV/0! | AA79: =N79/$N$18 -> #DIV/0! | AB79: =O79/$O$18 -> #DIV/0! | AC79: =P79/$P$18 -> #DIV/0! | AD79: =Q79/$Q$18 -> #DIV/0! | AE79: =R79/$R$18 -> #DIV/0! | AF79: =S79/$S$18 -> #DIV/0! | AG79: =T79/$T$18 -> #DIV/0! | AH79: =U79/$U$18 -> #DIV/0! | AJ79: =IFERROR(U79/E79,0)-1 -> -1
A80: ='งบกำไรขาดทุน ปี 2025'!A80 -> 0 | B80: ='งบกำไรขาดทุน ปี 2025'!B80 -> วัสดุสิ้นเปลือง | C80: ='งบกำไรขาดทุน ปี 2025'!O80 -> 0 | AJ80: =IFERROR(U80/E80,0)-1 -> -1
A81: ='งบกำไรขาดทุน ปี 2025'!A81 -> 60300001 | B81: ='งบกำไรขาดทุน ปี 2025'!B81 -> ค่าเครื่องเขียนแบบพิมพ์ | C81: ='งบกำไรขาดทุน ปี 2025'!O81 -> 0 | D81: =C81/$C$5 -> 0 | E81: =D81*$E$5 -> 0 | F81: =E81/$E$18 -> #DIV/0! | G81: 0.0005 | H81: x | I81: =((I$18*(+$G81))) -> 0 | J81: =((J$18*(+$G81))) -> 0 | K81: =((K$18*(+$G81))) -> 0 | L81: =((L$18*(+$G81))) -> 0 | M81: =((M$18*(+$G81))) -> 0 | N81: =((N$18*(+$G81))) -> 0 | O81: =((O$18*(+$G81))) -> 0 | P81: =((P$18*(+$G81))) -> 0 | ... T81: =((T$18*(+$G81))) -> 0 | U81: =SUM(I81:T81) -> 0 | V81: =I81/$I$18 -> #DIV/0! | W81: =J81/$J$18 -> #DIV/0! | X81: =K81/$K$18 -> #DIV/0! | Y81: =L81/$L$18 -> #DIV/0! | Z81: =M81/$M$18 -> #DIV/0! | AA81: =N81/$N$18 -> #DIV/0! | AB81: =O81/$O$18 -> #DIV/0! | AC81: =P81/$P$18 -> #DIV/0! | AD81: =Q81/$Q$18 -> #DIV/0! | AE81: =R81/$R$18 -> #DIV/0! | AF81: =S81/$S$18 -> #DIV/0! | AG81: =T81/$T$18 -> #DIV/0! | AH81: =U81/$U$18 -> #DIV/0! | AI81: V | AJ81: =IFERROR(U81/E81,0)-1 -> -1
A82: ='งบกำไรขาดทุน ปี 2025'!A82 -> 60300002 | B82: ='งบกำไรขาดทุน ปี 2025'!B82 -> ค่าอุปกรณ์สำนักงาน-ของใช้สิ้นเปลือง | C82: ='งบกำไรขาดทุน ปี 2025'!O82 -> 0 | D82: =C82/$C$5 -> 0 | E82: =D82*$E$5 -> 0 | F82: =E82/$E$18 -> #DIV/0! | G82: 0.019 | H82: x | I82: =((I$18*(+$G82))) -> 0 | J82: =((J$18*(+$G82))) -> 0 | K82: =((K$18*(+$G82))) -> 0 | L82: =((L$18*(+$G82))) -> 0 | M82: =((M$18*(+$G82))) -> 0 | N82: =((N$18*(+$G82))) -> 0 | O82: =((O$18*(+$G82))) -> 0 | P82: =((P$18*(+$G82))) -> 0 | ... T82: =((T$18*(+$G82))) -> 0 | U82: =SUM(I82:T82) -> 0 | V82: =I82/$I$18 -> #DIV/0! | W82: =J82/$J$18 -> #DIV/0! | X82: =K82/$K$18 -> #DIV/0! | Y82: =L82/$L$18 -> #DIV/0! | Z82: =M82/$M$18 -> #DIV/0! | AA82: =N82/$N$18 -> #DIV/0! | AB82: =O82/$O$18 -> #DIV/0! | AC82: =P82/$P$18 -> #DIV/0! | AD82: =Q82/$Q$18 -> #DIV/0! | AE82: =R82/$R$18 -> #DIV/0! | AF82: =S82/$S$18 -> #DIV/0! | AG82: =T82/$T$18 -> #DIV/0! | AH82: =U82/$U$18 -> #DIV/0! | AI82: V | AJ82: =IFERROR(U82/E82,0)-1 -> -1
A83: ='งบกำไรขาดทุน ปี 2025'!A83 -> 60300005 | B83: ='งบกำไรขาดทุน ปี 2025'!B83 -> ค่าเช่าเครื่องถ่ายเอกสาร | C83: ='งบกำไรขาดทุน ปี 2025'!O83 -> 0 | D83: =C83/$C$5 -> 0 | E83: =D83*$E$5 -> 0 | F83: =E83/$E$18 -> #DIV/0! | G83: 0.0005 | H83: x | I83: =((I$18*(+$G83))) -> 0 | J83: =((J$18*(+$G83))) -> 0 | K83: =((K$18*(+$G83))) -> 0 | L83: =((L$18*(+$G83))) -> 0 | M83: =((M$18*(+$G83))) -> 0 | N83: =((N$18*(+$G83))) -> 0 | O83: =((O$18*(+$G83))) -> 0 | P83: =((P$18*(+$G83))) -> 0 | ... T83: =((T$18*(+$G83))) -> 0 | U83: =SUM(I83:T83) -> 0 | V83: =I83/$I$18 -> #DIV/0! | W83: =J83/$J$18 -> #DIV/0! | X83: =K83/$K$18 -> #DIV/0! | Y83: =L83/$L$18 -> #DIV/0! | Z83: =M83/$M$18 -> #DIV/0! | AA83: =N83/$N$18 -> #DIV/0! | AB83: =O83/$O$18 -> #DIV/0! | AC83: =P83/$P$18 -> #DIV/0! | AD83: =Q83/$Q$18 -> #DIV/0! | AE83: =R83/$R$18 -> #DIV/0! | AF83: =S83/$S$18 -> #DIV/0! | AG83: =T83/$T$18 -> #DIV/0! | AH83: =U83/$U$18 -> #DIV/0! | AI83: V | AJ83: =IFERROR(U83/E83,0)-1 -> -1
A84: ='งบกำไรขาดทุน ปี 2025'!A84 -> 0 | B84: ='งบกำไรขาดทุน ปี 2025'!B84 -> รวมวัสดุสิ้นเปลือง | C84: ='งบกำไรขาดทุน ปี 2025'!O84 -> 0 | D84: =C84/$C$5 -> 0 | E84: =D84*$E$5 -> 0 | F84: =SUM(F81:F83) -> #DIV/0! | I84: =SUM(I81:I83) -> 0 | J84: =SUM(J81:J83) -> 0 | K84: =SUM(K81:K83) -> 0 | L84: =SUM(L81:L83) -> 0 | M84: =SUM(M81:M83) -> 0 | N84: =SUM(N81:N83) -> 0 | O84: =SUM(O81:O83) -> 0 | P84: =SUM(P81:P83) -> 0 | ... U84: =SUM(U81:U83) -> 0 | V84: =I84/$I$18 -> #DIV/0! | W84: =J84/$J$18 -> #DIV/0! | X84: =K84/$K$18 -> #DIV/0! | Y84: =L84/$L$18 -> #DIV/0! | Z84: =M84/$M$18 -> #DIV/0! | AA84: =N84/$N$18 -> #DIV/0! | AB84: =O84/$O$18 -> #DIV/0! | AC84: =P84/$P$18 -> #DIV/0! | AD84: =Q84/$Q$18 -> #DIV/0! | AE84: =R84/$R$18 -> #DIV/0! | AF84: =S84/$S$18 -> #DIV/0! | AG84: =T84/$T$18 -> #DIV/0! | AH84: =U84/$U$18 -> #DIV/0! | AJ84: =IFERROR(U84/E84,0)-1 -> -1
A85: ='งบกำไรขาดทุน ปี 2025'!A85 -> 0 | B85: ='งบกำไรขาดทุน ปี 2025'!B85 -> ค่่าโฆษณาและส่งเสริมการขาย | C85: ='งบกำไรขาดทุน ปี 2025'!O85 -> 0 | AJ85: =IFERROR(U85/E85,0)-1 -> -1
A86: ='งบกำไรขาดทุน ปี 2025'!A86 -> 60400001 | B86: ='งบกำไรขาดทุน ปี 2025'!B86 -> ค่าโฆษณา | C86: ='งบกำไรขาดทุน ปี 2025'!O86 -> 0 | D86: =C86/$C$5 -> 0 | E86: =D86*$E$5 -> 0 | F86: =E86/$E$18 -> #DIV/0! | H86: Z | I86: =(+'การลงระหว่างเดือน ปี 2026'!AO40) -> 0 | J86: =(+'การลงระหว่างเดือน ปี 2026'!AP40) -> 0 | K86: =(+'การลงระหว่างเดือน ปี 2026'!AQ40) -> 0 | L86: =(+'การลงระหว่างเดือน ปี 2026'!AR40) -> 0 | M86: =(+'การลงระหว่างเดือน ปี 2026'!AS40) -> 0 | N86: =(+'การลงระหว่างเดือน ปี 2026'!AT40) -> 0 | O86: =(+'การลงระหว่างเดือน ปี 2026'!AU40) -> 0 | P86: =(+'การลงระหว่างเดือน ปี 2026'!AV40) -> 0 | ... T86: =(+'การลงระหว่างเดือน ปี 2026'!AZ40) -> 0 | U86: =SUM(I86:T86) -> 0 | V86: =I86/$I$18 -> #DIV/0! | W86: =J86/$J$18 -> #DIV/0! | X86: =K86/$K$18 -> #DIV/0! | Y86: =L86/$L$18 -> #DIV/0! | Z86: =M86/$M$18 -> #DIV/0! | AA86: =N86/$N$18 -> #DIV/0! | AB86: =O86/$O$18 -> #DIV/0! | AC86: =P86/$P$18 -> #DIV/0! | AD86: =Q86/$Q$18 -> #DIV/0! | AE86: =R86/$R$18 -> #DIV/0! | AF86: =S86/$S$18 -> #DIV/0! | AG86: =T86/$T$18 -> #DIV/0! | AH86: =U86/$U$18 -> #DIV/0! | AI86: V | AJ86: =IFERROR(U86/E86,0)-1 -> -1
A87: ='งบกำไรขาดทุน ปี 2025'!A87 -> 60400003 | B87: ='งบกำไรขาดทุน ปี 2025'!B87 -> ค่าโฆษณาหาคน | C87: ='งบกำไรขาดทุน ปี 2025'!O87 -> 0 | D87: =C87/$C$5 -> 0 | E87: =D87*$E$5 -> 0 | F87: =E87/$E$18 -> #DIV/0! | H87: Z | I87: =(+'การลงระหว่างเดือน ปี 2026'!AO41) -> 0 | J87: =(+'การลงระหว่างเดือน ปี 2026'!AP41) -> 0 | K87: =(+'การลงระหว่างเดือน ปี 2026'!AQ41) -> 0 | L87: =(+'การลงระหว่างเดือน ปี 2026'!AR41) -> 0 | M87: =(+'การลงระหว่างเดือน ปี 2026'!AS41) -> 0 | N87: =(+'การลงระหว่างเดือน ปี 2026'!AT41) -> 0 | O87: =(+'การลงระหว่างเดือน ปี 2026'!AU41) -> 0 | P87: =(+'การลงระหว่างเดือน ปี 2026'!AV41) -> 0 | ... T87: =(+'การลงระหว่างเดือน ปี 2026'!AZ41) -> 0 | U87: =SUM(I87:T87) -> 0 | V87: =I87/$I$18 -> #DIV/0! | W87: =J87/$J$18 -> #DIV/0! | X87: =K87/$K$18 -> #DIV/0! | Y87: =L87/$L$18 -> #DIV/0! | Z87: =M87/$M$18 -> #DIV/0! | AA87: =N87/$N$18 -> #DIV/0! | AB87: =O87/$O$18 -> #DIV/0! | AC87: =P87/$P$18 -> #DIV/0! | AD87: =Q87/$Q$18 -> #DIV/0! | AE87: =R87/$R$18 -> #DIV/0! | AF87: =S87/$S$18 -> #DIV/0! | AG87: =T87/$T$18 -> #DIV/0! | AH87: =U87/$U$18 -> #DIV/0! | AI87: V | AJ87: =IFERROR(U87/E87,0)-1 -> -1
A88: ='งบกำไรขาดทุน ปี 2025'!A88 -> 60400002 | B88: ='งบกำไรขาดทุน ปี 2025'!B88 -> ค่า CRM | C88: ='งบกำไรขาดทุน ปี 2025'!O88 -> 0 | D88: =C88/$C$5 -> 0 | E88: =D88*$E$5 -> 0 | F88: =E88/$E$18 -> #DIV/0! | H88: V | I88: =(+'การลงระหว่างเดือน ปี 2026'!AO42) -> 0 | J88: =(+'การลงระหว่างเดือน ปี 2026'!AP42) -> 0 | K88: =(+'การลงระหว่างเดือน ปี 2026'!AQ42) -> 0 | L88: =(+'การลงระหว่างเดือน ปี 2026'!AR42) -> 0 | M88: =(+'การลงระหว่างเดือน ปี 2026'!AS42) -> 0 | N88: =(+'การลงระหว่างเดือน ปี 2026'!AT42) -> 0 | O88: =(+'การลงระหว่างเดือน ปี 2026'!AU42) -> 0 | P88: =(+'การลงระหว่างเดือน ปี 2026'!AV42) -> 0 | ... T88: =(+'การลงระหว่างเดือน ปี 2026'!AZ42) -> 0 | U88: =SUM(I88:T88) -> 0 | V88: =I88/$I$18 -> #DIV/0! | W88: =J88/$J$18 -> #DIV/0! | X88: =K88/$K$18 -> #DIV/0! | Y88: =L88/$L$18 -> #DIV/0! | Z88: =M88/$M$18 -> #DIV/0! | AA88: =N88/$N$18 -> #DIV/0! | AB88: =O88/$O$18 -> #DIV/0! | AC88: =P88/$P$18 -> #DIV/0! | AD88: =Q88/$Q$18 -> #DIV/0! | AE88: =R88/$R$18 -> #DIV/0! | AF88: =S88/$S$18 -> #DIV/0! | AG88: =T88/$T$18 -> #DIV/0! | AH88: =U88/$U$18 -> #DIV/0! | AI88: V | AJ88: =IFERROR(U88/E88,0)-1 -> -1
A89: ='งบกำไรขาดทุน ปี 2025'!A89 -> 0 | B89: ='งบกำไรขาดทุน ปี 2025'!B89 -> รวมค่าโฆษณาและส่งเสริมการขาย | C89: ='งบกำไรขาดทุน ปี 2025'!O89 -> 0 | D89: =C89/$C$5 -> 0 | E89: =D89*$E$5 -> 0 | F89: =E89/$E$18 -> #DIV/0! | I89: =SUM(I86:I88) -> 0 | J89: =SUM(J86:J88) -> 0 | K89: =SUM(K86:K88) -> 0 | L89: =SUM(L86:L88) -> 0 | M89: =SUM(M86:M88) -> 0 | N89: =SUM(N86:N88) -> 0 | O89: =SUM(O86:O88) -> 0 | P89: =SUM(P86:P88) -> 0 | ... U89: =SUM(U86:U88) -> 0 | V89: =I89/$I$18 -> #DIV/0! | W89: =J89/$J$18 -> #DIV/0! | X89: =K89/$K$18 -> #DIV/0! | Y89: =L89/$L$18 -> #DIV/0! | Z89: =M89/$M$18 -> #DIV/0! | AA89: =N89/$N$18 -> #DIV/0! | AB89: =O89/$O$18 -> #DIV/0! | AC89: =P89/$P$18 -> #DIV/0! | AD89: =Q89/$Q$18 -> #DIV/0! | AE89: =R89/$R$18 -> #DIV/0! | AF89: =S89/$S$18 -> #DIV/0! | AG89: =T89/$T$18 -> #DIV/0! | AH89: =U89/$U$18 -> #DIV/0! | AJ89: =IFERROR(U89/E89,0)-1 -> -1
A90: ='งบกำไรขาดทุน ปี 2025'!A90 -> 0 | B90: ='งบกำไรขาดทุน ปี 2025'!B90 -> ค่าซ่อมแซมและบำรุงรักษา | C90: ='งบกำไรขาดทุน ปี 2025'!O90 -> 0 | AJ90: =IFERROR(U90/E90,0)-1 -> -1
A91: ='งบกำไรขาดทุน ปี 2025'!A91 -> 60600001 | B91: ='งบกำไรขาดทุน ปี 2025'!B91 -> ค่าซ่อมแซมคอมพิวเตอร์ | C91: ='งบกำไรขาดทุน ปี 2025'!O91 -> 0 | D91: =C91/$C$5 -> 0 | E91: =D91*$E$5 -> 0 | F91: =E91/$E$18 -> #DIV/0! | G91: =$F$98+1% -> #DIV/0! | H91: F | I91: =(($D91*$G91)+$D91)+'การลงระหว่างเดือน ปี 2026'!AO44 -> #DIV/0! | J91: =(($D91*$G91)+$D91)+'การลงระหว่างเดือน ปี 2026'!AP44 -> #DIV/0! | K91: =(($D91*$G91)+$D91)+'การลงระหว่างเดือน ปี 2026'!AQ44 -> #DIV/0! | L91: =(($D91*$G91)+$D91)+'การลงระหว่างเดือน ปี 2026'!AR44 -> #DIV/0! | M91: =(($D91*$G91)+$D91)+'การลงระหว่างเดือน ปี 2026'!AS44 -> #DIV/0! | N91: =(($D91*$G91)+$D91)+'การลงระหว่างเดือน ปี 2026'!AT44 -> #DIV/0! | O91: =(($D91*$G91)+$D91)+'การลงระหว่างเดือน ปี 2026'!AU44 -> #DIV/0! | P91: =(($D91*$G91)+$D91)+'การลงระหว่างเดือน ปี 2026'!AV44 -> #DIV/0! | ... T91: =(($D91*$G91)+$D91)+'การลงระหว่างเดือน ปี 2026'!AZ44 -> #DIV/0! | U91: =SUM(I91:T91) -> #DIV/0! | V91: =I91/$I$18 -> #DIV/0! | W91: =J91/$J$18 -> #DIV/0! | X91: =K91/$K$18 -> #DIV/0! | Y91: =L91/$L$18 -> #DIV/0! | Z91: =M91/$M$18 -> #DIV/0! | AA91: =N91/$N$18 -> #DIV/0! | AB91: =O91/$O$18 -> #DIV/0! | AC91: =P91/$P$18 -> #DIV/0! | AD91: =Q91/$Q$18 -> #DIV/0! | AE91: =R91/$R$18 -> #DIV/0! | AF91: =S91/$S$18 -> #DIV/0! | AG91: =T91/$T$18 -> #DIV/0! | AH91: =U91/$U$18 -> #DIV/0! | AI91: S | AJ91: =IFERROR(U91/E91,0)-1 -> -1
A92: ='งบกำไรขาดทุน ปี 2025'!A92 -> 60600002 | B92: ='งบกำไรขาดทุน ปี 2025'!B92 -> ค่าซ่อมแซมเครื่องใช้สำนักงาน | C92: ='งบกำไรขาดทุน ปี 2025'!O92 -> 0 | D92: =C92/$C$5 -> 0 | E92: =D92*$E$5 -> 0 | F92: =E92/$E$18 -> #DIV/0! | G92: =$F$98+1% -> #DIV/0! | H92: F | I92: =(($D92*$G92)+$D92)+'การลงระหว่างเดือน ปี 2026'!AO45 -> #DIV/0! | J92: =(($D92*$G92)+$D92)+'การลงระหว่างเดือน ปี 2026'!AP45 -> #DIV/0! | K92: =(($D92*$G92)+$D92)+'การลงระหว่างเดือน ปี 2026'!AQ45 -> #DIV/0! | L92: =(($D92*$G92)+$D92)+'การลงระหว่างเดือน ปี 2026'!AR45 -> #DIV/0! | M92: =(($D92*$G92)+$D92)+'การลงระหว่างเดือน ปี 2026'!AS45 -> #DIV/0! | N92: =(($D92*$G92)+$D92)+'การลงระหว่างเดือน ปี 2026'!AT45 -> #DIV/0! | O92: =(($D92*$G92)+$D92)+'การลงระหว่างเดือน ปี 2026'!AU45 -> #DIV/0! | P92: =(($D92*$G92)+$D92)+'การลงระหว่างเดือน ปี 2026'!AV45 -> #DIV/0! | ... T92: =(($D92*$G92)+$D92)+'การลงระหว่างเดือน ปี 2026'!AZ45 -> #DIV/0! | U92: =SUM(I92:T92) -> #DIV/0! | V92: =I92/$I$18 -> #DIV/0! | W92: =J92/$J$18 -> #DIV/0! | X92: =K92/$K$18 -> #DIV/0! | Y92: =L92/$L$18 -> #DIV/0! | Z92: =M92/$M$18 -> #DIV/0! | AA92: =N92/$N$18 -> #DIV/0! | AB92: =O92/$O$18 -> #DIV/0! | AC92: =P92/$P$18 -> #DIV/0! | AD92: =Q92/$Q$18 -> #DIV/0! | AE92: =R92/$R$18 -> #DIV/0! | AF92: =S92/$S$18 -> #DIV/0! | AG92: =T92/$T$18 -> #DIV/0! | AH92: =U92/$U$18 -> #DIV/0! | AI92: S | AJ92: =IFERROR(U92/E92,0)-1 -> -1
A93: ='งบกำไรขาดทุน ปี 2025'!A93 -> 60600003 | B93: ='งบกำไรขาดทุน ปี 2025'!B93 -> ค่าซ่อมแซมเครื่องตกแต่งและติดตั้ง | C93: ='งบกำไรขาดทุน ปี 2025'!O93 -> 0 | D93: =C93/$C$5 -> 0 | E93: =D93*$E$5 -> 0 | F93: =E93/$E$18 -> #DIV/0! | G93: =$F$98+1% -> #DIV/0! | H93: F | I93: =(($D93*$G93)+$D93)+'การลงระหว่างเดือน ปี 2026'!AO46 -> #DIV/0! | J93: =(($D93*$G93)+$D93)+'การลงระหว่างเดือน ปี 2026'!AP46 -> #DIV/0! | K93: =(($D93*$G93)+$D93)+'การลงระหว่างเดือน ปี 2026'!AQ46 -> #DIV/0! | L93: =(($D93*$G93)+$D93)+'การลงระหว่างเดือน ปี 2026'!AR46 -> #DIV/0! | M93: =(($D93*$G93)+$D93)+'การลงระหว่างเดือน ปี 2026'!AS46 -> #DIV/0! | N93: =(($D93*$G93)+$D93)+'การลงระหว่างเดือน ปี 2026'!AT46 -> #DIV/0! | O93: =(($D93*$G93)+$D93)+'การลงระหว่างเดือน ปี 2026'!AU46 -> #DIV/0! | P93: =(($D93*$G93)+$D93)+'การลงระหว่างเดือน ปี 2026'!AV46 -> #DIV/0! | ... T93: =(($D93*$G93)+$D93)+'การลงระหว่างเดือน ปี 2026'!AZ46 -> #DIV/0! | U93: =SUM(I93:T93) -> #DIV/0! | V93: =I93/$I$18 -> #DIV/0! | W93: =J93/$J$18 -> #DIV/0! | X93: =K93/$K$18 -> #DIV/0! | Y93: =L93/$L$18 -> #DIV/0! | Z93: =M93/$M$18 -> #DIV/0! | AA93: =N93/$N$18 -> #DIV/0! | AB93: =O93/$O$18 -> #DIV/0! | AC93: =P93/$P$18 -> #DIV/0! | AD93: =Q93/$Q$18 -> #DIV/0! | AE93: =R93/$R$18 -> #DIV/0! | AF93: =S93/$S$18 -> #DIV/0! | AG93: =T93/$T$18 -> #DIV/0! | AH93: =U93/$U$18 -> #DIV/0! | AI93: S | AJ93: =IFERROR(U93/E93,0)-1 -> -1
A94: ='งบกำไรขาดทุน ปี 2025'!A94 -> 60600004 | B94: ='งบกำไรขาดทุน ปี 2025'!B94 -> ค่าซ่อมแซมยานพาหนะ | C94: ='งบกำไรขาดทุน ปี 2025'!O94 -> 0 | D94: =C94/$C$5 -> 0 | E94: =D94*$E$5 -> 0 | F94: =E94/$E$18 -> #DIV/0! | G94: =$F$98+1% -> #DIV/0! | H94: F | I94: =(($D94*$G94)+$D94)+'การลงระหว่างเดือน ปี 2026'!AO47 -> #DIV/0! | J94: =(($D94*$G94)+$D94)+'การลงระหว่างเดือน ปี 2026'!AP47 -> #DIV/0! | K94: =(($D94*$G94)+$D94)+'การลงระหว่างเดือน ปี 2026'!AQ47 -> #DIV/0! | L94: =(($D94*$G94)+$D94)+'การลงระหว่างเดือน ปี 2026'!AR47 -> #DIV/0! | M94: =(($D94*$G94)+$D94)+'การลงระหว่างเดือน ปี 2026'!AS47 -> #DIV/0! | N94: =(($D94*$G94)+$D94)+'การลงระหว่างเดือน ปี 2026'!AT47 -> #DIV/0! | O94: =(($D94*$G94)+$D94)+'การลงระหว่างเดือน ปี 2026'!AU47 -> #DIV/0! | P94: =(($D94*$G94)+$D94)+'การลงระหว่างเดือน ปี 2026'!AV47 -> #DIV/0! | ... T94: =(($D94*$G94)+$D94)+'การลงระหว่างเดือน ปี 2026'!AZ47 -> #DIV/0! | U94: =SUM(I94:T94) -> #DIV/0! | V94: =I94/$I$18 -> #DIV/0! | W94: =J94/$J$18 -> #DIV/0! | X94: =K94/$K$18 -> #DIV/0! | Y94: =L94/$L$18 -> #DIV/0! | Z94: =M94/$M$18 -> #DIV/0! | AA94: =N94/$N$18 -> #DIV/0! | AB94: =O94/$O$18 -> #DIV/0! | AC94: =P94/$P$18 -> #DIV/0! | AD94: =Q94/$Q$18 -> #DIV/0! | AE94: =R94/$R$18 -> #DIV/0! | AF94: =S94/$S$18 -> #DIV/0! | AG94: =T94/$T$18 -> #DIV/0! | AH94: =U94/$U$18 -> #DIV/0! | AI94: S | AJ94: =IFERROR(U94/E94,0)-1 -> -1
A95: ='งบกำไรขาดทุน ปี 2025'!A95 -> 60600005 | B95: ='งบกำไรขาดทุน ปี 2025'!B95 -> ค่าซ่อมแซมเครื่องมือแพทย์ | C95: ='งบกำไรขาดทุน ปี 2025'!O95 -> 0 | D95: =C95/$C$5 -> 0 | E95: =D95*$E$5 -> 0 | F95: =E95/$E$18 -> #DIV/0! | G95: =$F$98+1% -> #DIV/0! | H95: F | I95: =(($D95*$G95)+$D95)+'การลงระหว่างเดือน ปี 2026'!AO48 -> #DIV/0! | J95: =(($D95*$G95)+$D95)+'การลงระหว่างเดือน ปี 2026'!AP48 -> #DIV/0! | K95: =(($D95*$G95)+$D95)+'การลงระหว่างเดือน ปี 2026'!AQ48 -> #DIV/0! | L95: =(($D95*$G95)+$D95)+'การลงระหว่างเดือน ปี 2026'!AR48 -> #DIV/0! | M95: =(($D95*$G95)+$D95)+'การลงระหว่างเดือน ปี 2026'!AS48 -> #DIV/0! | N95: =(($D95*$G95)+$D95)+'การลงระหว่างเดือน ปี 2026'!AT48 -> #DIV/0! | O95: =(($D95*$G95)+$D95)+'การลงระหว่างเดือน ปี 2026'!AU48 -> #DIV/0! | P95: =(($D95*$G95)+$D95)+'การลงระหว่างเดือน ปี 2026'!AV48 -> #DIV/0! | ... T95: =(($D95*$G95)+$D95)+'การลงระหว่างเดือน ปี 2026'!AZ48 -> #DIV/0! | U95: =SUM(I95:T95) -> #DIV/0! | V95: =I95/$I$18 -> #DIV/0! | W95: =J95/$J$18 -> #DIV/0! | X95: =K95/$K$18 -> #DIV/0! | Y95: =L95/$L$18 -> #DIV/0! | Z95: =M95/$M$18 -> #DIV/0! | AA95: =N95/$N$18 -> #DIV/0! | AB95: =O95/$O$18 -> #DIV/0! | AC95: =P95/$P$18 -> #DIV/0! | AD95: =Q95/$Q$18 -> #DIV/0! | AE95: =R95/$R$18 -> #DIV/0! | AF95: =S95/$S$18 -> #DIV/0! | AG95: =T95/$T$18 -> #DIV/0! | AH95: =U95/$U$18 -> #DIV/0! | AI95: S | AJ95: =IFERROR(U95/E95,0)-1 -> -1
A96: ='งบกำไรขาดทุน ปี 2025'!A96 -> 60600006 | B96: ='งบกำไรขาดทุน ปี 2025'!B96 -> ค่าบำรุงรักษาโปรแกรม | C96: ='งบกำไรขาดทุน ปี 2025'!O96 -> 0 | D96: =C96/$C$5 -> 0 | E96: =D96*$E$5 -> 0 | F96: =E96/$E$18 -> #DIV/0! | G96: =$F$98+1% -> #DIV/0! | H96: F | I96: =(($D96*$G96)+$D96)+'การลงระหว่างเดือน ปี 2026'!AO49 -> #DIV/0! | J96: =(($D96*$G96)+$D96)+'การลงระหว่างเดือน ปี 2026'!AP49 -> #DIV/0! | K96: =(($D96*$G96)+$D96)+'การลงระหว่างเดือน ปี 2026'!AQ49 -> #DIV/0! | L96: =(($D96*$G96)+$D96)+'การลงระหว่างเดือน ปี 2026'!AR49 -> #DIV/0! | M96: =(($D96*$G96)+$D96)+'การลงระหว่างเดือน ปี 2026'!AS49 -> #DIV/0! | N96: =(($D96*$G96)+$D96)+'การลงระหว่างเดือน ปี 2026'!AT49 -> #DIV/0! | O96: =(($D96*$G96)+$D96)+'การลงระหว่างเดือน ปี 2026'!AU49 -> #DIV/0! | P96: =(($D96*$G96)+$D96)+'การลงระหว่างเดือน ปี 2026'!AV49 -> #DIV/0! | ... T96: =(($D96*$G96)+$D96)+'การลงระหว่างเดือน ปี 2026'!AZ49 -> #DIV/0! | U96: =SUM(I96:T96) -> #DIV/0! | V96: =I96/$I$18 -> #DIV/0! | W96: =J96/$J$18 -> #DIV/0! | X96: =K96/$K$18 -> #DIV/0! | Y96: =L96/$L$18 -> #DIV/0! | Z96: =M96/$M$18 -> #DIV/0! | AA96: =N96/$N$18 -> #DIV/0! | AB96: =O96/$O$18 -> #DIV/0! | AC96: =P96/$P$18 -> #DIV/0! | AD96: =Q96/$Q$18 -> #DIV/0! | AE96: =R96/$R$18 -> #DIV/0! | AF96: =S96/$S$18 -> #DIV/0! | AG96: =T96/$T$18 -> #DIV/0! | AH96: =U96/$U$18 -> #DIV/0! | AI96: S | AJ96: =IFERROR(U96/E96,0)-1 -> -1
A97: ='งบกำไรขาดทุน ปี 2025'!A97 -> 60600007 | B97: ='งบกำไรขาดทุน ปี 2025'!B97 -> ค่าบำรุงรักษาเครื่องใช้สำนักงาน | C97: ='งบกำไรขาดทุน ปี 2025'!O97 -> 0 | D97: =C97/$C$5 -> 0 | E97: =D97*$E$5 -> 0 | F97: =E97/$E$18 -> #DIV/0! | G97: =$F$98+1% -> #DIV/0! | H97: F | I97: =(($D97*$G97)+$D97)+'การลงระหว่างเดือน ปี 2026'!AO50 -> #DIV/0! | J97: =(($D97*$G97)+$D97)+'การลงระหว่างเดือน ปี 2026'!AP50 -> #DIV/0! | K97: =(($D97*$G97)+$D97)+'การลงระหว่างเดือน ปี 2026'!AQ50 -> #DIV/0! | L97: =(($D97*$G97)+$D97)+'การลงระหว่างเดือน ปี 2026'!AR50 -> #DIV/0! | M97: =(($D97*$G97)+$D97)+'การลงระหว่างเดือน ปี 2026'!AS50 -> #DIV/0! | N97: =(($D97*$G97)+$D97)+'การลงระหว่างเดือน ปี 2026'!AT50 -> #DIV/0! | O97: =(($D97*$G97)+$D97)+'การลงระหว่างเดือน ปี 2026'!AU50 -> #DIV/0! | P97: =(($D97*$G97)+$D97)+'การลงระหว่างเดือน ปี 2026'!AV50 -> #DIV/0! | ... T97: =(($D97*$G97)+$D97)+'การลงระหว่างเดือน ปี 2026'!AZ50 -> #DIV/0! | U97: =SUM(I97:T97) -> #DIV/0! | V97: =I97/$I$18 -> #DIV/0! | W97: =J97/$J$18 -> #DIV/0! | X97: =K97/$K$18 -> #DIV/0! | Y97: =L97/$L$18 -> #DIV/0! | Z97: =M97/$M$18 -> #DIV/0! | AA97: =N97/$N$18 -> #DIV/0! | AB97: =O97/$O$18 -> #DIV/0! | AC97: =P97/$P$18 -> #DIV/0! | AD97: =Q97/$Q$18 -> #DIV/0! | AE97: =R97/$R$18 -> #DIV/0! | AF97: =S97/$S$18 -> #DIV/0! | AG97: =T97/$T$18 -> #DIV/0! | AH97: =U97/$U$18 -> #DIV/0! | AI97: S | AJ97: =IFERROR(U97/E97,0)-1 -> -1
A98: ='งบกำไรขาดทุน ปี 2025'!A98 -> 0 | B98: ='งบกำไรขาดทุน ปี 2025'!B98 -> รวมค่าซ่อมแซมและค่าบำรุงรักษา | C98: ='งบกำไรขาดทุน ปี 2025'!O98 -> 0 | D98: =C98/$C$5 -> 0 | E98: =D98*$E$5 -> 0 | F98: =E98/$E$18 -> #DIV/0! | I98: =SUM(I91:I97) -> #DIV/0! | J98: =SUM(J91:J97) -> #DIV/0! | K98: =SUM(K91:K97) -> #DIV/0! | L98: =SUM(L91:L97) -> #DIV/0! | M98: =SUM(M91:M97) -> #DIV/0! | N98: =SUM(N91:N97) -> #DIV/0! | O98: =SUM(O91:O97) -> #DIV/0! | P98: =SUM(P91:P97) -> #DIV/0! | ... U98: =SUM(U91:U97) -> #DIV/0! | V98: =I98/$I$18 -> #DIV/0! | W98: =J98/$J$18 -> #DIV/0! | X98: =K98/$K$18 -> #DIV/0! | Y98: =L98/$L$18 -> #DIV/0! | Z98: =M98/$M$18 -> #DIV/0! | AA98: =N98/$N$18 -> #DIV/0! | AB98: =O98/$O$18 -> #DIV/0! | AC98: =P98/$P$18 -> #DIV/0! | AD98: =Q98/$Q$18 -> #DIV/0! | AE98: =R98/$R$18 -> #DIV/0! | AF98: =S98/$S$18 -> #DIV/0! | AG98: =T98/$T$18 -> #DIV/0! | AH98: =U98/$U$18 -> #DIV/0! | AJ98: =IFERROR(U98/E98,0)-1 -> -1
A99: ='งบกำไรขาดทุน ปี 2025'!A99 -> 0 | B99: ='งบกำไรขาดทุน ปี 2025'!B99 -> ค่าสาธารณูปโภค | C99: ='งบกำไรขาดทุน ปี 2025'!O99 -> 0 | AJ99: =IFERROR(U99/E99,0)-1 -> -1
A100: ='งบกำไรขาดทุน ปี 2025'!A100 -> 60700001 | B100: ='งบกำไรขาดทุน ปี 2025'!B100 -> ค่าโทรศัพท์ | C100: ='งบกำไรขาดทุน ปี 2025'!O100 -> 0 | D100: =C100/$C$5 -> 0 | E100: =D100*$E$5 -> 0 | F100: =E100/$E$18 -> #DIV/0! | G100: =$U$2 -> #DIV/0! | H100: F | I100: =(($D100*$G100)+$D100) -> #DIV/0! | J100: =(($D100*$G100)+$D100) -> #DIV/0! | K100: =(($D100*$G100)+$D100) -> #DIV/0! | L100: =(($D100*$G100)+$D100) -> #DIV/0! | M100: =(($D100*$G100)+$D100) -> #DIV/0! | N100: =(($D100*$G100)+$D100) -> #DIV/0! | O100: =(($D100*$G100)+$D100) -> #DIV/0! | P100: =(($D100*$G100)+$D100) -> #DIV/0! | ... T100: =(($D100*$G100)+$D100) -> #DIV/0! | U100: =SUM(I100:T100) -> #DIV/0! | V100: =I100/$I$18 -> #DIV/0! | W100: =J100/$J$18 -> #DIV/0! | X100: =K100/$K$18 -> #DIV/0! | Y100: =L100/$L$18 -> #DIV/0! | Z100: =M100/$M$18 -> #DIV/0! | AA100: =N100/$N$18 -> #DIV/0! | AB100: =O100/$O$18 -> #DIV/0! | AC100: =P100/$P$18 -> #DIV/0! | AD100: =Q100/$Q$18 -> #DIV/0! | AE100: =R100/$R$18 -> #DIV/0! | AF100: =S100/$S$18 -> #DIV/0! | AG100: =T100/$T$18 -> #DIV/0! | AH100: =U100/$U$18 -> #DIV/0! | AI100: S | AJ100: =IFERROR(U100/E100,0)-1 -> -1
...

Sheet การลงระหว่างเดือน ปี 2026
A1: THONGLOR PET HOSPITAL COMPANY LIMITED
A2: บริษัท โรงพยาบาลสัตว์ทองหล่อ จำกัด | G2: 0.01
B4: อายุการใช้งาน | C4: January | F4: February | I4: March | L4: April | O4: May | R4: June | U4: July | X4: August | AA4: September | AD4: October | AG4: November | AJ4: December | AM4: รวม | AO4: ลงระหว่างเดือนใน Budget
C5: รายละเอียด | D5: งบประมาณที่ใช้ | E5: ลงระหว่างเดือน | F5: รายละเอียด | G5: งบประมาณที่ใช้ | H5: ลงระหว่างเดือน | I5: รายละเอียด | J5: งบประมาณที่ใช้ | K5: ลงระหว่างเดือน | L5: รายละเอียด | M5: งบประมาณที่ใช้ | N5: ลงระหว่างเดือน | O5: รายละเอียด | P5: งบประมาณที่ใช้ | Q5: ลงระหว่างเดือน | R5: รายละเอียด | S5: งบประมาณที่ใช้ | T5: ลงระหว่างเดือน | U5: รายละเอียด | V5: งบประมาณที่ใช้ | W5: ลงระหว่างเดือน | X5: รายละเอียด | Y5: งบประมาณที่ใช้ | Z5: ลงระหว่างเดือน | AA5: รายละเอียด | AB5: งบประมาณที่ใช้ | AC5: ลงระหว่างเดือน | AD5: รายละเอียด | AE5: งบประมาณที่ใช้ | AF5: ลงระหว่างเดือน | AG5: รายละเอียด | AH5: งบประมาณที่ใช้ | AI5: ลงระหว่างเดือน | AJ5: รายละเอียด | AK5: งบประมาณที่ใช้ | AL5: ลงระหว่างเดือน | AO5: January | AP5: February | AQ5: March | AR5: April | AS5: May | AT5: June | AU5: July | AV5: August | AW5: September | AX5: October | AY5: November | AZ5: December
A6: รายได้ | BB6: รายได้ | BC6: JAN | BD6: FEB | BE6: MAR | BF6: APR | BG6: MAY | BH6: JUN | BI6: JUL | BJ6: AUG | BK6: SEP | BL6: OCT | BM6: NOV | BN6: DEC | BO6: Total | BP6: ผลต่าง
A7: รายได้จากการขาย - OPD/IPD | D7: =BC7 -> 0 | E7: =D7 -> 0 | G7: =BD7 -> 0 | H7: =G7 -> 0 | J7: =BE7 -> 0 | K7: =J7 -> 0 | M7: =BF7 -> 0 | N7: =M7 -> 0 | P7: =BG7 -> 0 | Q7: =P7 -> 0 | S7: =BH7 -> 0 | T7: =S7 -> 0 | V7: =BI7 -> 0 | W7: =V7 -> 0 | Y7: =BJ7 -> 0 | Z7: =Y7 -> 0 | AB7: =BK7 -> 0 | AC7: =AB7 -> 0 | AE7: =BL7 -> 0 | AF7: =AE7 -> 0 | AH7: =BM7 -> 0 | AI7: =AH7 -> 0 | AK7: =BN7 -> 0 | AL7: =AK7 -> 0 | AM7: =SUM(D7,G7,J7,M7,P7,S7,V7,Y7,AB7,AE7,AH7,AK7) -> 0 | AO7: =E7 -> 0 | AP7: =H7 -> 0 | AQ7: =K7 -> 0 | AR7: =N7 -> 0 | AS7: =Q7 -> 0 | AT7: =T7 -> 0 | AU7: =W7 -> 0 | AV7: =Z7 -> 0 | AW7: =AC7 -> 0 | AX7: =AF7 -> 0 | AY7: =AI7 -> 0 | AZ7: =AL7 -> 0 | BB7: รายได้จากการขาย - OPD/IPD | BO7: =SUM(BC7:BN7) -> 0 | BP7: =BO7-AM7 -> 0
A8: รายได้จากการขาย - Grooming | D8: =BC8 -> 0 | E8: =D8 -> 0 | G8: =BD8 -> 0 | H8: =G8 -> 0 | J8: =BE8 -> 0 | K8: =J8 -> 0 | M8: =BF8 -> 0 | N8: =M8 -> 0 | P8: =BG8 -> 0 | Q8: =P8 -> 0 | S8: =BH8 -> 0 | T8: =S8 -> 0 | V8: =BI8 -> 0 | W8: =V8 -> 0 | Y8: =BJ8 -> 0 | Z8: =Y8 -> 0 | AB8: =BK8 -> 0 | AC8: =AB8 -> 0 | AE8: =BL8 -> 0 | AF8: =AE8 -> 0 | AH8: =BM8 -> 0 | AI8: =AH8 -> 0 | AK8: =BN8 -> 0 | AL8: =AK8 -> 0 | AM8: =SUM(D8,G8,J8,M8,P8,S8,V8,Y8,AB8,AE8,AH8,AK8) -> 0 | AO8: =E8 -> 0 | AP8: =H8 -> 0 | AQ8: =K8 -> 0 | AR8: =N8 -> 0 | AS8: =Q8 -> 0 | AT8: =T8 -> 0 | AU8: =W8 -> 0 | AV8: =Z8 -> 0 | AW8: =AC8 -> 0 | AX8: =AF8 -> 0 | AY8: =AI8 -> 0 | AZ8: =AL8 -> 0 | BB8: รายได้จากการขาย - Grooming | BO8: =SUM(BC8:BN8) -> 0 | BP8: =BO8-AM8 -> 0
A9: รายได้จากการขาย - Petshop | D9: =BC9 -> 0 | E9: =D9 -> 0 | G9: =BD9 -> 0 | H9: =G9 -> 0 | J9: =BE9 -> 0 | K9: =J9 -> 0 | M9: =BF9 -> 0 | N9: =M9 -> 0 | P9: =BG9 -> 0 | Q9: =P9 -> 0 | S9: =BH9 -> 0 | T9: =S9 -> 0 | V9: =BI9 -> 0 | W9: =V9 -> 0 | Y9: =BJ9 -> 0 | Z9: =Y9 -> 0 | AB9: =BK9 -> 0 | AC9: =AB9 -> 0 | AE9: =BL9 -> 0 | AF9: =AE9 -> 0 | AH9: =BM9 -> 0 | AI9: =AH9 -> 0 | AK9: =BN9 -> 0 | AL9: =AK9 -> 0 | AM9: =SUM(D9,G9,J9,M9,P9,S9,V9,Y9,AB9,AE9,AH9,AK9) -> 0 | AO9: =E9 -> 0 | AP9: =H9 -> 0 | AQ9: =K9 -> 0 | AR9: =N9 -> 0 | AS9: =Q9 -> 0 | AT9: =T9 -> 0 | AU9: =W9 -> 0 | AV9: =Z9 -> 0 | AW9: =AC9 -> 0 | AX9: =AF9 -> 0 | AY9: =AI9 -> 0 | AZ9: =AL9 -> 0 | BB9: รายได้จากการขาย - Petshop | BO9: =SUM(BC9:BN9) -> 0 | BP9: =BO9-AM9 -> 0
A10: รายได้จากการขาย - Swimming | D10: =BC10 -> 0 | E10: =D10 -> 0 | G10: =BD10 -> 0 | H10: =G10 -> 0 | J10: =BE10 -> 0 | K10: =J10 -> 0 | M10: =BF10 -> 0 | N10: =M10 -> 0 | P10: =BG10 -> 0 | Q10: =P10 -> 0 | S10: =BH10 -> 0 | T10: =S10 -> 0 | V10: =BI10 -> 0 | W10: =V10 -> 0 | Y10: =BJ10 -> 0 | Z10: =Y10 -> 0 | AB10: =BK10 -> 0 | AC10: =AB10 -> 0 | AE10: =BL10 -> 0 | AF10: =AE10 -> 0 | AH10: =BM10 -> 0 | AI10: =AH10 -> 0 | AK10: =BN10 -> 0 | AL10: =AK10 -> 0 | AM10: =SUM(D10,G10,J10,M10,P10,S10,V10,Y10,AB10,AE10,AH10,AK10) -> 0 | AO10: =E10 -> 0 | AP10: =H10 -> 0 | AQ10: =K10 -> 0 | AR10: =N10 -> 0 | AS10: =Q10 -> 0 | AT10: =T10 -> 0 | AU10: =W10 -> 0 | AV10: =Z10 -> 0 | AW10: =AC10 -> 0 | AX10: =AF10 -> 0 | AY10: =AI10 -> 0 | AZ10: =AL10 -> 0 | BB10: รายได้จากการขาย - Swimming | BO10: =SUM(BC10:BN10) -> 0 | BP10: =BO10-AM10 -> 0
A11: รายได้จากการขาย - Pettaxi | D11: =BC11 -> 0 | E11: =D11 -> 0 | G11: =BD11 -> 0 | H11: =G11 -> 0 | J11: =BE11 -> 0 | K11: =J11 -> 0 | M11: =BF11 -> 0 | N11: =M11 -> 0 | P11: =BG11 -> 0 | Q11: =P11 -> 0 | S11: =BH11 -> 0 | T11: =S11 -> 0 | V11: =BI11 -> 0 | W11: =V11 -> 0 | Y11: =BJ11 -> 0 | Z11: =Y11 -> 0 | AB11: =BK11 -> 0 | AC11: =AB11 -> 0 | AE11: =BL11 -> 0 | AF11: =AE11 -> 0 | AH11: =BM11 -> 0 | AI11: =AH11 -> 0 | AK11: =BN11 -> 0 | AL11: =AK11 -> 0 | AM11: =SUM(D11,G11,J11,M11,P11,S11,V11,Y11,AB11,AE11,AH11,AK11) -> 0 | AO11: =E11 -> 0 | AP11: =H11 -> 0 | AQ11: =K11 -> 0 | AR11: =N11 -> 0 | AS11: =Q11 -> 0 | AT11: =T11 -> 0 | AU11: =W11 -> 0 | AV11: =Z11 -> 0 | AW11: =AC11 -> 0 | AX11: =AF11 -> 0 | AY11: =AI11 -> 0 | AZ11: =AL11 -> 0 | BB11: รายได้จากการขาย - Pettaxi | BO11: =SUM(BC11:BN11) -> 0 | BP11: =BO11-AM11 -> 0
A12: ค่าใช้จ่ายในการขาย | BB12: Total | BC12: =SUM(BC7:BC11) -> 0 | BD12: =SUM(BD7:BD11) -> 0 | BE12: =SUM(BE7:BE11) -> 0 | BF12: =SUM(BF7:BF11) -> 0 | BG12: =SUM(BG7:BG11) -> 0 | BH12: =SUM(BH7:BH11) -> 0 | BI12: =SUM(BI7:BI11) -> 0 | BJ12: =SUM(BJ7:BJ11) -> 0 | ... BO12: =SUM(BO7:BO11) -> 0
A13: ค่าส่งเสริมการขาย | B13: โปร คูปอง หรือสิทธิ์ที่ให้ลูกค้าเพื่อเร่งยอดขาย | E13: =D13 -> 0 | H13: =G13 -> 0 | K13: =J13 -> 0 | N13: =M13 -> 0 | Q13: =P13 -> 0 | T13: =S13 -> 0 | W13: =V13 -> 0 | Z13: =Y13 -> 0 | AC13: =AB13 -> 0 | AF13: =AE13 -> 0 | AI13: =AH13 -> 0 | AL13: =AK13 -> 0 | AM13: =SUM(D13,G13,J13,M13,P13,S13,V13,Y13,AB13,AE13,AH13,AK13) -> 0 | AO13: =E13 -> 0 | AP13: =H13 -> 0 | AQ13: =K13 -> 0 | AR13: =N13 -> 0 | AS13: =Q13 -> 0 | AT13: =T13 -> 0 | AU13: =W13 -> 0 | AV13: =Z13 -> 0 | AW13: =AC13 -> 0 | AX13: =AF13 -> 0 | AY13: =AI13 -> 0 | AZ13: =AL13 -> 0
A14: ค่าบริการวิชาชีพแพทย์ | D14: ='กำลัง VET'!E30 -> 0 | E14: =D14 -> 0 | G14: ='กำลัง VET'!F30 -> 0 | H14: =E14+G14 -> 0 | J14: ='กำลัง VET'!G30 -> 0 | K14: =H14+J14 -> 0 | M14: ='กำลัง VET'!H30 -> 0 | N14: =K14+M14 -> 0 | P14: ='กำลัง VET'!I30 -> 0 | Q14: =N14+P14 -> 0 | S14: ='กำลัง VET'!J30 -> 0 | T14: =Q14+S14 -> 0 | V14: ='กำลัง VET'!K30 -> 0 | W14: =T14+V14 -> 0 | Y14: ='กำลัง VET'!L30 -> 0 | Z14: =W14+Y14 -> 0 | AB14: ='กำลัง VET'!M30 -> 0 | AC14: =Z14+AB14 -> 0 | AE14: ='กำลัง VET'!N30 -> 0 | AF14: =AC14+AE14 -> 0 | AH14: ='กำลัง VET'!O30 -> 0 | AI14: =AF14+AH14 -> 0 | AK14: ='กำลัง VET'!P30 -> 0 | AL14: =AI14+AK14 -> 0 | AM14: =SUM(D14,G14,J14,M14,P14,S14,V14,Y14,AB14,AE14,AH14,AK14) -> 0 | AO14: =E14 -> 0 | AP14: =H14 -> 0 | AQ14: =K14 -> 0 | AR14: =N14 -> 0 | AS14: =Q14 -> 0 | AT14: =T14 -> 0 | AU14: =W14 -> 0 | AV14: =Z14 -> 0 | AW14: =AC14 -> 0 | AX14: =AF14 -> 0 | AY14: =AI14 -> 0 | AZ14: =AL14 -> 0
A15: ค่าเช่าเครื่องมือแพทย์ | E15: =D15 -> 0 | H15: =G15 -> 0 | K15: =J15 -> 0 | N15: =M15 -> 0 | Q15: =P15 -> 0 | T15: =S15 -> 0 | W15: =V15 -> 0 | Z15: =Y15 -> 0 | AC15: =AB15 -> 0 | AF15: =AE15 -> 0 | AI15: =AH15 -> 0 | AL15: =AK15 -> 0 | AM15: =SUM(D15,G15,J15,M15,P15,S15,V15,Y15,AB15,AE15,AH15,AK15) -> 0 | AO15: =E15 -> 0 | AP15: =H15 -> 0 | AQ15: =K15 -> 0 | AR15: =N15 -> 0 | AS15: =Q15 -> 0 | AT15: =T15 -> 0 | AU15: =W15 -> 0 | AV15: =Z15 -> 0 | AW15: =AC15 -> 0 | AX15: =AF15 -> 0 | AY15: =AI15 -> 0 | AZ15: =AL15 -> 0
A16: ค่าวัสดุเครื่องมือแพทย์ | E16: =D16 -> 0 | H16: =G16 -> 0 | K16: =J16 -> 0 | N16: =M16 -> 0 | Q16: =P16 -> 0 | T16: =S16 -> 0 | W16: =V16 -> 0 | Z16: =Y16 -> 0 | AC16: =AB16 -> 0 | AF16: =AE16 -> 0 | AI16: =AH16 -> 0 | AL16: =AK16 -> 0 | AM16: =SUM(D16,G16,J16,M16,P16,S16,V16,Y16,AB16,AE16,AH16,AK16) -> 0 | AO16: =E16 -> 0 | AP16: =H16 -> 0 | AQ16: =K16 -> 0 | AR16: =N16 -> 0 | AS16: =Q16 -> 0 | AT16: =T16 -> 0 | AU16: =W16 -> 0 | AV16: =Z16 -> 0 | AW16: =AC16 -> 0 | AX16: =AF16 -> 0 | AY16: =AI16 -> 0 | AZ16: =AL16 -> 0
A17: ค่าเช่าอุปกรณ์-เครื่องมือระหว่างสาขา | E17: =D17 -> 0 | H17: =G17 -> 0 | K17: =J17 -> 0 | N17: =M17 -> 0 | Q17: =P17 -> 0 | T17: =S17 -> 0 | W17: =V17 -> 0 | Z17: =Y17 -> 0 | AC17: =AB17 -> 0 | AF17: =AE17 -> 0 | AI17: =AH17 -> 0 | AL17: =AK17 -> 0 | AM17: =SUM(D17,G17,J17,M17,P17,S17,V17,Y17,AB17,AE17,AH17,AK17) -> 0 | AO17: =E17 -> 0 | AP17: =H17 -> 0 | AQ17: =K17 -> 0 | AR17: =N17 -> 0 | AS17: =Q17 -> 0 | AT17: =T17 -> 0 | AU17: =W17 -> 0 | AV17: =Z17 -> 0 | AW17: =AC17 -> 0 | AX17: =AF17 -> 0 | AY17: =AI17 -> 0 | AZ17: =AL17 -> 0
A18: ค่าเสื่อมราคา - เครื่องมือแพทย์ | B18: 0.2 | D18: =เครื่องมือแพทย์!E61 -> 0 | E18: =((D18*$B$18)/12) -> 0 | G18: =เครื่องมือแพทย์!F61 -> 0 | H18: =((G18*$B$18)/12)+E18 -> 0 | J18: =เครื่องมือแพทย์!G61 -> 0 | K18: =((J18*$B$18)/12)+H18 -> 0 | M18: =เครื่องมือแพทย์!H61 -> 0 | N18: =((M18*$B$18)/12)+K18 -> 0 | P18: =เครื่องมือแพทย์!I61 -> 0 | Q18: =((P18*$B$18)/12)+N18 -> 0 | S18: =เครื่องมือแพทย์!J61 -> 0 | T18: =((S18*$B$18)/12)+Q18 -> 0 | V18: =เครื่องมือแพทย์!K61 -> 0 | W18: =((V18*$B$18)/12)+T18 -> 0 | Y18: =เครื่องมือแพทย์!L61 -> 0 | Z18: =((Y18*$B$18)/12)+W18 -> 0 | AB18: =เครื่องมือแพทย์!M61 -> 0 | AC18: =((AB18*$B$18)/12)+Z18 -> 0 | AE18: =เครื่องมือแพทย์!N61 -> 0 | AF18: =((AE18*$B$18)/12)+AC18 -> 0 | AH18: =เครื่องมือแพทย์!O61 -> 0 | AI18: =((AH18*$B$18)/12)+AF18 -> 0 | AK18: =เครื่องมือแพทย์!P61 -> 0 | AL18: =((AK18*$B$18)/12)+AI18 -> 0 | AM18: =SUM(D18,G18,J18,M18,P18,S18,V18,Y18,AB18,AE18,AH18,AK18) -> 0 | AO18: =E18 -> 0 | AP18: =H18 -> 0 | AQ18: =K18 -> 0 | AR18: =N18 -> 0 | AS18: =Q18 -> 0 | AT18: =T18 -> 0 | AU18: =W18 -> 0 | AV18: =Z18 -> 0 | AW18: =AC18 -> 0 | AX18: =AF18 -> 0 | AY18: =AI18 -> 0 | AZ18: =AL18 -> 0
A19: เงินเดือนและสวัสดิการพนักงาน
A20: เงินเดือน | D20: ='กำลังคนNON VET'!F50+ปรับตำแหน่ง!E29 -> 0 | E20: =D20 -> 0 | G20: ='กำลังคนNON VET'!G50+ปรับตำแหน่ง!F29 -> 0 | H20: =G20+E20 -> 0 | J20: ='กำลังคนNON VET'!H50+ปรับตำแหน่ง!G29 -> 0 | K20: =J20+H20 -> 0 | M20: ='กำลังคนNON VET'!I50+ปรับตำแหน่ง!H29 -> 0 | N20: =M20+K20 -> 0 | P20: ='กำลังคนNON VET'!J50+ปรับตำแหน่ง!I29 -> 0 | Q20: =P20+N20 -> 0 | S20: ='กำลังคนNON VET'!K50+ปรับตำแหน่ง!J29 -> 0 | T20: =S20+Q20 -> 0 | V20: ='กำลังคนNON VET'!L50+ปรับตำแหน่ง!K29 -> 0 | W20: =V20+T20 -> 0 | Y20: ='กำลังคนNON VET'!M50+ปรับตำแหน่ง!L29 -> 0 | Z20: =Y20+W20 -> 0 | AB20: ='กำลังคนNON VET'!N50+ปรับตำแหน่ง!M29 -> 0 | AC20: =AB20+Z20 -> 0 | AE20: ='กำลังคนNON VET'!O50+ปรับตำแหน่ง!N29 -> 0 | AF20: =AE20+AC20 -> 0 | AH20: ='กำลังคนNON VET'!P50+ปรับตำแหน่ง!O29 -> 0 | AI20: =AH20+AF20 -> 0 | AK20: ='กำลังคนNON VET'!Q50+ปรับตำแหน่ง!P29 -> 0 | AL20: =AK20+AI20 -> 0 | AM20: =SUM(D20,G20,J20,M20,P20,S20,V20,Y20,AB20,AE20,AH20,AK20) -> 0 | AO20: =E20 -> 0 | AP20: =H20 -> 0 | AQ20: =K20 -> 0 | AR20: =N20 -> 0 | AS20: =Q20 -> 0 | AT20: =T20 -> 0 | AU20: =W20 -> 0 | AV20: =Z20 -> 0 | AW20: =AC20 -> 0 | AX20: =AF20 -> 0 | AY20: =AI20 -> 0 | AZ20: =AL20 -> 0
A21: ค่าหัวหน้าฝ่ายวิชาการแพทย์ | E21: =D21 -> 0 | H21: =G21+E21 -> 0 | K21: =J21+H21 -> 0 | N21: =M21+K21 -> 0 | Q21: =P21+N21 -> 0 | T21: =S21+Q21 -> 0 | W21: =V21+T21 -> 0 | Z21: =Y21+W21 -> 0 | AC21: =AB21+Z21 -> 0 | AF21: =AE21+AC21 -> 0 | AI21: =AH21+AF21 -> 0 | AL21: =AK21+AI21 -> 0 | AM21: =SUM(D21,G21,J21,M21,P21,S21,V21,Y21,AB21,AE21,AH21,AK21) -> 0 | AO21: =E21 -> 0 | AP21: =H21 -> 0 | AQ21: =K21 -> 0 | AR21: =N21 -> 0 | AS21: =Q21 -> 0 | AT21: =T21 -> 0 | AU21: =W21 -> 0 | AV21: =Z21 -> 0 | AW21: =AC21 -> 0 | AX21: =AF21 -> 0 | AY21: =AI21 -> 0 | AZ21: =AL21 -> 0
A22: เงินเดือนพยาบาล (ไม่ใช้อันนี้) | AO22: =E22 -> 0 | AP22: =H22 -> 0 | AQ22: =K22 -> 0 | AR22: =N22 -> 0 | AS22: =Q22 -> 0 | AT22: =T22 -> 0 | AU22: =W22 -> 0 | AV22: =Z22 -> 0 | AW22: =AC22 -> 0 | AX22: =AF22 -> 0 | AY22: =AI22 -> 0 | AZ22: =AL22 -> 0
A23: ค่าเช่ายานพาหนะ | E23: =D23 -> 0 | H23: =G23+E23 -> 0 | K23: =J23+H23 -> 0 | N23: =M23+K23 -> 0 | Q23: =P23+N23 -> 0 | T23: =S23+Q23 -> 0 | W23: =V23+T23 -> 0 | Z23: =Y23+W23 -> 0 | AC23: =AB23+Z23 -> 0 | AF23: =AE23+AC23 -> 0 | AI23: =AH23+AF23 -> 0 | AL23: =AK23+AI23 -> 0 | AM23: =SUM(D23,G23,J23,M23,P23,S23,V23,Y23,AB23,AE23,AH23,AK23) -> 0 | AO23: =E23 -> 0 | AP23: =H23 -> 0 | AQ23: =K23 -> 0 | AR23: =N23 -> 0 | AS23: =Q23 -> 0 | AT23: =T23 -> 0 | AU23: =W23 -> 0 | AV23: =Z23 -> 0 | AW23: =AC23 -> 0 | AX23: =AF23 -> 0 | AY23: =AI23 -> 0 | AZ23: =AL23 -> 0
A24: ค่าวัดระดับ/ค่าตำแหน่ง | D24: ='กำลังคนNON VET'!F75+ปรับตำแหน่ง!E44 -> 0 | E24: =D24 -> 0 | G24: ='กำลังคนNON VET'!G75+ปรับตำแหน่ง!F44 -> 0 | H24: =G24+E24 -> 0 | J24: ='กำลังคนNON VET'!H75+ปรับตำแหน่ง!G44 -> 0 | K24: =J24+H24 -> 0 | M24: ='กำลังคนNON VET'!I75+ปรับตำแหน่ง!H44 -> 0 | N24: =M24+K24 -> 0 | P24: ='กำลังคนNON VET'!J75+ปรับตำแหน่ง!I44 -> 0 | Q24: =P24+N24 -> 0 | S24: ='กำลังคนNON VET'!K75+ปรับตำแหน่ง!J44 -> 0 | T24: =S24+Q24 -> 0 | V24: ='กำลังคนNON VET'!L75+ปรับตำแหน่ง!K44 -> 0 | W24: =V24+T24 -> 0 | Y24: ='กำลังคนNON VET'!M75+ปรับตำแหน่ง!L44 -> 0 | Z24: =Y24+W24 -> 0 | AB24: ='กำลังคนNON VET'!N75+ปรับตำแหน่ง!M44 -> 0 | AC24: =AB24+Z24 -> 0 | AE24: ='กำลังคนNON VET'!O75+ปรับตำแหน่ง!N44 -> 0 | AF24: =AE24+AC24 -> 0 | AH24: ='กำลังคนNON VET'!P75+ปรับตำแหน่ง!O44 -> 0 | AI24: =AH24+AF24 -> 0 | AK24: ='กำลังคนNON VET'!Q75+ปรับตำแหน่ง!P44 -> 0 | AL24: =AK24+AI24 -> 0 | AM24: =SUM(D24,G24,J24,M24,P24,S24,V24,Y24,AB24,AE24,AH24,AK24) -> 0 | AO24: =E24 -> 0 | AP24: =H24 -> 0 | AQ24: =K24 -> 0 | AR24: =N24 -> 0 | AS24: =Q24 -> 0 | AT24: =T24 -> 0 | AU24: =W24 -> 0 | AV24: =Z24 -> 0 | AW24: =AC24 -> 0 | AX24: =AF24 -> 0 | AY24: =AI24 -> 0 | AZ24: =AL24 -> 0
A25: เงินกองทุนสำรองเลี้ยงชีพ | B25: 0.02 | D25: =(D20+D21+D22)*$B$25 -> 0 | E25: =D25 -> 0 | G25: =(G20+G21+G22)*$B$25 -> 0 | H25: =G25+E25 -> 0 | J25: =(J20+J21+J22)*$B$25 -> 0 | K25: =J25+H25 -> 0 | M25: =(M20+M21+M22)*$B$25 -> 0 | N25: =M25+K25 -> 0 | P25: =(P20+P21+P22)*$B$25 -> 0 | Q25: =P25+N25 -> 0 | S25: =(S20+S21+S22)*$B$25 -> 0 | T25: =S25+Q25 -> 0 | V25: =(V20+V21+V22)*$B$25 -> 0 | W25: =V25+T25 -> 0 | Y25: =(Y20+Y21+Y22)*$B$25 -> 0 | Z25: =Y25+W25 -> 0 | AB25: =(AB20+AB21+AB22)*$B$25 -> 0 | AC25: =AB25+Z25 -> 0 | AE25: =(AE20+AE21+AE22)*$B$25 -> 0 | AF25: =AE25+AC25 -> 0 | AH25: =(AH20+AH21+AH22)*$B$25 -> 0 | AI25: =AH25+AF25 -> 0 | AK25: =(AK20+AK21+AK22)*$B$25 -> 0 | AL25: =AK25+AI25 -> 0 | AM25: =SUM(D25,G25,J25,M25,P25,S25,V25,Y25,AB25,AE25,AH25,AK25) -> 0 | AO25: =E25 -> 0 | AP25: =H25 -> 0 | AQ25: =K25 -> 0 | AR25: =N25 -> 0 | AS25: =Q25 -> 0 | AT25: =T25 -> 0 | AU25: =W25 -> 0 | AV25: =Z25 -> 0 | AW25: =AC25 -> 0 | AX25: =AF25 -> 0 | AY25: =AI25 -> 0 | AZ25: =AL25 -> 0
A26: ค่าสวัสดิการพนักงาน | B26: 0.15 | D26: =(D20+D21+D22)*$B$26 -> 0 | E26: =D26 -> 0 | G26: =(G20+G21+G22)*$B$26 -> 0 | H26: =G26+E26 -> 0 | J26: =(J20+J21+J22)*$B$26 -> 0 | K26: =J26+H26 -> 0 | M26: =(M20+M21+M22)*$B$26 -> 0 | N26: =M26+K26 -> 0 | P26: =(P20+P21+P22)*$B$26 -> 0 | Q26: =P26+N26 -> 0 | S26: =(S20+S21+S22)*$B$26 -> 0 | T26: =S26+Q26 -> 0 | V26: =(V20+V21+V22)*$B$26 -> 0 | W26: =V26+T26 -> 0 | Y26: =(Y20+Y21+Y22)*$B$26 -> 0 | Z26: =Y26+W26 -> 0 | AB26: =(AB20+AB21+AB22)*$B$26 -> 0 | AC26: =AB26+Z26 -> 0 | AE26: =(AE20+AE21+AE22)*$B$26 -> 0 | AF26: =AE26+AC26 -> 0 | AH26: =(AH20+AH21+AH22)*$B$26 -> 0 | AI26: =AH26+AF26 -> 0 | AK26: =(AK20+AK21+AK22)*$B$26 -> 0 | AL26: =AK26+AI26 -> 0 | AM26: =SUM(D26,G26,J26,M26,P26,S26,V26,Y26,AB26,AE26,AH26,AK26) -> 0 | AO26: =E26 -> 0 | AP26: =H26 -> 0 | AQ26: =K26 -> 0 | AR26: =N26 -> 0 | AS26: =Q26 -> 0 | AT26: =T26 -> 0 | AU26: =W26 -> 0 | AV26: =Z26 -> 0 | AW26: =AC26 -> 0 | AX26: =AF26 -> 0 | AY26: =AI26 -> 0 | AZ26: =AL26 -> 0
A27: เงินกองทุนประกันสังคม | B27: 0.05 | D27: =(D20+D21+D22)*$B$27 -> 0 | E27: =D27 -> 0 | G27: =(G20+G21+G22)*$B$27 -> 0 | H27: =G27+E27 -> 0 | J27: =(J20+J21+J22)*$B$27 -> 0 | K27: =J27+H27 -> 0 | M27: =(M20+M21+M22)*$B$27 -> 0 | N27: =M27+K27 -> 0 | P27: =(P20+P21+P22)*$B$27 -> 0 | Q27: =P27+N27 -> 0 | S27: =(S20+S21+S22)*$B$27 -> 0 | T27: =S27+Q27 -> 0 | V27: =(V20+V21+V22)*$B$27 -> 0 | W27: =V27+T27 -> 0 | Y27: =(Y20+Y21+Y22)*$B$27 -> 0 | Z27: =Y27+W27 -> 0 | AB27: =(AB20+AB21+AB22)*$B$27 -> 0 | AC27: =AB27+Z27 -> 0 | AE27: =(AE20+AE21+AE22)*$B$27 -> 0 | AF27: =AE27+AC27 -> 0 | AH27: =(AH20+AH21+AH22)*$B$27 -> 0 | AI27: =AH27+AF27 -> 0 | AK27: =(AK20+AK21+AK22)*$B$27 -> 0 | AL27: =AK27+AI27 -> 0 | AM27: =SUM(D27,G27,J27,M27,P27,S27,V27,Y27,AB27,AE27,AH27,AK27) -> 0 | AO27: =E27 -> 0 | AP27: =H27 -> 0 | AQ27: =K27 -> 0 | AR27: =N27 -> 0 | AS27: =Q27 -> 0 | AT27: =T27 -> 0 | AU27: =W27 -> 0 | AV27: =Z27 -> 0 | AW27: =AC27 -> 0 | AX27: =AF27 -> 0 | AY27: =AI27 -> 0 | AZ27: =AL27 -> 0
A28: ค่า Incentive | B28: 0.03 | D28: =(D7+D8+D9+D10+D11)*$B$28 -> 0 | E28: =D28 -> 0 | G28: =(G7+G8+G9+G10+G11)*$B$28 -> 0 | H28: =G28 -> 0 | J28: =(J7+J8+J9+J10+J11)*$B$28 -> 0 | K28: =J28 -> 0 | M28: =(M7+M8+M9+M10+M11)*$B$28 -> 0 | N28: =M28 -> 0 | P28: =(P7+P8+P9+P10+P11)*$B$28 -> 0 | Q28: =P28 -> 0 | S28: =(S7+S8+S9+S10+S11)*$B$28 -> 0 | T28: =S28 -> 0 | V28: =(V7+V8+V9+V10+V11)*$B$28 -> 0 | W28: =V28 -> 0 | Y28: =(Y7+Y8+Y9+Y10+Y11)*$B$28 -> 0 | Z28: =Y28 -> 0 | AB28: =(AB7+AB8+AB9+AB10+AB11)*$B$28 -> 0 | AC28: =AB28 -> 0 | AE28: =(AE7+AE8+AE9+AE10+AE11)*$B$28 -> 0 | AF28: =AE28 -> 0 | AH28: =(AH7+AH8+AH9+AH10+AH11)*$B$28 -> 0 | AI28: =AH28 -> 0 | AK28: =(AK7+AK8+AK9+AK10+AK11)*$B$28 -> 0 | AL28: =AK28 -> 0 | AM28: =SUM(D28,G28,J28,M28,P28,S28,V28,Y28,AB28,AE28,AH28,AK28) -> 0 | AO28: =E28 -> 0 | AP28: =H28 -> 0 | AQ28: =K28 -> 0 | AR28: =N28 -> 0 | AS28: =Q28 -> 0 | AT28: =T28 -> 0 | AU28: =W28 -> 0 | AV28: =Z28 -> 0 | AW28: =AC28 -> 0 | AX28: =AF28 -> 0 | AY28: =AI28 -> 0 | AZ28: =AL28 -> 0
A29: ค่า GF | B29: 0.01 | D29: =(D7+D8+D9+D10+D11)*$B$29 -> 0 | E29: =D29 -> 0 | G29: =(G7+G8+G9+G10+G11)*$B$29 -> 0 | H29: =G29 -> 0 | J29: =(J7+J8+J9+J10+J11)*$B$29 -> 0 | K29: =J29 -> 0 | M29: =(M7+M8+M9+M10+M11)*$B$29 -> 0 | N29: =M29 -> 0 | P29: =(P7+P8+P9+P10+P11)*$B$29 -> 0 | Q29: =P29 -> 0 | S29: =(S7+S8+S9+S10+S11)*$B$29 -> 0 | T29: =S29 -> 0 | V29: =(V7+V8+V9+V10+V11)*$B$29 -> 0 | W29: =V29 -> 0 | Y29: =(Y7+Y8+Y9+Y10+Y11)*$B$29 -> 0 | Z29: =Y29 -> 0 | AB29: =(AB7+AB8+AB9+AB10+AB11)*$B$29 -> 0 | AC29: =AB29 -> 0 | AE29: =(AE7+AE8+AE9+AE10+AE11)*$B$29 -> 0 | AF29: =AE29 -> 0 | AH29: =(AH7+AH8+AH9+AH10+AH11)*$B$29 -> 0 | AI29: =AH29 -> 0 | AK29: =(AK7+AK8+AK9+AK10+AK11)*$B$29 -> 0 | AL29: =AK29 -> 0 | AM29: =SUM(D29,G29,J29,M29,P29,S29,V29,Y29,AB29,AE29,AH29,AK29) -> 0 | AO29: =E29 -> 0 | AP29: =H29 -> 0 | AQ29: =K29 -> 0 | AR29: =N29 -> 0 | AS29: =Q29 -> 0 | AT29: =T29 -> 0 | AU29: =W29 -> 0 | AV29: =Z29 -> 0 | AW29: =AC29 -> 0 | AX29: =AF29 -> 0 | AY29: =AI29 -> 0 | AZ29: =AL29 -> 0
A30: ค่าอบรมสัมมนา
A31: ค่าอบรม&สัมมนาพนักงาน | B31: เฉพาะทำและอนุมัติโดยสาขาตัวเอง | E31: =D31+'บริหารโดยส่วนกลาง (ไม่ต้องกรอก)'!E7 -> 0 | H31: =G31+'บริหารโดยส่วนกลาง (ไม่ต้องกรอก)'!H7 -> 0 | K31: =J31+'บริหารโดยส่วนกลาง (ไม่ต้องกรอก)'!K7 -> 0 | N31: =M31+'บริหารโดยส่วนกลาง (ไม่ต้องกรอก)'!N7 -> 0 | Q31: =P31+'บริหารโดยส่วนกลาง (ไม่ต้องกรอก)'!Q7 -> 0 | T31: =S31+'บริหารโดยส่วนกลาง (ไม่ต้องกรอก)'!T7 -> 0 | W31: =V31+'บริหารโดยส่วนกลาง (ไม่ต้องกรอก)'!W7 -> 0 | Z31: =Y31+'บริหารโดยส่วนกลาง (ไม่ต้องกรอก)'!Z7 -> 0 | AC31: =AB31+'บริหารโดยส่วนกลาง (ไม่ต้องกรอก)'!AC7 -> 0 | AF31: =AE31+'บริหารโดยส่วนกลาง (ไม่ต้องกรอก)'!AF7 -> 0 | AI31: =AH31+'บริหารโดยส่วนกลาง (ไม่ต้องกรอก)'!AI7 -> 0 | AL31: =AK31+'บริหารโดยส่วนกลาง (ไม่ต้องกรอก)'!AL7 -> 0 | AM31: =SUM(D31,G31,J31,M31,P31,S31,V31,Y31,AB31,AE31,AH31,AK31) -> 0 | AO31: =E31 -> 0 | AP31: =H31 -> 0 | AQ31: =K31 -> 0 | AR31: =N31 -> 0 | AS31: =Q31 -> 0 | AT31: =T31 -> 0 | AU31: =W31 -> 0 | AV31: =Z31 -> 0 | AW31: =AC31 -> 0 | AX31: =AF31 -> 0 | AY31: =AI31 -> 0 | AZ31: =AL31 -> 0
A32: ค่าอบรม&สัมมนาหมอ | E32: =D32+'บริหารโดยส่วนกลาง (ไม่ต้องกรอก)'!E8 -> 0 | H32: =G32+'บริหารโดยส่วนกลาง (ไม่ต้องกรอก)'!H8 -> 0 | K32: =J32+'บริหารโดยส่วนกลาง (ไม่ต้องกรอก)'!K8 -> 0 | N32: =M32+'บริหารโดยส่วนกลาง (ไม่ต้องกรอก)'!N8 -> 0 | Q32: =P32+'บริหารโดยส่วนกลาง (ไม่ต้องกรอก)'!Q8 -> 0 | T32: =S32+'บริหารโดยส่วนกลาง (ไม่ต้องกรอก)'!T8 -> 0 | W32: =V32+'บริหารโดยส่วนกลาง (ไม่ต้องกรอก)'!W8 -> 0 | Z32: =Y32+'บริหารโดยส่วนกลาง (ไม่ต้องกรอก)'!Z8 -> 0 | AC32: =AB32+'บริหารโดยส่วนกลาง (ไม่ต้องกรอก)'!AC8 -> 0 | AF32: =AE32+'บริหารโดยส่วนกลาง (ไม่ต้องกรอก)'!AF8 -> 0 | AI32: =AH32+'บริหารโดยส่วนกลาง (ไม่ต้องกรอก)'!AI8 -> 0 | AL32: =AK32+'บริหารโดยส่วนกลาง (ไม่ต้องกรอก)'!AL8 -> 0 | AM32: =SUM(D32,G32,J32,M32,P32,S32,V32,Y32,AB32,AE32,AH32,AK32) -> 0 | AO32: =E32 -> 0 | AP32: =H32 -> 0 | AQ32: =K32 -> 0 | AR32: =N32 -> 0 | AS32: =Q32 -> 0 | AT32: =T32 -> 0 | AU32: =W32 -> 0 | AV32: =Z32 -> 0 | AW32: =AC32 -> 0 | AX32: =AF32 -> 0 | AY32: =AI32 -> 0 | AZ32: =AL32 -> 0
A33: ค่าอบรมISO | E33: =D33+'บริหารโดยส่วนกลาง (ไม่ต้องกรอก)'!E9 -> 0 | H33: =G33+'บริหารโดยส่วนกลาง (ไม่ต้องกรอก)'!H9 -> 0 | K33: =J33+'บริหารโดยส่วนกลาง (ไม่ต้องกรอก)'!K9 -> 0 | N33: =M33+'บริหารโดยส่วนกลาง (ไม่ต้องกรอก)'!N9 -> 0 | Q33: =P33+'บริหารโดยส่วนกลาง (ไม่ต้องกรอก)'!Q9 -> 0 | T33: =S33+'บริหารโดยส่วนกลาง (ไม่ต้องกรอก)'!T9 -> 0 | W33: =V33+'บริหารโดยส่วนกลาง (ไม่ต้องกรอก)'!W9 -> 0 | Z33: =Y33+'บริหารโดยส่วนกลาง (ไม่ต้องกรอก)'!Z9 -> 0 | AC33: =AB33+'บริหารโดยส่วนกลาง (ไม่ต้องกรอก)'!AC9 -> 0 | AF33: =AE33+'บริหารโดยส่วนกลาง (ไม่ต้องกรอก)'!AF9 -> 0 | AI33: =AH33+'บริหารโดยส่วนกลาง (ไม่ต้องกรอก)'!AI9 -> 0 | AL33: =AK33+'บริหารโดยส่วนกลาง (ไม่ต้องกรอก)'!AL9 -> 0 | AM33: =SUM(D33,G33,J33,M33,P33,S33,V33,Y33,AB33,AE33,AH33,AK33) -> 0 | AO33: =E33 -> 0 | AP33: =H33 -> 0 | AQ33: =K33 -> 0 | AR33: =N33 -> 0 | AS33: =Q33 -> 0 | AT33: =T33 -> 0 | AU33: =W33 -> 0 | AV33: =Z33 -> 0 | AW33: =AC33 -> 0 | AX33: =AF33 -> 0 | AY33: =AI33 -> 0 | AZ33: =AL33 -> 0
A34: วัสดุสิ้นเปลือง
A35: ค่าเครื่องเขียนแบบพิมพ์ | E35: =D35 -> 0 | H35: =G35 -> 0 | K35: =J35 -> 0 | N35: =M35 -> 0 | Q35: =P35 -> 0 | T35: =S35 -> 0 | W35: =V35 -> 0 | Z35: =Y35 -> 0 | AC35: =AB35 -> 0 | AF35: =AE35 -> 0 | AI35: =AH35 -> 0 | AL35: =AK35 -> 0 | AM35: =SUM(D35,G35,J35,M35,P35,S35,V35,Y35,AB35,AE35,AH35,AK35) -> 0 | AO35: =E35 -> 0 | AP35: =H35 -> 0 | AQ35: =K35 -> 0 | AR35: =N35 -> 0 | AS35: =Q35 -> 0 | AT35: =T35 -> 0 | AU35: =W35 -> 0 | AV35: =Z35 -> 0 | AW35: =AC35 -> 0 | AX35: =AF35 -> 0 | AY35: =AI35 -> 0 | AZ35: =AL35 -> 0
A36: ค่าอุปกรณ์สำนักงาน-ของใช้สิ้นเปลือง | E36: =D36 -> 0 | H36: =G36 -> 0 | K36: =J36 -> 0 | N36: =M36 -> 0 | Q36: =P36 -> 0 | T36: =S36 -> 0 | W36: =V36 -> 0 | Z36: =Y36 -> 0 | AC36: =AB36 -> 0 | AF36: =AE36 -> 0 | AI36: =AH36 -> 0 | AL36: =AK36 -> 0 | AM36: =SUM(D36,G36,J36,M36,P36,S36,V36,Y36,AB36,AE36,AH36,AK36) -> 0 | AO36: =E36 -> 0 | AP36: =H36 -> 0 | AQ36: =K36 -> 0 | AR36: =N36 -> 0 | AS36: =Q36 -> 0 | AT36: =T36 -> 0 | AU36: =W36 -> 0 | AV36: =Z36 -> 0 | AW36: =AC36 -> 0 | AX36: =AF36 -> 0 | AY36: =AI36 -> 0 | AZ36: =AL36 -> 0
A37: ค่าเช่าเครื่องถ่ายเอกสาร | E37: =D37 -> 0 | H37: =G37 -> 0 | K37: =J37 -> 0 | N37: =M37 -> 0 | Q37: =P37 -> 0 | T37: =S37 -> 0 | W37: =V37 -> 0 | Z37: =Y37 -> 0 | AC37: =AB37 -> 0 | AF37: =AE37 -> 0 | AI37: =AH37 -> 0 | AL37: =AK37 -> 0 | AM37: =SUM(D37,G37,J37,M37,P37,S37,V37,Y37,AB37,AE37,AH37,AK37) -> 0 | AO37: =E37 -> 0 | AP37: =H37 -> 0 | AQ37: =K37 -> 0 | AR37: =N37 -> 0 | AS37: =Q37 -> 0 | AT37: =T37 -> 0 | AU37: =W37 -> 0 | AV37: =Z37 -> 0 | AW37: =AC37 -> 0 | AX37: =AF37 -> 0 | AY37: =AI37 -> 0 | AZ37: =AL37 -> 0
A38: รวมวัสดุสิ้นเปลือง
A39: ค่่าโฆษณาและส่งเสริมการขาย | AO39: =E39 -> 0 | AP39: =H39 -> 0 | AQ39: =K39 -> 0 | AR39: =N39 -> 0 | AS39: =Q39 -> 0 | AT39: =T39 -> 0 | AU39: =W39 -> 0 | AV39: =Z39 -> 0 | AW39: =AC39 -> 0 | AX39: =AF39 -> 0 | AY39: =AI39 -> 0 | AZ39: =AL39 -> 0
A40: ค่าโฆษณา | B40: เฉพาะทำและอนุมัติโดยสาขาตัวเอง | E40: =D40+'บริหารโดยส่วนกลาง (ไม่ต้องกรอก)'!E11 -> 0 | H40: =G40+'บริหารโดยส่วนกลาง (ไม่ต้องกรอก)'!H11 -> 0 | K40: =J40+'บริหารโดยส่วนกลาง (ไม่ต้องกรอก)'!K11 -> 0 | N40: =M40+'บริหารโดยส่วนกลาง (ไม่ต้องกรอก)'!N11 -> 0 | Q40: =P40+'บริหารโดยส่วนกลาง (ไม่ต้องกรอก)'!Q11 -> 0 | T40: =S40+'บริหารโดยส่วนกลาง (ไม่ต้องกรอก)'!T11 -> 0 | W40: =V40+'บริหารโดยส่วนกลาง (ไม่ต้องกรอก)'!W11 -> 0 | Z40: =Y40+'บริหารโดยส่วนกลาง (ไม่ต้องกรอก)'!Z11 -> 0 | AC40: =AB40+'บริหารโดยส่วนกลาง (ไม่ต้องกรอก)'!AC11 -> 0 | AF40: =AE40+'บริหารโดยส่วนกลาง (ไม่ต้องกรอก)'!AF11 -> 0 | AI40: =AH40+'บริหารโดยส่วนกลาง (ไม่ต้องกรอก)'!AI11 -> 0 | AL40: =AK40+'บริหารโดยส่วนกลาง (ไม่ต้องกรอก)'!AL11 -> 0 | AM40: =SUM(D40,G40,J40,M40,P40,S40,V40,Y40,AB40,AE40,AH40,AK40) -> 0 | AO40: =E40 -> 0 | AP40: =H40 -> 0 | AQ40: =K40 -> 0 | AR40: =N40 -> 0 | AS40: =Q40 -> 0 | AT40: =T40 -> 0 | AU40: =W40 -> 0 | AV40: =Z40 -> 0 | AW40: =AC40 -> 0 | AX40: =AF40 -> 0 | AY40: =AI40 -> 0 | AZ40: =AL40 -> 0
A41: ค่าโฆษณาหาคน | E41: =D41+'บริหารโดยส่วนกลาง (ไม่ต้องกรอก)'!E12 -> 0 | H41: =G41+'บริหารโดยส่วนกลาง (ไม่ต้องกรอก)'!H12 -> 0 | K41: =J41+'บริหารโดยส่วนกลาง (ไม่ต้องกรอก)'!K12 -> 0 | N41: =M41+'บริหารโดยส่วนกลาง (ไม่ต้องกรอก)'!N12 -> 0 | Q41: =P41+'บริหารโดยส่วนกลาง (ไม่ต้องกรอก)'!Q12 -> 0 | T41: =S41+'บริหารโดยส่วนกลาง (ไม่ต้องกรอก)'!T12 -> 0 | W41: =V41+'บริหารโดยส่วนกลาง (ไม่ต้องกรอก)'!W12 -> 0 | Z41: =Y41+'บริหารโดยส่วนกลาง (ไม่ต้องกรอก)'!Z12 -> 0 | AC41: =AB41+'บริหารโดยส่วนกลาง (ไม่ต้องกรอก)'!AC12 -> 0 | AF41: =AE41+'บริหารโดยส่วนกลาง (ไม่ต้องกรอก)'!AF12 -> 0 | AI41: =AH41+'บริหารโดยส่วนกลาง (ไม่ต้องกรอก)'!AI12 -> 0 | AL41: =AK41+'บริหารโดยส่วนกลาง (ไม่ต้องกรอก)'!AL12 -> 0 | AM41: =SUM(D41,G41,J41,M41,P41,S41,V41,Y41,AB41,AE41,AH41,AK41) -> 0 | AO41: =E41 -> 0 | AP41: =H41 -> 0 | AQ41: =K41 -> 0 | AR41: =N41 -> 0 | AS41: =Q41 -> 0 | AT41: =T41 -> 0 | AU41: =W41 -> 0 | AV41: =Z41 -> 0 | AW41: =AC41 -> 0 | AX41: =AF41 -> 0 | AY41: =AI41 -> 0 | AZ41: =AL41 -> 0
A42: ค่า CRM | E42: =D42+'บริหารโดยส่วนกลาง (ไม่ต้องกรอก)'!E13 -> 0 | H42: =G42+'บริหารโดยส่วนกลาง (ไม่ต้องกรอก)'!H13 -> 0 | K42: =J42+'บริหารโดยส่วนกลาง (ไม่ต้องกรอก)'!K13 -> 0 | N42: =M42+'บริหารโดยส่วนกลาง (ไม่ต้องกรอก)'!N13 -> 0 | Q42: =P42+'บริหารโดยส่วนกลาง (ไม่ต้องกรอก)'!Q13 -> 0 | T42: =S42+'บริหารโดยส่วนกลาง (ไม่ต้องกรอก)'!T13 -> 0 | W42: =V42+'บริหารโดยส่วนกลาง (ไม่ต้องกรอก)'!W13 -> 0 | Z42: =Y42+'บริหารโดยส่วนกลาง (ไม่ต้องกรอก)'!Z13 -> 0 | AC42: =AB42+'บริหารโดยส่วนกลาง (ไม่ต้องกรอก)'!AC13 -> 0 | AF42: =AE42+'บริหารโดยส่วนกลาง (ไม่ต้องกรอก)'!AF13 -> 0 | AI42: =AH42+'บริหารโดยส่วนกลาง (ไม่ต้องกรอก)'!AI13 -> 0 | AL42: =AK42+'บริหารโดยส่วนกลาง (ไม่ต้องกรอก)'!AL13 -> 0 | AM42: =SUM(D42,G42,J42,M42,P42,S42,V42,Y42,AB42,AE42,AH42,AK42) -> 0 | AO42: =E42 -> 0 | AP42: =H42 -> 0 | AQ42: =K42 -> 0 | AR42: =N42 -> 0 | AS42: =Q42 -> 0 | AT42: =T42 -> 0 | AU42: =W42 -> 0 | AV42: =Z42 -> 0 | AW42: =AC42 -> 0 | AX42: =AF42 -> 0 | AY42: =AI42 -> 0 | AZ42: =AL42 -> 0
A43: ค่าซ่อมแซมและบำรุงรักษา
A44: ค่าซ่อมแซมคอมพิวเตอร์ | B44: เฉพาะทำและอนุมัติโดยสาขาตัวเอง | E44: =D44+'บริหารโดยส่วนกลาง (ไม่ต้องกรอก)'!E15 -> 0 | H44: =G44+'บริหารโดยส่วนกลาง (ไม่ต้องกรอก)'!H15 -> 0 | K44: =J44+'บริหารโดยส่วนกลาง (ไม่ต้องกรอก)'!K15 -> 0 | N44: =M44+'บริหารโดยส่วนกลาง (ไม่ต้องกรอก)'!N15 -> 0 | Q44: =P44+'บริหารโดยส่วนกลาง (ไม่ต้องกรอก)'!Q15 -> 0 | T44: =S44+'บริหารโดยส่วนกลาง (ไม่ต้องกรอก)'!T15 -> 0 | W44: =V44+'บริหารโดยส่วนกลาง (ไม่ต้องกรอก)'!W15 -> 0 | Z44: =Y44+'บริหารโดยส่วนกลาง (ไม่ต้องกรอก)'!Z15 -> 0 | AC44: =AB44+'บริหารโดยส่วนกลาง (ไม่ต้องกรอก)'!AC15 -> 0 | AF44: =AE44+'บริหารโดยส่วนกลาง (ไม่ต้องกรอก)'!AF15 -> 0 | AI44: =AH44+'บริหารโดยส่วนกลาง (ไม่ต้องกรอก)'!AI15 -> 0 | AL44: =AK44+'บริหารโดยส่วนกลาง (ไม่ต้องกรอก)'!AL15 -> 0 | AM44: =SUM(D44,G44,J44,M44,P44,S44,V44,Y44,AB44,AE44,AH44,AK44) -> 0 | AO44: =E44 -> 0 | AP44: =H44 -> 0 | AQ44: =K44 -> 0 | AR44: =N44 -> 0 | AS44: =Q44 -> 0 | AT44: =T44 -> 0 | AU44: =W44 -> 0 | AV44: =Z44 -> 0 | AW44: =AC44 -> 0 | AX44: =AF44 -> 0 | AY44: =AI44 -> 0 | AZ44: =AL44 -> 0
A45: ค่าซ่อมแซมเครื่องใช้สำนักงาน | E45: =D45+'บริหารโดยส่วนกลาง (ไม่ต้องกรอก)'!E16 -> 0 | H45: =G45+'บริหารโดยส่วนกลาง (ไม่ต้องกรอก)'!H16 -> 0 | K45: =J45+'บริหารโดยส่วนกลาง (ไม่ต้องกรอก)'!K16 -> 0 | N45: =M45+'บริหารโดยส่วนกลาง (ไม่ต้องกรอก)'!N16 -> 0 | Q45: =P45+'บริหารโดยส่วนกลาง (ไม่ต้องกรอก)'!Q16 -> 0 | T45: =S45+'บริหารโดยส่วนกลาง (ไม่ต้องกรอก)'!T16 -> 0 | W45: =V45+'บริหารโดยส่วนกลาง (ไม่ต้องกรอก)'!W16 -> 0 | Z45: =Y45+'บริหารโดยส่วนกลาง (ไม่ต้องกรอก)'!Z16 -> 0 | AC45: =AB45+'บริหารโดยส่วนกลาง (ไม่ต้องกรอก)'!AC16 -> 0 | AF45: =AE45+'บริหารโดยส่วนกลาง (ไม่ต้องกรอก)'!AF16 -> 0 | AI45: =AH45+'บริหารโดยส่วนกลาง (ไม่ต้องกรอก)'!AI16 -> 0 | AL45: =AK45+'บริหารโดยส่วนกลาง (ไม่ต้องกรอก)'!AL16 -> 0 | AM45: =SUM(D45,G45,J45,M45,P45,S45,V45,Y45,AB45,AE45,AH45,AK45) -> 0 | AO45: =E45 -> 0 | AP45: =H45 -> 0 | AQ45: =K45 -> 0 | AR45: =N45 -> 0 | AS45: =Q45 -> 0 | AT45: =T45 -> 0 | AU45: =W45 -> 0 | AV45: =Z45 -> 0 | AW45: =AC45 -> 0 | AX45: =AF45 -> 0 | AY45: =AI45 -> 0 | AZ45: =AL45 -> 0
A46: ค่าซ่อมแซมเครื่องตกแต่งและติดตั้ง | E46: =D46+'บริหารโดยส่วนกลาง (ไม่ต้องกรอก)'!E17 -> 0 | H46: =G46+'บริหารโดยส่วนกลาง (ไม่ต้องกรอก)'!H17 -> 0 | K46: =J46+'บริหารโดยส่วนกลาง (ไม่ต้องกรอก)'!K17 -> 0 | N46: =M46+'บริหารโดยส่วนกลาง (ไม่ต้องกรอก)'!N17 -> 0 | Q46: =P46+'บริหารโดยส่วนกลาง (ไม่ต้องกรอก)'!Q17 -> 0 | T46: =S46+'บริหารโดยส่วนกลาง (ไม่ต้องกรอก)'!T17 -> 0 | W46: =V46+'บริหารโดยส่วนกลาง (ไม่ต้องกรอก)'!W17 -> 0 | Z46: =Y46+'บริหารโดยส่วนกลาง (ไม่ต้องกรอก)'!Z17 -> 0 | AC46: =AB46+'บริหารโดยส่วนกลาง (ไม่ต้องกรอก)'!AC17 -> 0 | AF46: =AE46+'บริหารโดยส่วนกลาง (ไม่ต้องกรอก)'!AF17 -> 0 | AI46: =AH46+'บริหารโดยส่วนกลาง (ไม่ต้องกรอก)'!AI17 -> 0 | AL46: =AK46+'บริหารโดยส่วนกลาง (ไม่ต้องกรอก)'!AL17 -> 0 | AM46: =SUM(D46,G46,J46,M46,P46,S46,V46,Y46,AB46,AE46,AH46,AK46) -> 0 | AO46: =E46 -> 0 | AP46: =H46 -> 0 | AQ46: =K46 -> 0 | AR46: =N46 -> 0 | AS46: =Q46 -> 0 | AT46: =T46 -> 0 | AU46: =W46 -> 0 | AV46: =Z46 -> 0 | AW46: =AC46 -> 0 | AX46: =AF46 -> 0 | AY46: =AI46 -> 0 | AZ46: =AL46 -> 0
A47: ค่าซ่อมแซมยานพาหนะ | E47: =D47+'บริหารโดยส่วนกลาง (ไม่ต้องกรอก)'!E18 -> 0 | H47: =G47+'บริหารโดยส่วนกลาง (ไม่ต้องกรอก)'!H18 -> 0 | K47: =J47+'บริหารโดยส่วนกลาง (ไม่ต้องกรอก)'!K18 -> 0 | N47: =M47+'บริหารโดยส่วนกลาง (ไม่ต้องกรอก)'!N18 -> 0 | Q47: =P47+'บริหารโดยส่วนกลาง (ไม่ต้องกรอก)'!Q18 -> 0 | T47: =S47+'บริหารโดยส่วนกลาง (ไม่ต้องกรอก)'!T18 -> 0 | W47: =V47+'บริหารโดยส่วนกลาง (ไม่ต้องกรอก)'!W18 -> 0 | Z47: =Y47+'บริหารโดยส่วนกลาง (ไม่ต้องกรอก)'!Z18 -> 0 | AC47: =AB47+'บริหารโดยส่วนกลาง (ไม่ต้องกรอก)'!AC18 -> 0 | AF47: =AE47+'บริหารโดยส่วนกลาง (ไม่ต้องกรอก)'!AF18 -> 0 | AI47: =AH47+'บริหารโดยส่วนกลาง (ไม่ต้องกรอก)'!AI18 -> 0 | AL47: =AK47+'บริหารโดยส่วนกลาง (ไม่ต้องกรอก)'!AL18 -> 0 | AM47: =SUM(D47,G47,J47,M47,P47,S47,V47,Y47,AB47,AE47,AH47,AK47) -> 0 | AO47: =E47 -> 0 | AP47: =H47 -> 0 | AQ47: =K47 -> 0 | AR47: =N47 -> 0 | AS47: =Q47 -> 0 | AT47: =T47 -> 0 | AU47: =W47 -> 0 | AV47: =Z47 -> 0 | AW47: =AC47 -> 0 | AX47: =AF47 -> 0 | AY47: =AI47 -> 0 | AZ47: =AL47 -> 0
A48: ค่าซ่อมแซมเครื่องมือแพทย์ | E48: =D48+'บริหารโดยส่วนกลาง (ไม่ต้องกรอก)'!E19 -> 0 | H48: =G48+'บริหารโดยส่วนกลาง (ไม่ต้องกรอก)'!H19 -> 0 | K48: =J48+'บริหารโดยส่วนกลาง (ไม่ต้องกรอก)'!K19 -> 0 | N48: =M48+'บริหารโดยส่วนกลาง (ไม่ต้องกรอก)'!N19 -> 0 | Q48: =P48+'บริหารโดยส่วนกลาง (ไม่ต้องกรอก)'!Q19 -> 0 | T48: =S48+'บริหารโดยส่วนกลาง (ไม่ต้องกรอก)'!T19 -> 0 | W48: =V48+'บริหารโดยส่วนกลาง (ไม่ต้องกรอก)'!W19 -> 0 | Z48: =Y48+'บริหารโดยส่วนกลาง (ไม่ต้องกรอก)'!Z19 -> 0 | AC48: =AB48+'บริหารโดยส่วนกลาง (ไม่ต้องกรอก)'!AC19 -> 0 | AF48: =AE48+'บริหารโดยส่วนกลาง (ไม่ต้องกรอก)'!AF19 -> 0 | AI48: =AH48+'บริหารโดยส่วนกลาง (ไม่ต้องกรอก)'!AI19 -> 0 | AL48: =AK48+'บริหารโดยส่วนกลาง (ไม่ต้องกรอก)'!AL19 -> 0 | AM48: =SUM(D48,G48,J48,M48,P48,S48,V48,Y48,AB48,AE48,AH48,AK48) -> 0 | AO48: =E48 -> 0 | AP48: =H48 -> 0 | AQ48: =K48 -> 0 | AR48: =N48 -> 0 | AS48: =Q48 -> 0 | AT48: =T48 -> 0 | AU48: =W48 -> 0 | AV48: =Z48 -> 0 | AW48: =AC48 -> 0 | AX48: =AF48 -> 0 | AY48: =AI48 -> 0 | AZ48: =AL48 -> 0
A49: ค่าบำรุงรักษาโปรแกรม | E49: =D49+'บริหารโดยส่วนกลาง (ไม่ต้องกรอก)'!E20 -> 0 | H49: =G49+'บริหารโดยส่วนกลาง (ไม่ต้องกรอก)'!H20 -> 0 | K49: =J49+'บริหารโดยส่วนกลาง (ไม่ต้องกรอก)'!K20 -> 0 | N49: =M49+'บริหารโดยส่วนกลาง (ไม่ต้องกรอก)'!N20 -> 0 | Q49: =P49+'บริหารโดยส่วนกลาง (ไม่ต้องกรอก)'!Q20 -> 0 | T49: =S49+'บริหารโดยส่วนกลาง (ไม่ต้องกรอก)'!T20 -> 0 | W49: =V49+'บริหารโดยส่วนกลาง (ไม่ต้องกรอก)'!W20 -> 0 | Z49: =Y49+'บริหารโดยส่วนกลาง (ไม่ต้องกรอก)'!Z20 -> 0 | AC49: =AB49+'บริหารโดยส่วนกลาง (ไม่ต้องกรอก)'!AC20 -> 0 | AF49: =AE49+'บริหารโดยส่วนกลาง (ไม่ต้องกรอก)'!AF20 -> 0 | AI49: =AH49+'บริหารโดยส่วนกลาง (ไม่ต้องกรอก)'!AI20 -> 0 | AL49: =AK49+'บริหารโดยส่วนกลาง (ไม่ต้องกรอก)'!AL20 -> 0 | AM49: =SUM(D49,G49,J49,M49,P49,S49,V49,Y49,AB49,AE49,AH49,AK49) -> 0 | AO49: =E49 -> 0 | AP49: =H49 -> 0 | AQ49: =K49 -> 0 | AR49: =N49 -> 0 | AS49: =Q49 -> 0 | AT49: =T49 -> 0 | AU49: =W49 -> 0 | AV49: =Z49 -> 0 | AW49: =AC49 -> 0 | AX49: =AF49 -> 0 | AY49: =AI49 -> 0 | AZ49: =AL49 -> 0
A50: ค่าบำรุงรักษาเครื่องใช้สำนักงาน | E50: =D50+'บริหารโดยส่วนกลาง (ไม่ต้องกรอก)'!E21 -> 0 | H50: =G50+'บริหารโดยส่วนกลาง (ไม่ต้องกรอก)'!H21 -> 0 | K50: =J50+'บริหารโดยส่วนกลาง (ไม่ต้องกรอก)'!K21 -> 0 | N50: =M50+'บริหารโดยส่วนกลาง (ไม่ต้องกรอก)'!N21 -> 0 | Q50: =P50+'บริหารโดยส่วนกลาง (ไม่ต้องกรอก)'!Q21 -> 0 | T50: =S50+'บริหารโดยส่วนกลาง (ไม่ต้องกรอก)'!T21 -> 0 | W50: =V50+'บริหารโดยส่วนกลาง (ไม่ต้องกรอก)'!W21 -> 0 | Z50: =Y50+'บริหารโดยส่วนกลาง (ไม่ต้องกรอก)'!Z21 -> 0 | AC50: =AB50+'บริหารโดยส่วนกลาง (ไม่ต้องกรอก)'!AC21 -> 0 | AF50: =AE50+'บริหารโดยส่วนกลาง (ไม่ต้องกรอก)'!AF21 -> 0 | AI50: =AH50+'บริหารโดยส่วนกลาง (ไม่ต้องกรอก)'!AI21 -> 0 | AL50: =AK50+'บริหารโดยส่วนกลาง (ไม่ต้องกรอก)'!AL21 -> 0 | AM50: =SUM(D50,G50,J50,M50,P50,S50,V50,Y50,AB50,AE50,AH50,AK50) -> 0 | AO50: =E50 -> 0 | AP50: =H50 -> 0 | AQ50: =K50 -> 0 | AR50: =N50 -> 0 | AS50: =Q50 -> 0 | AT50: =T50 -> 0 | AU50: =W50 -> 0 | AV50: =Z50 -> 0 | AW50: =AC50 -> 0 | AX50: =AF50 -> 0 | AY50: =AI50 -> 0 | AZ50: =AL50 -> 0
A51: ค่าเข่า
A52: ค่าเช่าอาคาร | E52: =D52 -> 0 | H52: =G52 -> 0 | K52: =J52 -> 0 | N52: =M52 -> 0 | Q52: =P52 -> 0 | T52: =S52 -> 0 | W52: =V52 -> 0 | Z52: =Y52 -> 0 | AC52: =AB52 -> 0 | AF52: =AE52 -> 0 | AI52: =AH52 -> 0 | AL52: =AK52 -> 0 | AM52: =SUM(D52,G52,J52,M52,P52,S52,V52,Y52,AB52,AE52,AH52,AK52) -> 0 | AO52: =E52 -> 0 | AP52: =H52 -> 0 | AQ52: =K52 -> 0 | AR52: =N52 -> 0 | AS52: =Q52 -> 0 | AT52: =T52 -> 0 | AU52: =W52 -> 0 | AV52: =Z52 -> 0 | AW52: =AC52 -> 0 | AX52: =AF52 -> 0 | AY52: =AI52 -> 0 | AZ52: =AL52 -> 0
A53: ค่าเช่าที่ดิน | E53: =D53 -> 0 | H53: =G53 -> 0 | K53: =J53 -> 0 | N53: =M53 -> 0 | Q53: =P53 -> 0 | T53: =S53 -> 0 | W53: =V53 -> 0 | Z53: =Y53 -> 0 | AC53: =AB53 -> 0 | AF53: =AE53 -> 0 | AI53: =AH53 -> 0 | AL53: =AK53 -> 0 | AM53: =SUM(D53,G53,J53,M53,P53,S53,V53,Y53,AB53,AE53,AH53,AK53) -> 0 | AO53: =E53 -> 0 | AP53: =H53 -> 0 | AQ53: =K53 -> 0 | AR53: =N53 -> 0 | AS53: =Q53 -> 0 | AT53: =T53 -> 0 | AU53: =W53 -> 0 | AV53: =Z53 -> 0 | AW53: =AC53 -> 0 | AX53: =AF53 -> 0 | AY53: =AI53 -> 0 | AZ53: =AL53 -> 0
A54: ค่าบริการส่วนกลาง | E54: =D54 -> 0 | H54: =G54 -> 0 | K54: =J54 -> 0 | N54: =M54 -> 0 | Q54: =P54 -> 0 | T54: =S54 -> 0 | W54: =V54 -> 0 | Z54: =Y54 -> 0 | AC54: =AB54 -> 0 | AF54: =AE54 -> 0 | AI54: =AH54 -> 0 | AL54: =AK54 -> 0 | AM54: =SUM(D54,G54,J54,M54,P54,S54,V54,Y54,AB54,AE54,AH54,AK54) -> 0 | AO54: =E54 -> 0 | AP54: =H54 -> 0 | AQ54: =K54 -> 0 | AR54: =N54 -> 0 | AS54: =Q54 -> 0 | AT54: =T54 -> 0 | AU54: =W54 -> 0 | AV54: =Z54 -> 0 | AW54: =AC54 -> 0 | AX54: =AF54 -> 0 | AY54: =AI54 -> 0 | AZ54: =AL54 -> 0
A55: ค่าใช้จ่ายในการเดินทาง
A56: ค่าพาหนะ | E56: =D56 -> 0 | H56: =G56 -> 0 | K56: =J56 -> 0 | N56: =M56 -> 0 | Q56: =P56 -> 0 | T56: =S56 -> 0 | W56: =V56 -> 0 | Z56: =Y56 -> 0 | AC56: =AB56 -> 0 | AF56: =AE56 -> 0 | AI56: =AH56 -> 0 | AL56: =AK56 -> 0 | AM56: =SUM(D56,G56,J56,M56,P56,S56,V56,Y56,AB56,AE56,AH56,AK56) -> 0 | AO56: =E56 -> 0 | AP56: =H56 -> 0 | AQ56: =K56 -> 0 | AR56: =N56 -> 0 | AS56: =Q56 -> 0 | AT56: =T56 -> 0 | AU56: =W56 -> 0 | AV56: =Z56 -> 0 | AW56: =AC56 -> 0 | AX56: =AF56 -> 0 | AY56: =AI56 -> 0 | AZ56: =AL56 -> 0
A57: ค่าน้ำมัน | E57: =D57 -> 0 | H57: =G57 -> 0 | K57: =J57 -> 0 | N57: =M57 -> 0 | Q57: =P57 -> 0 | T57: =S57 -> 0 | W57: =V57 -> 0 | Z57: =Y57 -> 0 | AC57: =AB57 -> 0 | AF57: =AE57 -> 0 | AI57: =AH57 -> 0 | AL57: =AK57 -> 0 | AM57: =SUM(D57,G57,J57,M57,P57,S57,V57,Y57,AB57,AE57,AH57,AK57) -> 0 | AO57: =E57 -> 0 | AP57: =H57 -> 0 | AQ57: =K57 -> 0 | AR57: =N57 -> 0 | AS57: =Q57 -> 0 | AT57: =T57 -> 0 | AU57: =W57 -> 0 | AV57: =Z57 -> 0 | AW57: =AC57 -> 0 | AX57: =AF57 -> 0 | AY57: =AI57 -> 0 | AZ57: =AL57 -> 0
A58: ค่าใช้จ่ายเดินทางต่างประเทศ | E58: =D58 -> 0 | H58: =G58 -> 0 | K58: =J58 -> 0 | N58: =M58 -> 0 | Q58: =P58 -> 0 | T58: =S58 -> 0 | W58: =V58 -> 0 | Z58: =Y58 -> 0 | AC58: =AB58 -> 0 | AF58: =AE58 -> 0 | AI58: =AH58 -> 0 | AL58: =AK58 -> 0 | AM58: =SUM(D58,G58,J58,M58,P58,S58,V58,Y58,AB58,AE58,AH58,AK58) -> 0 | AO58: =E58 -> 0 | AP58: =H58 -> 0 | AQ58: =K58 -> 0 | AR58: =N58 -> 0 | AS58: =Q58 -> 0 | AT58: =T58 -> 0 | AU58: =W58 -> 0 | AV58: =Z58 -> 0 | AW58: =AC58 -> 0 | AX58: =AF58 -> 0 | AY58: =AI58 -> 0 | AZ58: =AL58 -> 0
A59: ค่าใช้จ่ายอื่น
A60: ค่ารับรอง | E60: =D60 -> 0 | H60: =G60 -> 0 | K60: =J60 -> 0 | N60: =M60 -> 0 | Q60: =P60 -> 0 | T60: =S60 -> 0 | W60: =V60 -> 0 | Z60: =Y60 -> 0 | AC60: =AB60 -> 0 | AF60: =AE60 -> 0 | AI60: =AH60 -> 0 | AL60: =AK60 -> 0 | AM60: =SUM(D60,G60,J60,M60,P60,S60,V60,Y60,AB60,AE60,AH60,AK60) -> 0 | AO60: =E60 -> 0 | AP60: =H60 -> 0 | AQ60: =K60 -> 0 | AR60: =N60 -> 0 | AS60: =Q60 -> 0 | AT60: =T60 -> 0 | AU60: =W60 -> 0 | AV60: =Z60 -> 0 | AW60: =AC60 -> 0 | AX60: =AF60 -> 0 | AY60: =AI60 -> 0 | AZ60: =AL60 -> 0
A61: ค่าสมาชิก | E61: =D61 -> 0 | H61: =G61 -> 0 | K61: =J61 -> 0 | N61: =M61 -> 0 | Q61: =P61 -> 0 | T61: =S61 -> 0 | W61: =V61 -> 0 | Z61: =Y61 -> 0 | AC61: =AB61 -> 0 | AF61: =AE61 -> 0 | AI61: =AH61 -> 0 | AL61: =AK61 -> 0 | AM61: =SUM(D61,G61,J61,M61,P61,S61,V61,Y61,AB61,AE61,AH61,AK61) -> 0 | AO61: =E61 -> 0 | AP61: =H61 -> 0 | AQ61: =K61 -> 0 | AR61: =N61 -> 0 | AS61: =Q61 -> 0 | AT61: =T61 -> 0 | AU61: =W61 -> 0 | AV61: =Z61 -> 0 | AW61: =AC61 -> 0 | AX61: =AF61 -> 0 | AY61: =AI61 -> 0 | AZ61: =AL61 -> 0
A62: ค่าทำความสะอาด | E62: =D62 -> 0 | H62: =G62 -> 0 | K62: =J62 -> 0 | N62: =M62 -> 0 | Q62: =P62 -> 0 | T62: =S62 -> 0 | W62: =V62 -> 0 | Z62: =Y62 -> 0 | AC62: =AB62 -> 0 | AF62: =AE62 -> 0 | AI62: =AH62 -> 0 | AL62: =AK62 -> 0 | AM62: =SUM(D62,G62,J62,M62,P62,S62,V62,Y62,AB62,AE62,AH62,AK62) -> 0 | AO62: =E62 -> 0 | AP62: =H62 -> 0 | AQ62: =K62 -> 0 | AR62: =N62 -> 0 | AS62: =Q62 -> 0 | AT62: =T62 -> 0 | AU62: =W62 -> 0 | AV62: =Z62 -> 0 | AW62: =AC62 -> 0 | AX62: =AF62 -> 0 | AY62: =AI62 -> 0 | AZ62: =AL62 -> 0
A63: ค่าใช้จ่ายเบ็ดเตล็ด | E63: =D63 -> 0 | H63: =G63 -> 0 | K63: =J63 -> 0 | N63: =M63 -> 0 | Q63: =P63 -> 0 | T63: =S63 -> 0 | W63: =V63 -> 0 | Z63: =Y63 -> 0 | AC63: =AB63 -> 0 | AF63: =AE63 -> 0 | AI63: =AH63 -> 0 | AL63: =AK63 -> 0 | AM63: =SUM(D63,G63,J63,M63,P63,S63,V63,Y63,AB63,AE63,AH63,AK63) -> 0 | AO63: =E63 -> 0 | AP63: =H63 -> 0 | AQ63: =K63 -> 0 | AR63: =N63 -> 0 | AS63: =Q63 -> 0 | AT63: =T63 -> 0 | AU63: =W63 -> 0 | AV63: =Z63 -> 0 | AW63: =AC63 -> 0 | AX63: =AF63 -> 0 | AY63: =AI63 -> 0 | AZ63: =AL63 -> 0
A64: ต้นทุนดอกเบี้ยผลประโยชน์พนักงาน | E64: =D64 -> 0 | H64: =G64 -> 0 | K64: =J64 -> 0 | N64: =M64 -> 0 | Q64: =P64 -> 0 | T64: =S64 -> 0 | W64: =V64 -> 0 | Z64: =Y64 -> 0 | AC64: =AB64 -> 0 | AF64: =AE64 -> 0 | AI64: =AH64 -> 0 | AL64: =AK64 -> 0 | AM64: =SUM(D64,G64,J64,M64,P64,S64,V64,Y64,AB64,AE64,AH64,AK64) -> 0 | AO64: =E64 -> 0 | AP64: =H64 -> 0 | AQ64: =K64 -> 0 | AR64: =N64 -> 0 | AS64: =Q64 -> 0 | AT64: =T64 -> 0 | AU64: =W64 -> 0 | AV64: =Z64 -> 0 | AW64: =AC64 -> 0 | AX64: =AF64 -> 0 | AY64: =AI64 -> 0 | AZ64: =AL64 -> 0
A65: ต้นทุนดอกเบี้ยค่ารื้อถอนอาคาร | E65: =D65 -> 0 | H65: =G65 -> 0 | K65: =J65 -> 0 | N65: =M65 -> 0 | Q65: =P65 -> 0 | T65: =S65 -> 0 | W65: =V65 -> 0 | Z65: =Y65 -> 0 | AC65: =AB65 -> 0 | AF65: =AE65 -> 0 | AI65: =AH65 -> 0 | AL65: =AK65 -> 0 | AM65: =SUM(D65,G65,J65,M65,P65,S65,V65,Y65,AB65,AE65,AH65,AK65) -> 0 | AO65: =E65 -> 0 | AP65: =H65 -> 0 | AQ65: =K65 -> 0 | AR65: =N65 -> 0 | AS65: =Q65 -> 0 | AT65: =T65 -> 0 | AU65: =W65 -> 0 | AV65: =Z65 -> 0 | AW65: =AC65 -> 0 | AX65: =AF65 -> 0 | AY65: =AI65 -> 0 | AZ65: =AL65 -> 0
A66: ผลต่างจากการตรวจนับ | E66: =D66 -> 0 | H66: =G66 -> 0 | K66: =J66 -> 0 | N66: =M66 -> 0 | Q66: =P66 -> 0 | T66: =S66 -> 0 | W66: =V66 -> 0 | Z66: =Y66 -> 0 | AC66: =AB66 -> 0 | AF66: =AE66 -> 0 | AI66: =AH66 -> 0 | AL66: =AK66 -> 0 | AM66: =SUM(D66,G66,J66,M66,P66,S66,V66,Y66,AB66,AE66,AH66,AK66) -> 0 | AO66: =E66 -> 0 | AP66: =H66 -> 0 | AQ66: =K66 -> 0 | AR66: =N66 -> 0 | AS66: =Q66 -> 0 | AT66: =T66 -> 0 | AU66: =W66 -> 0 | AV66: =Z66 -> 0 | AW66: =AC66 -> 0 | AX66: =AF66 -> 0 | AY66: =AI66 -> 0 | AZ66: =AL66 -> 0
A67: ค่าสินค้าเสื่อมสภาพ | E67: =D67 -> 0 | H67: =G67 -> 0 | K67: =J67 -> 0 | N67: =M67 -> 0 | Q67: =P67 -> 0 | T67: =S67 -> 0 | W67: =V67 -> 0 | Z67: =Y67 -> 0 | AC67: =AB67 -> 0 | AF67: =AE67 -> 0 | AI67: =AH67 -> 0 | AL67: =AK67 -> 0 | AM67: =SUM(D67,G67,J67,M67,P67,S67,V67,Y67,AB67,AE67,AH67,AK67) -> 0 | AO67: =E67 -> 0 | AP67: =H67 -> 0 | AQ67: =K67 -> 0 | AR67: =N67 -> 0 | AS67: =Q67 -> 0 | AT67: =T67 -> 0 | AU67: =W67 -> 0 | AV67: =Z67 -> 0 | AW67: =AC67 -> 0 | AX67: =AF67 -> 0 | AY67: =AI67 -> 0 | AZ67: =AL67 -> 0
A68: ค่ารักษาความปลอดภัย | E68: =D68 -> 0 | H68: =G68 -> 0 | K68: =J68 -> 0 | N68: =M68 -> 0 | Q68: =P68 -> 0 | T68: =S68 -> 0 | W68: =V68 -> 0 | Z68: =Y68 -> 0 | AC68: =AB68 -> 0 | AF68: =AE68 -> 0 | AI68: =AH68 -> 0 | AL68: =AK68 -> 0 | AM68: =SUM(D68,G68,J68,M68,P68,S68,V68,Y68,AB68,AE68,AH68,AK68) -> 0 | AO68: =E68 -> 0 | AP68: =H68 -> 0 | AQ68: =K68 -> 0 | AR68: =N68 -> 0 | AS68: =Q68 -> 0 | AT68: =T68 -> 0 | AU68: =W68 -> 0 | AV68: =Z68 -> 0 | AW68: =AC68 -> 0 | AX68: =AF68 -> 0 | AY68: =AI68 -> 0 | AZ68: =AL68 -> 0
A69: ค่าเสื่อมราคา
A70: ค่าเสื่อมราคา - ป้ายสำนักงาน | B70: 0.2 | E70: =((D70*$B70)/12)+'บริหารโดยส่วนกลาง (ไม่ต้องกรอก)'!E25 -> 0 | H70: =((G70*$B70)/12)+'บริหารโดยส่วนกลาง (ไม่ต้องกรอก)'!H25+E70 -> 0 | K70: =((J70*$B70)/12)+'บริหารโดยส่วนกลาง (ไม่ต้องกรอก)'!K25+H70 -> 0 | N70: =((M70*$B70)/12)+'บริหารโดยส่วนกลาง (ไม่ต้องกรอก)'!N25+K70 -> 0 | Q70: =((P70*$B70)/12)+'บริหารโดยส่วนกลาง (ไม่ต้องกรอก)'!Q25+N70 -> 0 | T70: =((S70*$B70)/12)+'บริหารโดยส่วนกลาง (ไม่ต้องกรอก)'!T25+Q70 -> 0 | W70: =((V70*$B70)/12)+'บริหารโดยส่วนกลาง (ไม่ต้องกรอก)'!W25+T70 -> 0 | Z70: =((Y70*$B70)/12)+'บริหารโดยส่วนกลาง (ไม่ต้องกรอก)'!Z25+W70 -> 0 | AC70: =((AB70*$B70)/12)+'บริหารโดยส่วนกลาง (ไม่ต้องกรอก)'!AC25+Z70 -> 0 | AF70: =((AE70*$B70)/12)+'บริหารโดยส่วนกลาง (ไม่ต้องกรอก)'!AF25+AC70 -> 0 | AI70: =((AH70*$B70)/12)+'บริหารโดยส่วนกลาง (ไม่ต้องกรอก)'!AI25+AF70 -> 0 | AL70: =((AK70*$B70)/12)+'บริหารโดยส่วนกลาง (ไม่ต้องกรอก)'!AL25+AI70 -> 0 | AM70: =SUM(D70,G70,J70,M70,P70,S70,V70,Y70,AB70,AE70,AH70,AK70) -> 0 | AO70: =E70 -> 0 | AP70: =H70 -> 0 | AQ70: =K70 -> 0 | AR70: =N70 -> 0 | AS70: =Q70 -> 0 | AT70: =T70 -> 0 | AU70: =W70 -> 0 | AV70: =Z70 -> 0 | AW70: =AC70 -> 0 | AX70: =AF70 -> 0 | AY70: =AI70 -> 0 | AZ70: =AL70 -> 0
A71: ค่าเสื่อมราคา - คอมพิวเตอร์ | B71: 0.33333 | D71: =คอมพิวเตอร์!E41 -> 0 | E71: =((D71*$B71)/12)+'บริหารโดยส่วนกลาง (ไม่ต้องกรอก)'!E26 -> 0 | G71: =คอมพิวเตอร์!F41 -> 0 | H71: =((G71*$B71)/12)+'บริหารโดยส่วนกลาง (ไม่ต้องกรอก)'!H26+E71 -> 0 | J71: =คอมพิวเตอร์!G41 -> 0 | K71: =((J71*$B71)/12)+'บริหารโดยส่วนกลาง (ไม่ต้องกรอก)'!K26+H71 -> 0 | M71: =คอมพิวเตอร์!H41 -> 0 | N71: =((M71*$B71)/12)+'บริหารโดยส่วนกลาง (ไม่ต้องกรอก)'!N26+K71 -> 0 | P71: =คอมพิวเตอร์!I41 -> 0 | Q71: =((P71*$B71)/12)+'บริหารโดยส่วนกลาง (ไม่ต้องกรอก)'!Q26+N71 -> 0 | S71: =คอมพิวเตอร์!J41 -> 0 | T71: =((S71*$B71)/12)+'บริหารโดยส่วนกลาง (ไม่ต้องกรอก)'!T26+Q71 -> 0 | V71: =คอมพิวเตอร์!K41 -> 0 | W71: =((V71*$B71)/12)+'บริหารโดยส่วนกลาง (ไม่ต้องกรอก)'!W26+T71 -> 0 | Y71: =คอมพิวเตอร์!L41 -> 0 | Z71: =((Y71*$B71)/12)+'บริหารโดยส่วนกลาง (ไม่ต้องกรอก)'!Z26+W71 -> 0 | AB71: =คอมพิวเตอร์!M41 -> 0 | AC71: =((AB71*$B71)/12)+'บริหารโดยส่วนกลาง (ไม่ต้องกรอก)'!AC26+Z71 -> 0 | AE71: =คอมพิวเตอร์!N41 -> 0 | AF71: =((AE71*$B71)/12)+'บริหารโดยส่วนกลาง (ไม่ต้องกรอก)'!AF26+AC71 -> 0 | AH71: =คอมพิวเตอร์!O41 -> 0 | AI71: =((AH71*$B71)/12)+'บริหารโดยส่วนกลาง (ไม่ต้องกรอก)'!AI26+AF71 -> 0 | AK71: =คอมพิวเตอร์!P41 -> 0 | AL71: =((AK71*$B71)/12)+'บริหารโดยส่วนกลาง (ไม่ต้องกรอก)'!AL26+AI71 -> 0 | AM71: =SUM(D71,G71,J71,M71,P71,S71,V71,Y71,AB71,AE71,AH71,AK71) -> 0 | AO71: =E71 -> 0 | AP71: =H71 -> 0 | AQ71: =K71 -> 0 | AR71: =N71 -> 0 | AS71: =Q71 -> 0 | AT71: =T71 -> 0 | AU71: =W71 -> 0 | AV71: =Z71 -> 0 | AW71: =AC71 -> 0 | AX71: =AF71 -> 0 | AY71: =AI71 -> 0 | AZ71: =AL71 -> 0
A72: ค่าเสื่อมราคา - ระบบ software | B72: 0.33 | E72: =((D72*$B72)/12)+'บริหารโดยส่วนกลาง (ไม่ต้องกรอก)'!E27 -> 0 | H72: =((G72*$B72)/12)+'บริหารโดยส่วนกลาง (ไม่ต้องกรอก)'!H27+E72 -> 0 | K72: =((J72*$B72)/12)+'บริหารโดยส่วนกลาง (ไม่ต้องกรอก)'!K27+H72 -> 0 | N72: =((M72*$B72)/12)+'บริหารโดยส่วนกลาง (ไม่ต้องกรอก)'!N27+K72 -> 0 | Q72: =((P72*$B72)/12)+'บริหารโดยส่วนกลาง (ไม่ต้องกรอก)'!Q27+N72 -> 0 | T72: =((S72*$B72)/12)+'บริหารโดยส่วนกลาง (ไม่ต้องกรอก)'!T27+Q72 -> 0 | W72: =((V72*$B72)/12)+'บริหารโดยส่วนกลาง (ไม่ต้องกรอก)'!W27+T72 -> 0 | Z72: =((Y72*$B72)/12)+'บริหารโดยส่วนกลาง (ไม่ต้องกรอก)'!Z27+W72 -> 0 | AC72: =((AB72*$B72)/12)+'บริหารโดยส่วนกลาง (ไม่ต้องกรอก)'!AC27+Z72 -> 0 | AF72: =((AE72*$B72)/12)+'บริหารโดยส่วนกลาง (ไม่ต้องกรอก)'!AF27+AC72 -> 0 | AI72: =((AH72*$B72)/12)+'บริหารโดยส่วนกลาง (ไม่ต้องกรอก)'!AI27+AF72 -> 0 | AL72: =((AK72*$B72)/12)+'บริหารโดยส่วนกลาง (ไม่ต้องกรอก)'!AL27+AI72 -> 0 | AM72: =SUM(D72,G72,J72,M72,P72,S72,V72,Y72,AB72,AE72,AH72,AK72) -> 0 | AO72: =E72 -> 0 | AP72: =H72 -> 0 | AQ72: =K72 -> 0 | AR72: =N72 -> 0 | AS72: =Q72 -> 0 | AT72: =T72 -> 0 | AU72: =W72 -> 0 | AV72: =Z72 -> 0 | AW72: =AC72 -> 0 | AX72: =AF72 -> 0 | AY72: =AI72 -> 0 | AZ72: =AL72 -> 0
A73: ค่าเสื่อมราคา - อาคารบนที่ดินเช่า | B73: 0.2 | E73: =((D73*$B73)/12)+'บริหารโดยส่วนกลาง (ไม่ต้องกรอก)'!E28 -> 0 | H73: =((G73*$B73)/12)+'บริหารโดยส่วนกลาง (ไม่ต้องกรอก)'!H28+E73 -> 0 | K73: =((J73*$B73)/12)+'บริหารโดยส่วนกลาง (ไม่ต้องกรอก)'!K28+H73 -> 0 | N73: =((M73*$B73)/12)+'บริหารโดยส่วนกลาง (ไม่ต้องกรอก)'!N28+K73 -> 0 | Q73: =((P73*$B73)/12)+'บริหารโดยส่วนกลาง (ไม่ต้องกรอก)'!Q28+N73 -> 0 | T73: =((S73*$B73)/12)+'บริหารโดยส่วนกลาง (ไม่ต้องกรอก)'!T28+Q73 -> 0 | W73: =((V73*$B73)/12)+'บริหารโดยส่วนกลาง (ไม่ต้องกรอก)'!W28+T73 -> 0 | Z73: =((Y73*$B73)/12)+'บริหารโดยส่วนกลาง (ไม่ต้องกรอก)'!Z28+W73 -> 0 | AC73: =((AB73*$B73)/12)+'บริหารโดยส่วนกลาง (ไม่ต้องกรอก)'!AC28+Z73 -> 0 | AF73: =((AE73*$B73)/12)+'บริหารโดยส่วนกลาง (ไม่ต้องกรอก)'!AF28+AC73 -> 0 | AI73: =((AH73*$B73)/12)+'บริหารโดยส่วนกลาง (ไม่ต้องกรอก)'!AI28+AF73 -> 0 | AL73: =((AK73*$B73)/12)+'บริหารโดยส่วนกลาง (ไม่ต้องกรอก)'!AL28+AI73 -> 0 | AM73: =SUM(D73,G73,J73,M73,P73,S73,V73,Y73,AB73,AE73,AH73,AK73) -> 0 | AO73: =E73 -> 0 | AP73: =H73 -> 0 | AQ73: =K73 -> 0 | AR73: =N73 -> 0 | AS73: =Q73 -> 0 | AT73: =T73 -> 0 | AU73: =W73 -> 0 | AV73: =Z73 -> 0 | AW73: =AC73 -> 0 | AX73: =AF73 -> 0 | AY73: =AI73 -> 0 | AZ73: =AL73 -> 0
A74: ค่าเสื่อมราคา - ส่วนต่อเติมตกแต่ง | B74: 0.1 | E74: =((D74*$B74)/12)+'บริหารโดยส่วนกลาง (ไม่ต้องกรอก)'!E29 -> 0 | H74: =((G74*$B74)/12)+'บริหารโดยส่วนกลาง (ไม่ต้องกรอก)'!H29+E74 -> 0 | K74: =((J74*$B74)/12)+'บริหารโดยส่วนกลาง (ไม่ต้องกรอก)'!K29+H74 -> 0 | N74: =((M74*$B74)/12)+'บริหารโดยส่วนกลาง (ไม่ต้องกรอก)'!N29+K74 -> 0 | Q74: =((P74*$B74)/12)+'บริหารโดยส่วนกลาง (ไม่ต้องกรอก)'!Q29+N74 -> 0 | T74: =((S74*$B74)/12)+'บริหารโดยส่วนกลาง (ไม่ต้องกรอก)'!T29+Q74 -> 0 | W74: =((V74*$B74)/12)+'บริหารโดยส่วนกลาง (ไม่ต้องกรอก)'!W29+T74 -> 0 | Z74: =((Y74*$B74)/12)+'บริหารโดยส่วนกลาง (ไม่ต้องกรอก)'!Z29+W74 -> 0 | AC74: =((AB74*$B74)/12)+'บริหารโดยส่วนกลาง (ไม่ต้องกรอก)'!AC29+Z74 -> 0 | AF74: =((AE74*$B74)/12)+'บริหารโดยส่วนกลาง (ไม่ต้องกรอก)'!AF29+AC74 -> 0 | AI74: =((AH74*$B74)/12)+'บริหารโดยส่วนกลาง (ไม่ต้องกรอก)'!AI29+AF74 -> 0 | AL74: =((AK74*$B74)/12)+'บริหารโดยส่วนกลาง (ไม่ต้องกรอก)'!AL29+AI74 -> 0 | AM74: =SUM(D74,G74,J74,M74,P74,S74,V74,Y74,AB74,AE74,AH74,AK74) -> 0 | AO74: =E74 -> 0 | AP74: =H74 -> 0 | AQ74: =K74 -> 0 | AR74: =N74 -> 0 | AS74: =Q74 -> 0 | AT74: =T74 -> 0 | AU74: =W74 -> 0 | AV74: =Z74 -> 0 | AW74: =AC74 -> 0 | AX74: =AF74 -> 0 | AY74: =AI74 -> 0 | AZ74: =AL74 -> 0
A75: ค่าเสื่อมราคา - ต้นทุนค่ารื้อถอน | B75: 0.05 | E75: =((D75*$B75)/12)+'บริหารโดยส่วนกลาง (ไม่ต้องกรอก)'!E30 -> 0 | H75: =((G75*$B75)/12)+'บริหารโดยส่วนกลาง (ไม่ต้องกรอก)'!H30+E75 -> 0 | K75: =((J75*$B75)/12)+'บริหารโดยส่วนกลาง (ไม่ต้องกรอก)'!K30+H75 -> 0 | N75: =((M75*$B75)/12)+'บริหารโดยส่วนกลาง (ไม่ต้องกรอก)'!N30+K75 -> 0 | Q75: =((P75*$B75)/12)+'บริหารโดยส่วนกลาง (ไม่ต้องกรอก)'!Q30+N75 -> 0 | T75: =((S75*$B75)/12)+'บริหารโดยส่วนกลาง (ไม่ต้องกรอก)'!T30+Q75 -> 0 | W75: =((V75*$B75)/12)+'บริหารโดยส่วนกลาง (ไม่ต้องกรอก)'!W30+T75 -> 0 | Z75: =((Y75*$B75)/12)+'บริหารโดยส่วนกลาง (ไม่ต้องกรอก)'!Z30+W75 -> 0 | AC75: =((AB75*$B75)/12)+'บริหารโดยส่วนกลาง (ไม่ต้องกรอก)'!AC30+Z75 -> 0 | AF75: =((AE75*$B75)/12)+'บริหารโดยส่วนกลาง (ไม่ต้องกรอก)'!AF30+AC75 -> 0 | AI75: =((AH75*$B75)/12)+'บริหารโดยส่วนกลาง (ไม่ต้องกรอก)'!AI30+AF75 -> 0 | AL75: =((AK75*$B75)/12)+'บริหารโดยส่วนกลาง (ไม่ต้องกรอก)'!AL30+AI75 -> 0 | AM75: =SUM(D75,G75,J75,M75,P75,S75,V75,Y75,AB75,AE75,AH75,AK75) -> 0 | AO75: =E75 -> 0 | AP75: =H75 -> 0 | AQ75: =K75 -> 0 | AR75: =N75 -> 0 | AS75: =Q75 -> 0 | AT75: =T75 -> 0 | AU75: =W75 -> 0 | AV75: =Z75 -> 0 | AW75: =AC75 -> 0 | AX75: =AF75 -> 0 | AY75: =AI75 -> 0 | AZ75: =AL75 -> 0
A76: ค่าเสื่อมราคา - เครื่องมือเครื่องใช้ | B76: 0.2 | D76: =เครื่องมือเครื่องใช้!E51 -> 0 | E76: =((D76*$B76)/12)+'บริหารโดยส่วนกลาง (ไม่ต้องกรอก)'!E31 -> 0 | G76: =เครื่องมือเครื่องใช้!F51 -> 0 | H76: =((G76*$B76)/12)+'บริหารโดยส่วนกลาง (ไม่ต้องกรอก)'!H31+E76 -> 0 | J76: =เครื่องมือเครื่องใช้!G51 -> 0 | K76: =((J76*$B76)/12)+'บริหารโดยส่วนกลาง (ไม่ต้องกรอก)'!K31+H76 -> 0 | M76: =เครื่องมือเครื่องใช้!H51 -> 0 | N76: =((M76*$B76)/12)+'บริหารโดยส่วนกลาง (ไม่ต้องกรอก)'!N31+K76 -> 0 | P76: =เครื่องมือเครื่องใช้!I51 -> 0 | Q76: =((P76*$B76)/12)+'บริหารโดยส่วนกลาง (ไม่ต้องกรอก)'!Q31+N76 -> 0 | S76: =เครื่องมือเครื่องใช้!J51 -> 0 | T76: =((S76*$B76)/12)+'บริหารโดยส่วนกลาง (ไม่ต้องกรอก)'!T31+Q76 -> 0 | V76: =เครื่องมือเครื่องใช้!K51 -> 0 | W76: =((V76*$B76)/12)+'บริหารโดยส่วนกลาง (ไม่ต้องกรอก)'!W31+T76 -> 0 | Y76: =เครื่องมือเครื่องใช้!L51 -> 0 | Z76: =((Y76*$B76)/12)+'บริหารโดยส่วนกลาง (ไม่ต้องกรอก)'!Z31+W76 -> 0 | AB76: =เครื่องมือเครื่องใช้!M51 -> 0 | AC76: =((AB76*$B76)/12)+'บริหารโดยส่วนกลาง (ไม่ต้องกรอก)'!AC31+Z76 -> 0 | AE76: =เครื่องมือเครื่องใช้!N51 -> 0 | AF76: =((AE76*$B76)/12)+'บริหารโดยส่วนกลาง (ไม่ต้องกรอก)'!AF31+AC76 -> 0 | AH76: =เครื่องมือเครื่องใช้!O51 -> 0 | AI76: =((AH76*$B76)/12)+'บริหารโดยส่วนกลาง (ไม่ต้องกรอก)'!AI31+AF76 -> 0 | AK76: =เครื่องมือเครื่องใช้!P51 -> 0 | AL76: =((AK76*$B76)/12)+'บริหารโดยส่วนกลาง (ไม่ต้องกรอก)'!AL31+AI76 -> 0 | AM76: =SUM(D76,G76,J76,M76,P76,S76,V76,Y76,AB76,AE76,AH76,AK76) -> 0 | AO76: =E76 -> 0 | AP76: =H76 -> 0 | AQ76: =K76 -> 0 | AR76: =N76 -> 0 | AS76: =Q76 -> 0 | AT76: =T76 -> 0 | AU76: =W76 -> 0 | AV76: =Z76 -> 0 | AW76: =AC76 -> 0 | AX76: =AF76 -> 0 | AY76: =AI76 -> 0 | AZ76: =AL76 -> 0
A77: ค่าเสื่อมราคา - เฟอร์นิเจอร์ & เครื่องใช้สำนักงาน | B77: 0.2 | D77: =เฟอร์นิเจอร์!E51 -> 0 | E77: =((D77*$B77)/12)+'บริหารโดยส่วนกลาง (ไม่ต้องกรอก)'!E32 -> 0 | G77: =เฟอร์นิเจอร์!F51 -> 0 | H77: =((G77*$B77)/12)+'บริหารโดยส่วนกลาง (ไม่ต้องกรอก)'!H32+E77 -> 0 | J77: =เฟอร์นิเจอร์!G51 -> 0 | K77: =((J77*$B77)/12)+'บริหารโดยส่วนกลาง (ไม่ต้องกรอก)'!K32+H77 -> 0 | M77: =เฟอร์นิเจอร์!H51 -> 0 | N77: =((M77*$B77)/12)+'บริหารโดยส่วนกลาง (ไม่ต้องกรอก)'!N32+K77 -> 0 | P77: =เฟอร์นิเจอร์!I51 -> 0 | Q77: =((P77*$B77)/12)+'บริหารโดยส่วนกลาง (ไม่ต้องกรอก)'!Q32+N77 -> 0 | S77: =เฟอร์นิเจอร์!J51 -> 0 | T77: =((S77*$B77)/12)+'บริหารโดยส่วนกลาง (ไม่ต้องกรอก)'!T32+Q77 -> 0 | V77: =เฟอร์นิเจอร์!K51 -> 0 | W77: =((V77*$B77)/12)+'บริหารโดยส่วนกลาง (ไม่ต้องกรอก)'!W32+T77 -> 0 | Y77: =เฟอร์นิเจอร์!L51 -> 0 | Z77: =((Y77*$B77)/12)+'บริหารโดยส่วนกลาง (ไม่ต้องกรอก)'!Z32+W77 -> 0 | AB77: =เฟอร์นิเจอร์!M51 -> 0 | AC77: =((AB77*$B77)/12)+'บริหารโดยส่วนกลาง (ไม่ต้องกรอก)'!AC32+Z77 -> 0 | AE77: =เฟอร์นิเจอร์!N51 -> 0 | AF77: =((AE77*$B77)/12)+'บริหารโดยส่วนกลาง (ไม่ต้องกรอก)'!AF32+AC77 -> 0 | AH77: =เฟอร์นิเจอร์!O51 -> 0 | AI77: =((AH77*$B77)/12)+'บริหารโดยส่วนกลาง (ไม่ต้องกรอก)'!AI32+AF77 -> 0 | AK77: =เฟอร์นิเจอร์!P51 -> 0 | AL77: =((AK77*$B77)/12)+'บริหารโดยส่วนกลาง (ไม่ต้องกรอก)'!AL32+AI77 -> 0 | AM77: =SUM(D77,G77,J77,M77,P77,S77,V77,Y77,AB77,AE77,AH77,AK77) -> 0 | AO77: =E77 -> 0 | AP77: =H77 -> 0 | AQ77: =K77 -> 0 | AR77: =N77 -> 0 | AS77: =Q77 -> 0 | AT77: =T77 -> 0 | AU77: =W77 -> 0 | AV77: =Z77 -> 0 | AW77: =AC77 -> 0 | AX77: =AF77 -> 0 | AY77: =AI77 -> 0 | AZ77: =AL77 -> 0
A78: ค่าเสื่อมราคา - ยานพาหนะ | B78: 0.2 | E78: =((D78*$B78)/12)+'บริหารโดยส่วนกลาง (ไม่ต้องกรอก)'!E33 -> 0 | H78: =((G78*$B78)/12)+'บริหารโดยส่วนกลาง (ไม่ต้องกรอก)'!H33+E78 -> 0 | K78: =((J78*$B78)/12)+'บริหารโดยส่วนกลาง (ไม่ต้องกรอก)'!K33+H78 -> 0 | N78: =((M78*$B78)/12)+'บริหารโดยส่วนกลาง (ไม่ต้องกรอก)'!N33+K78 -> 0 | Q78: =((P78*$B78)/12)+'บริหารโดยส่วนกลาง (ไม่ต้องกรอก)'!Q33+N78 -> 0 | T78: =((S78*$B78)/12)+'บริหารโดยส่วนกลาง (ไม่ต้องกรอก)'!T33+Q78 -> 0 | W78: =((V78*$B78)/12)+'บริหารโดยส่วนกลาง (ไม่ต้องกรอก)'!W33+T78 -> 0 | Z78: =((Y78*$B78)/12)+'บริหารโดยส่วนกลาง (ไม่ต้องกรอก)'!Z33+W78 -> 0 | AC78: =((AB78*$B78)/12)+'บริหารโดยส่วนกลาง (ไม่ต้องกรอก)'!AC33+Z78 -> 0 | AF78: =((AE78*$B78)/12)+'บริหารโดยส่วนกลาง (ไม่ต้องกรอก)'!AF33+AC78 -> 0 | AI78: =((AH78*$B78)/12)+'บริหารโดยส่วนกลาง (ไม่ต้องกรอก)'!AI33+AF78 -> 0 | AL78: =((AK78*$B78)/12)+'บริหารโดยส่วนกลาง (ไม่ต้องกรอก)'!AL33+AI78 -> 0 | AM78: =SUM(D78,G78,J78,M78,P78,S78,V78,Y78,AB78,AE78,AH78,AK78) -> 0 | AO78: =E78 -> 0 | AP78: =H78 -> 0 | AQ78: =K78 -> 0 | AR78: =N78 -> 0 | AS78: =Q78 -> 0 | AT78: =T78 -> 0 | AU78: =W78 -> 0 | AV78: =Z78 -> 0 | AW78: =AC78 -> 0 | AX78: =AF78 -> 0 | AY78: =AI78 -> 0 | AZ78: =AL78 -> 0
A79: ค่าเสื่อมราคา - อาคารและสิ่งปลูกสร้าง | B79: 0.2 | E79: =((D79*$B79)/12)+'บริหารโดยส่วนกลาง (ไม่ต้องกรอก)'!E34 -> 0 | H79: =((G79*$B79)/12)+'บริหารโดยส่วนกลาง (ไม่ต้องกรอก)'!H34+E79 -> 0 | K79: =((J79*$B79)/12)+'บริหารโดยส่วนกลาง (ไม่ต้องกรอก)'!K34+H79 -> 0 | N79: =((M79*$B79)/12)+'บริหารโดยส่วนกลาง (ไม่ต้องกรอก)'!N34+K79 -> 0 | Q79: =((P79*$B79)/12)+'บริหารโดยส่วนกลาง (ไม่ต้องกรอก)'!Q34+N79 -> 0 | T79: =((S79*$B79)/12)+'บริหารโดยส่วนกลาง (ไม่ต้องกรอก)'!T34+Q79 -> 0 | W79: =((V79*$B79)/12)+'บริหารโดยส่วนกลาง (ไม่ต้องกรอก)'!W34+T79 -> 0 | Z79: =((Y79*$B79)/12)+'บริหารโดยส่วนกลาง (ไม่ต้องกรอก)'!Z34+W79 -> 0 | AC79: =((AB79*$B79)/12)+'บริหารโดยส่วนกลาง (ไม่ต้องกรอก)'!AC34+Z79 -> 0 | AF79: =((AE79*$B79)/12)+'บริหารโดยส่วนกลาง (ไม่ต้องกรอก)'!AF34+AC79 -> 0 | AI79: =((AH79*$B79)/12)+'บริหารโดยส่วนกลาง (ไม่ต้องกรอก)'!AI34+AF79 -> 0 | AL79: =((AK79*$B79)/12)+'บริหารโดยส่วนกลาง (ไม่ต้องกรอก)'!AL34+AI79 -> 0 | AM79: =SUM(D79,G79,J79,M79,P79,S79,V79,Y79,AB79,AE79,AH79,AK79) -> 0 | AO79: =E79 -> 0 | AP79: =H79 -> 0 | AQ79: =K79 -> 0 | AR79: =N79 -> 0 | AS79: =Q79 -> 0 | AT79: =T79 -> 0 | AU79: =W79 -> 0 | AV79: =Z79 -> 0 | AW79: =AC79 -> 0 | AX79: =AF79 -> 0 | AY79: =AI79 -> 0 | AZ79: =AL79 -> 0
A80: สรุปค่าใช้จ่ายทั้งสิ้น | D80: =SUM(D12:D79) -> 0 | G80: =SUM(G12:G79) -> 0 | J80: =SUM(J12:J79) -> 0 | M80: =SUM(M12:M79) -> 0 | P80: =SUM(P12:P79) -> 0 | S80: =SUM(S12:S79) -> 0 | V80: =SUM(V12:V79) -> 0 | Y80: =SUM(Y12:Y79) -> 0 | AB80: =SUM(AB12:AB79) -> 0 | AE80: =SUM(AE12:AE79) -> 0 | AH80: =SUM(AH12:AH79) -> 0 | AK80: =SUM(AK12:AK79) -> 0 | AM80: =SUM(C80:AL80) -> 0 | AZ80: =AL80 -> 0
AK82: ค่าแรงงานเพิ่มขึ้น
AK83: ค่าบริการวิชาชีพแพทย์ | AM83: =AM14 -> 0
AK84: เงินเดือนและสวัสดิการพนักงาน | AM84: =SUM(AM20:AM27) -> 0
AK85: TOTAL | AM85: =SUM(AM83:AM84) -> 0
AK86: ค่าใช้จ่ายอื่น ๆ ที่เพิ่มขึ้น
AK87: วัสดุสิ้นเปลือง | AM87: =AM35+AM36+AM37 -> 0
AK88: ค่่าโฆษณาและส่งเสริมการขาย | AM88: =AM40+AM41+AM42 -> 0
AK89: ค่าซ่อมแซมและบำรุงรักษา | AM89: =AM44+AM45+AM46+AM47+AM48+AM49+AM50 -> 0
AK90: ค่าเช่า | AM90: =AM52+AM53+AM54 -> 0
AK91: ค่าใช้จ่ายในการเดินทาง | AM91: =AM56+AM57+AM58 -> 0
AK92: ค่าใช้จ่ายในการจัดสัมมนา | AM92: =AM17 -> 0
AK93: ค่าใช้จ่ายอื่น | AM93: =SUM(AM60:AM68) -> 0
AK94: TOTAL | AM94: =SUM(AM87:AM93) -> 0
AK95: เงินลงทุน
AK96: เครื่องมือแพทย์ | AM96: =AM18 -> 0
AK97: ค่าสิทธิการเช่าอาคารตัดจ่าย | AM97: =AM52 -> 0
AK98: ป้ายสำนักงาน | AM98: =AM70 -> 0
AK99: คอมพิวเตอร์ | AM99: =AM71 -> 0
AK100: ระบบ software | AM100: =AM72 -> 0
AK101: อาคารบนที่ดินเช่า | AM101: =AM73 -> 0
AK102: ส่วนต่อเติมตกแต่ง | AM102: =AM74 -> 0
...

Sheet สรุป
B2: บริษัท โรงพยาบาลสัตว์ทองหล่อ จำกัด สาขา:TN
B3: รายละเอียด | C3: ปี 2024 | E3: ปี 2025 | G3: ผลต่าง
C4: ยอด | D4: สัดส่วน | E4: ยอด | F4: สัดส่วน | G4: ยอด | H4: % การเปลี่ยน
B5: ='Budget ปี 2026'!B8 -> รายได้จากการขาย - OPD/IPD | C5: ='Budget ปี 2026'!E8 -> 0 | D5: ='Budget ปี 2026'!F8 -> #DIV/0! | E5: ='Budget ปี 2026'!U8 -> 0 | F5: ='Budget ปี 2026'!AH8 -> #DIV/0! | G5: =E5-C5 -> 0 | H5: =G5/C5 -> #DIV/0!
B6: ='Budget ปี 2026'!B9 -> รายได้จากการขาย - Grooming | C6: ='Budget ปี 2026'!E9 -> 0 | D6: ='Budget ปี 2026'!F9 -> #DIV/0! | E6: ='Budget ปี 2026'!U9 -> 0 | F6: ='Budget ปี 2026'!AH9 -> #DIV/0! | G6: =E6-C6 -> 0 | H6: =G6/C6 -> #DIV/0!
B7: ='Budget ปี 2026'!B10 -> รายได้จากการขาย - Petshop | C7: ='Budget ปี 2026'!E10 -> 0 | D7: ='Budget ปี 2026'!F10 -> #DIV/0! | E7: ='Budget ปี 2026'!U10 -> 0 | F7: ='Budget ปี 2026'!AH10 -> #DIV/0! | G7: =E7-C7 -> 0 | H7: =G7/C7 -> #DIV/0!
B8: ='Budget ปี 2026'!B11 -> รายได้จากการขาย - Swimming | C8: ='Budget ปี 2026'!E11 -> 0 | D8: ='Budget ปี 2026'!F11 -> #DIV/0! | E8: ='Budget ปี 2026'!U11 -> 0 | F8: ='Budget ปี 2026'!AH11 -> #DIV/0! | G8: =E8-C8 -> 0 | H8: =G8/C8 -> #DIV/0!
B9: ='Budget ปี 2026'!B12 -> รายได้จากการขาย - Pettaxi | C9: ='Budget ปี 2026'!E12 -> 0 | D9: ='Budget ปี 2026'!F12 -> #DIV/0! | E9: ='Budget ปี 2026'!U12 -> 0 | F9: ='Budget ปี 2026'!AH12 -> #DIV/0! | G9: =E9-C9 -> 0 | H9: =G9/C9 -> #DIV/0!
B10: ='Budget ปี 2026'!B13 -> รายได้จากการขาย - อื่นๆ | C10: ='Budget ปี 2026'!E13 -> 0 | D10: ='Budget ปี 2026'!F13 -> #DIV/0! | E10: ='Budget ปี 2026'!U13 -> 0 | F10: ='Budget ปี 2026'!AH13 -> #DIV/0! | G10: =E10-C10 -> 0 | H10: =G10/C10 -> #DIV/0!
B11: ='Budget ปี 2026'!B14 -> หัก รับคืน | C11: ='Budget ปี 2026'!E14 -> 0 | D11: ='Budget ปี 2026'!F14 -> #DIV/0! | E11: ='Budget ปี 2026'!U14 -> 0 | F11: ='Budget ปี 2026'!AH14 -> #DIV/0! | G11: =E11-C11 -> 0 | H11: =G11/C11 -> #DIV/0!
B12: ='Budget ปี 2026'!B15 -> หัก ส่วนลดจ่าย | C12: ='Budget ปี 2026'!E15 -> 0 | D12: ='Budget ปี 2026'!F15 -> #DIV/0! | E12: ='Budget ปี 2026'!U15 -> 0 | F12: ='Budget ปี 2026'!AH15 -> #DIV/0! | G12: =E12-C12 -> 0 | H12: =G12/C12 -> #DIV/0!
B13: ='Budget ปี 2026'!B16 -> รายได้อื่นๆ | C13: ='Budget ปี 2026'!E16 -> 0 | D13: ='Budget ปี 2026'!F16 -> #DIV/0! | E13: ='Budget ปี 2026'!U16 -> 0 | F13: ='Budget ปี 2026'!AH16 -> #DIV/0! | G13: =E13-C13 -> 0 | H13: =G13/C13 -> #DIV/0!
B14: รวมรายได้จาการขายและอื่นๆ | C14: ='Budget ปี 2026'!E18 -> 0 | D14: ='Budget ปี 2026'!F18 -> #DIV/0! | E14: ='Budget ปี 2026'!U18 -> 0 | F14: ='Budget ปี 2026'!AH18 -> #DIV/0! | G14: =E14-C14 -> 0 | H14: =G14/C14 -> #DIV/0!
B15: ='Budget ปี 2026'!B24 -> รวมต้นทุนขาย | C15: ='Budget ปี 2026'!E24 -> 0 | D15: ='Budget ปี 2026'!F24 -> #DIV/0! | E15: ='Budget ปี 2026'!U24 -> #DIV/0! | F15: ='Budget ปี 2026'!AH24 -> #DIV/0! | G15: =E15-C15 -> #DIV/0! | H15: =IFERROR(G15/C15,"") | I15: =F15<D15 -> #DIV/0!
B16: ='Budget ปี 2026'!B38 -> รวมค่าใช้จ่ายในการขาย | C16: ='Budget ปี 2026'!E38 -> 0 | D16: ='Budget ปี 2026'!F38 -> #DIV/0! | E16: ='Budget ปี 2026'!U38 -> #DIV/0! | F16: ='Budget ปี 2026'!AH38 -> #DIV/0! | G16: =E16-C16 -> #DIV/0! | H16: =IFERROR(G16/C16,"") | I16: =F16<D16 -> #DIV/0!
B17: ='Budget ปี 2026'!B41 -> รวมค่ายานพาหนะ | C17: ='Budget ปี 2026'!E41 -> 0 | D17: ='Budget ปี 2026'!F41 -> #DIV/0! | E17: ='Budget ปี 2026'!U41 -> #DIV/0! | F17: ='Budget ปี 2026'!AH41 -> #DIV/0! | G17: =E17-C17 -> #DIV/0! | H17: =IFERROR(G17/C17,"") | I17: =F17<D17 -> #DIV/0!
B18: ='Budget ปี 2026'!B42 -> รวมต้นทุนขายและค่าใช้จ่ายในการขาย | C18: ='Budget ปี 2026'!E42 -> 0 | D18: ='Budget ปี 2026'!F42 -> #DIV/0! | E18: ='Budget ปี 2026'!U42 -> #DIV/0! | F18: ='Budget ปี 2026'!AH42 -> #DIV/0! | G18: =E18-C18 -> #DIV/0! | H18: =IFERROR(G18/C18,"") | I18: =F18<D18 -> #DIV/0!
B19: ='Budget ปี 2026'!B63 -> รวมเงินเดือนและสวัสดิการพนักงาน | C19: ='Budget ปี 2026'!E63 -> 0 | D19: ='Budget ปี 2026'!F63 -> #DIV/0! | E19: ='Budget ปี 2026'!U63 -> #DIV/0! | F19: ='Budget ปี 2026'!AH63 -> #DIV/0! | G19: =E19-C19 -> #DIV/0! | H19: =IFERROR(G19/C19,"") | I19: =F19<D19 -> #DIV/0!
B20: ='Budget ปี 2026'!B68 -> รวมค่าอบรมสัมมนา | C20: ='Budget ปี 2026'!E68 -> 0 | D20: ='Budget ปี 2026'!F68 -> #DIV/0! | E20: ='Budget ปี 2026'!U68 -> 0 | F20: ='Budget ปี 2026'!AH68 -> #DIV/0! | G20: =E20-C20 -> 0 | H20: =IFERROR(G20/C20,"") | I20: =F20<D20 -> #DIV/0!
B21: ='Budget ปี 2026'!B74 -> รวม Professional Fees | C21: ='Budget ปี 2026'!E74 -> 0 | D21: ='Budget ปี 2026'!F74 -> #DIV/0! | E21: ='Budget ปี 2026'!U74 -> #DIV/0! | F21: ='Budget ปี 2026'!AH74 -> #DIV/0! | G21: =E21-C21 -> #DIV/0! | H21: =IFERROR(G21/C21,"") | I21: =F21<D21 -> #DIV/0!
B22: ='Budget ปี 2026'!B79 -> รวมค่าธรรมเนียม | C22: ='Budget ปี 2026'!E79 -> 0 | D22: ='Budget ปี 2026'!F79 -> #DIV/0! | E22: ='Budget ปี 2026'!U79 -> #DIV/0! | F22: ='Budget ปี 2026'!AH79 -> #DIV/0! | G22: =E22-C22 -> #DIV/0! | H22: =IFERROR(G22/C22,"") | I22: =F22<D22 -> #DIV/0!
A23: [ | B23: ='Budget ปี 2026'!B84 -> รวมวัสดุสิ้นเปลือง | C23: ='Budget ปี 2026'!E84 -> 0 | D23: ='Budget ปี 2026'!F84 -> #DIV/0! | E23: ='Budget ปี 2026'!U84 -> 0 | F23: ='Budget ปี 2026'!AH84 -> #DIV/0! | G23: =E23-C23 -> 0 | H23: =IFERROR(G23/C23,"") | I23: =F23<D23 -> #DIV/0!
B24: ='Budget ปี 2026'!B89 -> รวมค่าโฆษณาและส่งเสริมการขาย | C24: ='Budget ปี 2026'!E89 -> 0 | D24: ='Budget ปี 2026'!F89 -> #DIV/0! | E24: ='Budget ปี 2026'!U89 -> 0 | F24: ='Budget ปี 2026'!AH89 -> #DIV/0! | G24: =E24-C24 -> 0 | H24: =IFERROR(G24/C24,"") | I24: =F24<D24 -> #DIV/0!
B25: ='Budget ปี 2026'!B98 -> รวมค่าซ่อมแซมและค่าบำรุงรักษา | C25: ='Budget ปี 2026'!E98 -> 0 | D25: ='Budget ปี 2026'!F98 -> #DIV/0! | E25: ='Budget ปี 2026'!U98 -> #DIV/0! | F25: ='Budget ปี 2026'!AH98 -> #DIV/0! | G25: =E25-C25 -> #DIV/0! | H25: =IFERROR(G25/C25,"") | I25: =F25<D25 -> #DIV/0!
B26: ='Budget ปี 2026'!B111 -> รวมค่าสาธารณูปโภค | C26: ='Budget ปี 2026'!E111 -> 0 | D26: ='Budget ปี 2026'!F111 -> #DIV/0! | E26: ='Budget ปี 2026'!U111 -> #DIV/0! | F26: ='Budget ปี 2026'!AH111 -> #DIV/0! | G26: =E26-C26 -> #DIV/0! | H26: =IFERROR(G26/C26,"") | I26: =F26<D26 -> #DIV/0!
B27: ='Budget ปี 2026'!B116 -> รวมค่าเช่า | C27: ='Budget ปี 2026'!E116 -> 0 | D27: ='Budget ปี 2026'!F116 -> #DIV/0! | E27: ='Budget ปี 2026'!U116 -> #DIV/0! | F27: ='Budget ปี 2026'!AI116 -> 0 | G27: =E27-C27 -> #DIV/0! | H27: =IFERROR(G27/C27,"") | I27: =F27<D27 -> #DIV/0!
B28: ='Budget ปี 2026'!B121 -> รวมค่าใช้จ่ายในการเดินทาง | C28: ='Budget ปี 2026'!E121 -> 0 | D28: ='Budget ปี 2026'!F121 -> #DIV/0! | E28: ='Budget ปี 2026'!U121 -> #DIV/0! | F28: ='Budget ปี 2026'!AI121 -> 0 | G28: =E28-C28 -> #DIV/0! | H28: =IFERROR(G28/C28,"") | I28: =F28<D28 -> #DIV/0!
B29: ='Budget ปี 2026'!B132 -> รวมค่าใช้จ่ายอื่น | C29: ='Budget ปี 2026'!E132 -> 0 | D29: ='Budget ปี 2026'!F132 -> #DIV/0! | E29: ='Budget ปี 2026'!U132 -> #DIV/0! | F29: ='Budget ปี 2026'!AH132 -> #DIV/0! | G29: =E29-C29 -> #DIV/0! | H29: =IFERROR(G29/C29,"") | I29: =F29<D29 -> #DIV/0!
B30: ='Budget ปี 2026'!B141 -> รวมภาษี | C30: ='Budget ปี 2026'!E141 -> 0 | D30: ='Budget ปี 2026'!F141 -> #DIV/0! | E30: ='Budget ปี 2026'!U141 -> #DIV/0! | F30: ='Budget ปี 2026'!AI141 -> 0 | G30: =E30-C30 -> #DIV/0! | H30: =IFERROR(G30/C30,"") | I30: =F30<D30 -> #DIV/0!
B31: ='Budget ปี 2026'!B146 -> รวมค่าใช้จ่ายตัดบัญชี | C31: ='Budget ปี 2026'!E146 -> 0 | D31: ='Budget ปี 2026'!F146 -> #DIV/0! | E31: ='Budget ปี 2026'!U146 -> #DIV/0! | F31: ='Budget ปี 2026'!AH146 -> #DIV/0! | G31: =E31-C31 -> #DIV/0! | H31: =IFERROR(G31/C31,"") | I31: =F31<D31 -> #DIV/0!
B32: ='Budget ปี 2026'!B147 -> รวมค่าใช้จ่ายในการบริหาร | C32: ='Budget ปี 2026'!E147 -> 0 | D32: ='Budget ปี 2026'!F147 -> #DIV/0! | E32: ='Budget ปี 2026'!U147 -> #DIV/0! | F32: ='Budget ปี 2026'!AH147 -> #DIV/0! | G32: =E32-C32 -> #DIV/0! | H32: =IFERROR(G32/C32,"") | I32: =F32<D32 -> #DIV/0!
B33: ='Budget ปี 2026'!B148 -> กำไร(ขาดทุน)ก่อนหักค่าเสื่อมราคา | C33: ='Budget ปี 2026'!E148 -> 0 | D33: ='Budget ปี 2026'!F148 -> #DIV/0! | E33: ='Budget ปี 2026'!U148 -> #DIV/0! | F33: ='Budget ปี 2026'!AH148 -> #DIV/0! | G33: =E33-C33 -> #DIV/0! | H33: =IFERROR(G33/C33,"") | I33: =F33<D33 -> #DIV/0!
B34: ='Budget ปี 2026'!B164 -> รวมค่าเสื่อมราคา | C34: ='Budget ปี 2026'!E164 -> 0 | D34: ='Budget ปี 2026'!F164 -> #DIV/0! | E34: ='Budget ปี 2026'!U164 -> 0 | F34: ='Budget ปี 2026'!AH164 -> #DIV/0! | G34: =E34-C34 -> 0 | H34: =IFERROR(G34/C34,"") | I34: =F34<D34 -> #DIV/0!
B35: ='Budget ปี 2026'!B168 -> รวม Asset Movement | C35: ='Budget ปี 2026'!E168 -> 0 | D35: ='Budget ปี 2026'!F168 -> #DIV/0! | E35: ='Budget ปี 2026'!U168 -> #DIV/0! | F35: ='Budget ปี 2026'!AH168 -> #DIV/0! | G35: =E35-C35 -> #DIV/0! | H35: =IFERROR(G35/C35,"") | I35: =F35<D35 -> #DIV/0!
B36: ='Budget ปี 2026'!B169 -> กำไร (ขาดทุน)ก่อนหัก Back Office | C36: ='Budget ปี 2026'!E169 -> 0 | D36: ='Budget ปี 2026'!F169 -> #DIV/0! | E36: ='Budget ปี 2026'!U169 -> #DIV/0! | F36: ='Budget ปี 2026'!AH169 -> #DIV/0! | G36: =E36-C36 -> #DIV/0! | H36: =G36/C36 -> #DIV/0! | I36: จะดูการเปลี่ยนแปลงตรงนี้เป็นผลงาน BU
B37: ='Budget ปี 2026'!B173 -> รวมค่าใช้จ่ายระหว่างกัน | C37: ='Budget ปี 2026'!E174 -> 0 | D37: ='Budget ปี 2026'!F174 -> #DIV/0! | E37: ='Budget ปี 2026'!U174 -> #DIV/0! | F37: ='Budget ปี 2026'!AH174 -> #DIV/0! | G37: =E37-C37 -> #DIV/0! | H37: =G37/C37 -> #DIV/0!
B38: ='Budget ปี 2026'!B174 -> กำไร (ขาดทุน)ก่อนดอกเบี้ยและภาษี | C38: ='Budget ปี 2026'!E174 -> 0 | D38: ='Budget ปี 2026'!F174 -> #DIV/0! | E38: ='Budget ปี 2026'!U174 -> #DIV/0! | F38: ='Budget ปี 2026'!AH174 -> #DIV/0! | G38: =E38-C38 -> #DIV/0! | H38: =G38/C38 -> #DIV/0!
B39: ='Budget ปี 2026'!B183 -> รวมดอกเบี้ยธนาคาร | C39: ='Budget ปี 2026'!E183 -> 0 | D39: ='Budget ปี 2026'!F183 -> #DIV/0! | E39: ='Budget ปี 2026'!U183 -> 0 | F39: ='Budget ปี 2026'!AH183 -> #DIV/0! | G39: =E39-C39 -> 0 | H39: =G39/C39 -> #DIV/0!
B40: ='Budget ปี 2026'!B185 -> ภาษีเงินได้นิติบุคคล | C40: ='Budget ปี 2026'!E185 -> 0 | D40: ='Budget ปี 2026'!F185 -> #DIV/0! | E40: ='Budget ปี 2026'!U185 -> #DIV/0! | F40: ='Budget ปี 2026'!AH185 -> #DIV/0! | G40: =E40-C40 -> #DIV/0! | H40: =G40/C40 -> #DIV/0!
B41: ='Budget ปี 2026'!B186 -> กำไร (ขาดทุน) สุทธิ | C41: ='Budget ปี 2026'!E186 -> 0 | D41: ='Budget ปี 2026'!F186 -> #DIV/0! | E41: ='Budget ปี 2026'!U186 -> #DIV/0! | F41: ='Budget ปี 2026'!AH186 -> #DIV/0! | G41: =E41-C41 -> #DIV/0! | H41: =G41/C41 -> #DIV/0!

Sheet กำลัง VET
B2: ลำดับ | C2: ตำแหน่ง | D2: เงินเดือน | E2: จำนวนคนใหม่
E3: Jan | F3: Feb | G3: Mar | H3: Apr | I3: May | J3: Jun | K3: Jul | L3: Aug | M3: Sep | N3: Oct | O3: Nov | P3: Dec | Q3: รวม
B4: 1 | D4: =IFERROR(VLOOKUP(C4,$C$37:$D$143,2,0),0) -> 0 | Q4: =SUM(E4:P4) -> 0 | R4: ขอสัปดาห์ละ 2 วันขอเป็นอาจารย์หมอ
B5: 2 | D5: =IFERROR(VLOOKUP(C5,$C$37:$D$143,2,0),0) -> 0 | Q5: =SUM(E5:P5) -> 0 | R5: ขอทดแทนจำนวนที่ขาด (ปี67 หาหมอมาเติมไม่ครบ)
B6: 3 | D6: =IFERROR(VLOOKUP(C6,$C$37:$D$143,2,0),0) -> 0 | Q6: =SUM(E6:P6) -> 0
B7: 4 | D7: =IFERROR(VLOOKUP(C7,$C$37:$D$143,2,0),0) -> 0 | Q7: =SUM(E7:P7) -> 0
B8: 5 | D8: =IFERROR(VLOOKUP(C8,$C$37:$D$143,2,0),0) -> 0 | Q8: =SUM(E8:P8) -> 0
B9: 6 | D9: =IFERROR(VLOOKUP(C9,$C$37:$D$143,2,0),0) -> 0 | Q9: =SUM(E9:P9) -> 0
B10: 7 | D10: =IFERROR(VLOOKUP(C10,$C$37:$D$143,2,0),0) -> 0 | Q10: =SUM(E10:P10) -> 0
B11: 8 | D11: =IFERROR(VLOOKUP(C11,$C$37:$D$143,2,0),0) -> 0 | Q11: =SUM(E11:P11) -> 0
B12: 9 | D12: =IFERROR(VLOOKUP(C12,$C$37:$D$143,2,0),0) -> 0 | Q12: =SUM(E12:P12) -> 0
B13: 10 | D13: =IFERROR(VLOOKUP(C13,$C$37:$D$143,2,0),0) -> 0 | Q13: =SUM(E13:P13) -> 0
C15: Total | E15: =SUM(E4:E14) -> 0 | F15: =SUM(F4:F14) -> 0 | G15: =SUM(G4:G14) -> 0 | H15: =SUM(H4:H14) -> 0 | I15: =SUM(I4:I14) -> 0 | J15: =SUM(J4:J14) -> 0 | K15: =SUM(K4:K14) -> 0 | L15: =SUM(L4:L14) -> 0 | ... Q15: =SUM(Q4:Q14) -> 0
C16: ถ้าเป็น Part time ให้กรอก 0.5 แทน 1
B17: ลำดับ | C17: ตำแหน่ง | D17: เงินเดือน | E17: งบประมาณ ด้านกำลังคน ใหม่
E18: Jan | F18: Feb | G18: Mar | H18: Apr | I18: May | J18: Jun | K18: Jul | L18: Aug | M18: Sep | N18: Oct | O18: Nov | P18: Dec | Q18: รวม
B19: 1 | C19: =C4 -> 0 | D19: =D4 -> 0 | E19: =$D19*E4 -> 0 | F19: =$D19*F4 -> 0 | G19: =$D19*G4 -> 0 | H19: =$D19*H4 -> 0 | I19: =$D19*I4 -> 0 | J19: =$D19*J4 -> 0 | K19: =$D19*K4 -> 0 | L19: =$D19*L4 -> 0 | ... P19: =$D19*P4 -> 0 | Q19: =SUM(E19:P19) -> 0
B20: 2 | C20: =C5 -> 0 | D20: =D5 -> 0 | E20: =$D20*E5 -> 0 | F20: =$D20*F5 -> 0 | G20: =$D20*G5 -> 0 | H20: =$D20*H5 -> 0 | I20: =$D20*I5 -> 0 | J20: =$D20*J5 -> 0 | K20: =$D20*K5 -> 0 | L20: =$D20*L5 -> 0 | ... P20: =$D20*P5 -> 0 | Q20: =SUM(E20:P20) -> 0
B21: 3 | C21: =C6 -> 0 | D21: =D6 -> 0 | E21: =$D21*E6 -> 0 | F21: =$D21*F6 -> 0 | G21: =$D21*G6 -> 0 | H21: =$D21*H6 -> 0 | I21: =$D21*I6 -> 0 | J21: =$D21*J6 -> 0 | K21: =$D21*K6 -> 0 | L21: =$D21*L6 -> 0 | ... P21: =$D21*P6 -> 0 | Q21: =SUM(E21:P21) -> 0
B22: 4 | C22: =C7 -> 0 | D22: =D7 -> 0 | E22: =$D22*E7 -> 0 | F22: =$D22*F7 -> 0 | G22: =$D22*G7 -> 0 | H22: =$D22*H7 -> 0 | I22: =$D22*I7 -> 0 | J22: =$D22*J7 -> 0 | K22: =$D22*K7 -> 0 | L22: =$D22*L7 -> 0 | ... P22: =$D22*P7 -> 0 | Q22: =SUM(E22:P22) -> 0
B23: 5 | C23: =C8 -> 0 | D23: =D8 -> 0 | E23: =$D23*E8 -> 0 | F23: =$D23*F8 -> 0 | G23: =$D23*G8 -> 0 | H23: =$D23*H8 -> 0 | I23: =$D23*I8 -> 0 | J23: =$D23*J8 -> 0 | K23: =$D23*K8 -> 0 | L23: =$D23*L8 -> 0 | ... P23: =$D23*P8 -> 0 | Q23: =SUM(E23:P23) -> 0
B24: 6 | C24: =C9 -> 0 | D24: =D9 -> 0 | E24: =$D24*E9 -> 0 | F24: =$D24*F9 -> 0 | G24: =$D24*G9 -> 0 | H24: =$D24*H9 -> 0 | I24: =$D24*I9 -> 0 | J24: =$D24*J9 -> 0 | K24: =$D24*K9 -> 0 | L24: =$D24*L9 -> 0 | ... P24: =$D24*P9 -> 0 | Q24: =SUM(E24:P24) -> 0
B25: 7 | C25: =C10 -> 0 | D25: =D10 -> 0 | E25: =$D25*E10 -> 0 | F25: =$D25*F10 -> 0 | G25: =$D25*G10 -> 0 | H25: =$D25*H10 -> 0 | I25: =$D25*I10 -> 0 | J25: =$D25*J10 -> 0 | K25: =$D25*K10 -> 0 | L25: =$D25*L10 -> 0 | ... P25: =$D25*P10 -> 0 | Q25: =SUM(E25:P25) -> 0
B26: 8 | C26: =C11 -> 0 | D26: =D11 -> 0 | E26: =$D26*E11 -> 0 | F26: =$D26*F11 -> 0 | G26: =$D26*G11 -> 0 | H26: =$D26*H11 -> 0 | I26: =$D26*I11 -> 0 | J26: =$D26*J11 -> 0 | K26: =$D26*K11 -> 0 | L26: =$D26*L11 -> 0 | ... P26: =$D26*P11 -> 0 | Q26: =SUM(E26:P26) -> 0
B27: 9 | C27: =C12 -> 0 | D27: =D12 -> 0 | E27: =$D27*E12 -> 0 | F27: =$D27*F12 -> 0 | G27: =$D27*G12 -> 0 | H27: =$D27*H12 -> 0 | I27: =$D27*I12 -> 0 | J27: =$D27*J12 -> 0 | K27: =$D27*K12 -> 0 | L27: =$D27*L12 -> 0 | ... P27: =$D27*P12 -> 0 | Q27: =SUM(E27:P27) -> 0
B28: 10 | C28: =C13 -> 0 | D28: =D13 -> 0 | E28: =$D28*E13 -> 0 | F28: =$D28*F13 -> 0 | G28: =$D28*G13 -> 0 | H28: =$D28*H13 -> 0 | I28: =$D28*I13 -> 0 | J28: =$D28*J13 -> 0 | K28: =$D28*K13 -> 0 | L28: =$D28*L13 -> 0 | ... P28: =$D28*P13 -> 0 | Q28: =SUM(E28:P28) -> 0
C30: Total | E30: =SUM(E19:E29) -> 0 | F30: =SUM(F19:F29) -> 0 | G30: =SUM(G19:G29) -> 0 | H30: =SUM(H19:H29) -> 0 | I30: =SUM(I19:I29) -> 0 | J30: =SUM(J19:J29) -> 0 | K30: =SUM(K19:K29) -> 0 | L30: =SUM(L19:L29) -> 0 | ... Q30: =SUM(Q19:Q29) -> 0
B35: โรงพยาบาลสัตว์ทองหล่อ ทองหล่อ | E35: Part-time (ครึ่งเวรแชร์กับ Hub&spoke)
B36: No. | C36: ตำแหน่งงาน (ไทย) | D36: เงินเดือน | E36: ค่าเวรโดยประมาน
B37: 1 | C37: สัตวแพทย์ทั่วไป | D37: 30000 | E37: =D37/2 -> 15000
B38: 2 | C38: สัตวแพทย์เฉพาะทาง - คลินิกผิวหนัง | D38: 45000 | E38: =D38/2 -> 22500
B39: 3 | C39: สัตวแพทย์เฉพาะทาง - คลินิกกายภาพ | D39: 45000 | E39: =D39/2 -> 22500
B40: 4 | C40: สัตวแพทย์เฉพาะทาง - คลินิกช่องปากและฟัน | D40: 45000 | E40: =D40/2 -> 22500
B41: 5 | C41: สัตวแพทย์เฉพาะทาง - คลินิกแมว | D41: 45000 | E41: =D41/2 -> 22500
B42: 6 | C42: สัตวแพทย์เฉพาะทาง - คลินิกสัตว์เลี้ยงพิเศษ | D42: 45000 | E42: =D42/2 -> 22500
B43: 7 | C43: สัตวแพทย์เฉพาะทาง - คลินิกโรคตา | D43: 45000 | E43: =D43/2 -> 22500
B44: 8 | C44: สัตวแพทย์เฉพาะทาง - คลินิกหัวใจ | D44: 45000 | E44: =D44/2 -> 22500
B45: 9 | C45: สัตวแพทย์เฉพาะทาง - อัลตราซาวด์ | D45: 45000 | E45: =D45/2 -> 22500
B46: 10 | C46: สัตวแพทย์เฉพาะทาง - ศัลยกรรมและวิสัญญี | D46: 45000 | E46: =D46/2 -> 22500
B47: 11 | C47: สัตวแพทย์เฉพาะทาง - ศูนย์ระบบประสาทและกระดูกสันหลัง | D47: 45000 | E47: =D47/2 -> 22500
B48: 12 | C48: สัตวแพทย์เฉพาะทาง - ศูนย์รักษาโรคอายุรกรรม | D48: 45000 | E48: =D48/2 -> 22500
B49: 13 | C49: สัตวแพทย์เฉพาะทาง - คลินิกเนื้องอกและมะเร็ง | D49: 45000 | E49: =D49/2 -> 22500
B50: 14
B51: 15

Sheet กำลังคนNON VET
B2: ลำดับ | C2: ตำแหน่ง | D2: เงินเดือน | E2: ค่าวัดระดับ/ค่าตำแหน่ง | F2: จำนวนคนใหม่
F3: Jan | G3: Feb | H3: Mar | I3: Apr | J3: May | K3: Jun | L3: Jul | M3: Aug | N3: Sep | O3: Oct | P3: Nov | Q3: Dec | R3: รวม
B4: 1 | D4: =IFERROR(VLOOKUP(C4,$C$80:$E$337,2,0),0) -> 0 | E4: =IFERROR(VLOOKUP(C4,$C$80:$E$337,3,0),0) -> 0 | R4: =SUM(F4:Q4) -> 0
B5: 2 | D5: =IFERROR(VLOOKUP(C5,$C$80:$E$337,2,0),0) -> 0 | E5: =IFERROR(VLOOKUP(C5,$C$80:$E$337,3,0),0) -> 0 | R5: =SUM(F5:Q5) -> 0
B6: 3 | D6: =IFERROR(VLOOKUP(C6,$C$80:$E$337,2,0),0) -> 0 | E6: =IFERROR(VLOOKUP(C6,$C$80:$E$337,3,0),0) -> 0 | R6: =SUM(F6:Q6) -> 0
B7: 4 | D7: =IFERROR(VLOOKUP(C7,$C$80:$E$337,2,0),0) -> 0 | E7: =IFERROR(VLOOKUP(C7,$C$80:$E$337,3,0),0) -> 0 | R7: =SUM(F7:Q7) -> 0
B8: 5 | D8: =IFERROR(VLOOKUP(C8,$C$80:$E$337,2,0),0) -> 0 | E8: =IFERROR(VLOOKUP(C8,$C$80:$E$337,3,0),0) -> 0 | R8: =SUM(F8:Q8) -> 0
B9: 6 | D9: =IFERROR(VLOOKUP(C9,$C$80:$E$337,2,0),0) -> 0 | E9: =IFERROR(VLOOKUP(C9,$C$80:$E$337,3,0),0) -> 0 | R9: =SUM(F9:Q9) -> 0
B10: 7 | D10: =IFERROR(VLOOKUP(C10,$C$80:$E$337,2,0),0) -> 0 | E10: =IFERROR(VLOOKUP(C10,$C$80:$E$337,3,0),0) -> 0 | R10: =SUM(F10:Q10) -> 0
B11: 8 | D11: =IFERROR(VLOOKUP(C11,$C$80:$E$337,2,0),0) -> 0 | E11: =IFERROR(VLOOKUP(C11,$C$80:$E$337,3,0),0) -> 0 | R11: =SUM(F11:Q11) -> 0
B12: 9 | D12: =IFERROR(VLOOKUP(C12,$C$80:$E$337,2,0),0) -> 0 | E12: =IFERROR(VLOOKUP(C12,$C$80:$E$337,3,0),0) -> 0 | R12: =SUM(F12:Q12) -> 0
B13: 10 | D13: =IFERROR(VLOOKUP(C13,$C$80:$E$337,2,0),0) -> 0 | E13: =IFERROR(VLOOKUP(C13,$C$80:$E$337,3,0),0) -> 0 | R13: =SUM(F13:Q13) -> 0
B14: 11 | D14: =IFERROR(VLOOKUP(C14,$C$80:$E$337,2,0),0) -> 0 | E14: =IFERROR(VLOOKUP(C14,$C$80:$E$337,3,0),0) -> 0 | R14: =SUM(F14:Q14) -> 0
B15: 12 | D15: =IFERROR(VLOOKUP(C15,$C$80:$E$337,2,0),0) -> 0 | E15: =IFERROR(VLOOKUP(C15,$C$80:$E$337,3,0),0) -> 0 | R15: =SUM(F15:Q15) -> 0
... B23: 20 | D23: =IFERROR(VLOOKUP(C23,$C$80:$E$337,2,0),0) -> 0 | E23: =IFERROR(VLOOKUP(C23,$C$80:$E$337,3,0),0) -> 0 | R23: =SUM(F23:Q23) -> 0
R24: =SUM(F24:Q24) -> 0
C25: Total | F25: =SUM(F4:F24) -> 0 | G25: =SUM(G4:G24) -> 0 | H25: =SUM(H4:H24) -> 0 | I25: =SUM(I4:I24) -> 0 | J25: =SUM(J4:J24) -> 0 | K25: =SUM(K4:K24) -> 0 | L25: =SUM(L4:L24) -> 0 | M25: =SUM(M4:M24) -> 0 | ... R25: =SUM(R4:R24) -> 0
B27: ลำดับ | C27: ตำแหน่ง | D27: เงินเดือน | E27: ค่าวัดระดับ/ค่าตำแหน่ง | F27: งบประมาณ ด้านกำลังคน ใหม่
F28: Jan | G28: Feb | H28: Mar | I28: Apr | J28: May | K28: Jun | L28: Jul | M28: Aug | N28: Sep | O28: Oct | P28: Nov | Q28: Dec | R28: รวม
B29: 1 | C29: =C4 -> 0 | D29: =D4 -> 0 | F29: =$D29*F4 -> 0 | G29: =$D29*G4 -> 0 | H29: =$D29*H4 -> 0 | I29: =$D29*I4 -> 0 | J29: =$D29*J4 -> 0 | K29: =$D29*K4 -> 0 | L29: =$D29*L4 -> 0 | M29: =$D29*M4 -> 0 | ... Q29: =$D29*Q4 -> 0 | R29: =SUM(F29:Q29) -> 0
B30: 2 | C30: =C5 -> 0 | D30: =D5 -> 0 | F30: =$D30*F5 -> 0 | G30: =$D30*G5 -> 0 | H30: =$D30*H5 -> 0 | I30: =$D30*I5 -> 0 | J30: =$D30*J5 -> 0 | K30: =$D30*K5 -> 0 | L30: =$D30*L5 -> 0 | M30: =$D30*M5 -> 0 | ... Q30: =$D30*Q5 -> 0 | R30: =SUM(F30:Q30) -> 0
B31: 3 | C31: =C6 -> 0 | D31: =D6 -> 0 | F31: =$D31*F6 -> 0 | G31: =$D31*G6 -> 0 | H31: =$D31*H6 -> 0 | I31: =$D31*I6 -> 0 | J31: =$D31*J6 -> 0 | K31: =$D31*K6 -> 0 | L31: =$D31*L6 -> 0 | M31: =$D31*M6 -> 0 | ... Q31: =$D31*Q6 -> 0 | R31: =SUM(F31:Q31) -> 0
B32: 4 | C32: =C7 -> 0 | D32: =D7 -> 0 | F32: =$D32*F7 -> 0 | G32: =$D32*G7 -> 0 | H32: =$D32*H7 -> 0 | I32: =$D32*I7 -> 0 | J32: =$D32*J7 -> 0 | K32: =$D32*K7 -> 0 | L32: =$D32*L7 -> 0 | M32: =$D32*M7 -> 0 | ... Q32: =$D32*Q7 -> 0 | R32: =SUM(F32:Q32) -> 0
B33: 5 | C33: =C8 -> 0 | D33: =D8 -> 0 | F33: =$D33*F8 -> 0 | G33: =$D33*G8 -> 0 | H33: =$D33*H8 -> 0 | I33: =$D33*I8 -> 0 | J33: =$D33*J8 -> 0 | K33: =$D33*K8 -> 0 | L33: =$D33*L8 -> 0 | M33: =$D33*M8 -> 0 | ... Q33: =$D33*Q8 -> 0 | R33: =SUM(F33:Q33) -> 0
B34: 6 | C34: =C9 -> 0 | D34: =D9 -> 0 | F34: =$D34*F9 -> 0 | G34: =$D34*G9 -> 0 | H34: =$D34*H9 -> 0 | I34: =$D34*I9 -> 0 | J34: =$D34*J9 -> 0 | K34: =$D34*K9 -> 0 | L34: =$D34*L9 -> 0 | M34: =$D34*M9 -> 0 | ... Q34: =$D34*Q9 -> 0 | R34: =SUM(F34:Q34) -> 0
B35: 7 | C35: =C10 -> 0 | D35: =D10 -> 0 | F35: =$D35*F10 -> 0 | G35: =$D35*G10 -> 0 | H35: =$D35*H10 -> 0 | I35: =$D35*I10 -> 0 | J35: =$D35*J10 -> 0 | K35: =$D35*K10 -> 0 | L35: =$D35*L10 -> 0 | M35: =$D35*M10 -> 0 | ... Q35: =$D35*Q10 -> 0 | R35: =SUM(F35:Q35) -> 0
B36: 8 | C36: =C11 -> 0 | D36: =D11 -> 0 | F36: =$D36*F11 -> 0 | G36: =$D36*G11 -> 0 | H36: =$D36*H11 -> 0 | I36: =$D36*I11 -> 0 | J36: =$D36*J11 -> 0 | K36: =$D36*K11 -> 0 | L36: =$D36*L11 -> 0 | M36: =$D36*M11 -> 0 | ... Q36: =$D36*Q11 -> 0 | R36: =SUM(F36:Q36) -> 0
B37: 9 | C37: =C12 -> 0 | D37: =D12 -> 0 | F37: =$D37*F12 -> 0 | G37: =$D37*G12 -> 0 | H37: =$D37*H12 -> 0 | I37: =$D37*I12 -> 0 | J37: =$D37*J12 -> 0 | K37: =$D37*K12 -> 0 | L37: =$D37*L12 -> 0 | M37: =$D37*M12 -> 0 | ... Q37: =$D37*Q12 -> 0 | R37: =SUM(F37:Q37) -> 0
B38: 10 | C38: =C13 -> 0 | D38: =D13 -> 0 | F38: =$D38*F13 -> 0 | G38: =$D38*G13 -> 0 | H38: =$D38*H13 -> 0 | I38: =$D38*I13 -> 0 | J38: =$D38*J13 -> 0 | K38: =$D38*K13 -> 0 | L38: =$D38*L13 -> 0 | M38: =$D38*M13 -> 0 | ... Q38: =$D38*Q13 -> 0 | R38: =SUM(F38:Q38) -> 0
B39: 11 | C39: =C14 -> 0 | D39: =D14 -> 0 | F39: =$D39*F14 -> 0 | G39: =$D39*G14 -> 0 | H39: =$D39*H14 -> 0 | I39: =$D39*I14 -> 0 | J39: =$D39*J14 -> 0 | K39: =$D39*K14 -> 0 | L39: =$D39*L14 -> 0 | M39: =$D39*M14 -> 0 | ... Q39: =$D39*Q14 -> 0 | R39: =SUM(F39:Q39) -> 0
B40: 12 | C40: =C15 -> 0 | D40: =D15 -> 0 | F40: =$D40*F15 -> 0 | G40: =$D40*G15 -> 0 | H40: =$D40*H15 -> 0 | I40: =$D40*I15 -> 0 | J40: =$D40*J15 -> 0 | K40: =$D40*K15 -> 0 | L40: =$D40*L15 -> 0 | M40: =$D40*M15 -> 0 | ... Q40: =$D40*Q15 -> 0 | R40: =SUM(F40:Q40) -> 0
... B48: 20 | C48: =C23 -> 0 | D48: =D23 -> 0 | F48: =$D48*F23 -> 0 | G48: =$D48*G23 -> 0 | H48: =$D48*H23 -> 0 | I48: =$D48*I23 -> 0 | J48: =$D48*J23 -> 0 | K48: =$D48*K23 -> 0 | L48: =$D48*L23 -> 0 | M48: =$D48*M23 -> 0 | ... Q48: =$D48*Q23 -> 0 | R48: =SUM(F48:Q48) -> 0
C50: Total | F50: =SUM(F29:F49) -> 0 | G50: =SUM(G29:G49) -> 0 | H50: =SUM(H29:H49) -> 0 | I50: =SUM(I29:I49) -> 0 | J50: =SUM(J29:J49) -> 0 | K50: =SUM(K29:K49) -> 0 | L50: =SUM(L29:L49) -> 0 | M50: =SUM(M29:M49) -> 0 | ... R50: =SUM(R29:R49) -> 0
B52: ลำดับ | C52: ตำแหน่ง | D52: เงินเดือน | E52: ค่าวัดระดับ/ค่าตำแหน่ง | F52: งบประมาณ ด้านกำลังคน ใหม่
F53: Jan | G53: Feb | H53: Mar | I53: Apr | J53: May | K53: Jun | L53: Jul | M53: Aug | N53: Sep | O53: Oct | P53: Nov | Q53: Dec | R53: รวม
B54: 1 | C54: =C4 -> 0 | E54: =E4 -> 0 | F54: =$E54*F4 -> 0 | G54: =$E54*G4 -> 0 | H54: =$E54*H4 -> 0 | I54: =$E54*I4 -> 0 | J54: =$E54*J4 -> 0 | K54: =$E54*K4 -> 0 | L54: =$E54*L4 -> 0 | M54: =$E54*M4 -> 0 | ... Q54: =$E54*Q4 -> 0 | R54: =SUM(F54:Q54) -> 0
B55: 2 | C55: =C5 -> 0 | E55: =E5 -> 0 | F55: =$E55*F5 -> 0 | G55: =$E55*G5 -> 0 | H55: =$E55*H5 -> 0 | I55: =$E55*I5 -> 0 | J55: =$E55*J5 -> 0 | K55: =$E55*K5 -> 0 | L55: =$E55*L5 -> 0 | M55: =$E55*M5 -> 0 | ... Q55: =$E55*Q5 -> 0 | R55: =SUM(F55:Q55) -> 0
B56: 3 | C56: =C6 -> 0 | E56: =E6 -> 0 | F56: =$E56*F6 -> 0 | G56: =$E56*G6 -> 0 | H56: =$E56*H6 -> 0 | I56: =$E56*I6 -> 0 | J56: =$E56*J6 -> 0 | K56: =$E56*K6 -> 0 | L56: =$E56*L6 -> 0 | M56: =$E56*M6 -> 0 | ... Q56: =$E56*Q6 -> 0 | R56: =SUM(F56:Q56) -> 0
B57: 4 | C57: =C7 -> 0 | E57: =E7 -> 0 | F57: =$E57*F7 -> 0 | G57: =$E57*G7 -> 0 | H57: =$E57*H7 -> 0 | I57: =$E57*I7 -> 0 | J57: =$E57*J7 -> 0 | K57: =$E57*K7 -> 0 | L57: =$E57*L7 -> 0 | M57: =$E57*M7 -> 0 | ... Q57: =$E57*Q7 -> 0 | R57: =SUM(F57:Q57) -> 0
B58: 5 | C58: =C8 -> 0 | E58: =E8 -> 0 | F58: =$E58*F8 -> 0 | G58: =$E58*G8 -> 0 | H58: =$E58*H8 -> 0 | I58: =$E58*I8 -> 0 | J58: =$E58*J8 -> 0 | K58: =$E58*K8 -> 0 | L58: =$E58*L8 -> 0 | M58: =$E58*M8 -> 0 | ... Q58: =$E58*Q8 -> 0 | R58: =SUM(F58:Q58) -> 0
B59: 6 | C59: =C9 -> 0 | E59: =E9 -> 0 | F59: =$E59*F9 -> 0 | G59: =$E59*G9 -> 0 | H59: =$E59*H9 -> 0 | I59: =$E59*I9 -> 0 | J59: =$E59*J9 -> 0 | K59: =$E59*K9 -> 0 | L59: =$E59*L9 -> 0 | M59: =$E59*M9 -> 0 | ... Q59: =$E59*Q9 -> 0 | R59: =SUM(F59:Q59) -> 0
B60: 7 | C60: =C10 -> 0 | E60: =E10 -> 0 | F60: =$E60*F10 -> 0 | G60: =$E60*G10 -> 0 | H60: =$E60*H10 -> 0 | I60: =$E60*I10 -> 0 | J60: =$E60*J10 -> 0 | K60: =$E60*K10 -> 0 | L60: =$E60*L10 -> 0 | M60: =$E60*M10 -> 0 | ... Q60: =$E60*Q10 -> 0 | R60: =SUM(F60:Q60) -> 0
B61: 8 | C61: =C11 -> 0 | E61: =E11 -> 0 | F61: =$E61*F11 -> 0 | G61: =$E61*G11 -> 0 | H61: =$E61*H11 -> 0 | I61: =$E61*I11 -> 0 | J61: =$E61*J11 -> 0 | K61: =$E61*K11 -> 0 | L61: =$E61*L11 -> 0 | M61: =$E61*M11 -> 0 | ... Q61: =$E61*Q11 -> 0 | R61: =SUM(F61:Q61) -> 0
B62: 9 | C62: =C12 -> 0 | E62: =E12 -> 0 | F62: =$E62*F12 -> 0 | G62: =$E62*G12 -> 0 | H62: =$E62*H12 -> 0 | I62: =$E62*I12 -> 0 | J62: =$E62*J12 -> 0 | K62: =$E62*K12 -> 0 | L62: =$E62*L12 -> 0 | M62: =$E62*M12 -> 0 | ... Q62: =$E62*Q12 -> 0 | R62: =SUM(F62:Q62) -> 0
